Workbook
Name AcquisitionFee: 'Provided - CAP Acct. 1'!$H$114
Name AssetManagementFee: 'Provided - CAP Acct. 1'!$H$115
Name ClosingDate: 'Provided - CAP Acct. 1'!$H$18
Name CoInvestorEquityContributionPct: 'Provided - CAP Acct. 1'!$M$13
Name CommonEquityOBalance: 'Provided - CAP Acct. 1'!$L$11
Name CommonEquityWeight: 'Q1 - CAP Acct. 2'!$I$23
Name ConstLoanExtensionDate: 'Provided - CAP Acct. 1'!$R$17
Name ConstLoanExtensionDummy: 'Provided - CAP Acct. 1'!$R$16
Name ConstLoanExtensionFee: 'Provided - CAP Acct. 1'!$R$15
Name ConstLoanMaturity: 'Provided - CAP Acct. 1'!$Q$13
Name ConstLoanMaturityDate: 'Provided - CAP Acct. 1'!$R$13
Name ConstLoanOBalance: 'Provided - CAP Acct. 1'!$R$9
Name ConstLoanOFees: 'Provided - CAP Acct. 1'!$H$14
Name ConstLoanOriginationDate: 'Provided - CAP Acct. 1'!$R$12
Name ConstLoanSpread: 'Provided - CAP Acct. 1'!$R$11
Name ConstLoanType: 'Provided - CAP Acct. 1'!$R$14
Name Contingency: 'Provided - CAP Acct. 1'!$H$12
Name CumulEquityInvested: 'Provided - CAP Acct. 1'!A$56
Name DaysInMonth: 'Provided - CAP Acct. 1'!A$29
Name DaysOpen: Inputs!$F$8
Name DiscountRateHotel: Inputs!$C$13
Name DispositionFee: 'Provided - CAP Acct. 1'!$H$116
Name ExitDate: 'Provided - CAP Acct. 1'!$H$20
Name GraphVariable: Inputs!$B$35
Name GrossSaleProceedsHotel: Valuation!$G$20
Name GroupADR: Inputs!$F$14
Name GroupFBWeight: Inputs!$F$17
Name HardCost: 'Provided - CAP Acct. 1'!$H$11
Name HistOccupancy: Inputs!$F$9
Name HoldingDates: 'Provided - CAP Acct. 1'!$I$28:$CO$28
Name HoldingPeriod: Inputs!$C$12
Name HotelForecastTable: Inputs!$B$23:$H$32
Name InterestReserve: 'Provided - CAP Acct. 1'!$H$13
Name LandCost: 'Provided - CAP Acct. 1'!$H$9
Name MiscRate: Inputs!$F$18
Name NOI_Today: 'Provided - CAP Acct. 1'!A$38
Name NumberRooms: Inputs!$F$7
Name OccGroupWeight: Inputs!$F$11
Name OccTransientWeight: Inputs!$F$10
Name OpeningDate: 'Provided - CAP Acct. 1'!$H$19
Name PermanentLoanAmortization: 'Provided - CAP Acct. 1'!$V$14
Name PermanentLoanDebtServiceDummy: 'Provided - CAP Acct. 1'!A$108
Name PermanentLoanDSCR: 'Provided - CAP Acct. 1'!$V$11
Name PermanentLoanMaturityDate: 'Provided - CAP Acct. 1'!$V$17
Name PermanentLoanMortgageConstant: 'Provided - CAP Acct. 1'!$V$15
Name PermanentLoanNOI: 'Provided - CAP Acct. 1'!$V$10
Name PermanentLoanOBalance: 'Provided - CAP Acct. 1'!$V$9
Name PermanentLoanOriginationDate: 'Provided - CAP Acct. 1'!$V$16
Name PermanentLoanPoints: 'Provided - CAP Acct. 1'!$V$12
Name PermanentLoanPPMTDummy: 'Provided - CAP Acct. 1'!$V$19
Name PermanentLoanPPMTFee: 'Provided - CAP Acct. 1'!$V$18
Name PermanentLoanRate: 'Provided - CAP Acct. 1'!$V$13
Name PreferredEquityOBalance: 'Provided - CAP Acct. 1'!$R$19
Name PreferredEquityReturn_Case1: 'Provided - CAP Acct. 1'!$R$20
Name PreferredEquityReturn_Case2: 'Q1 - CAP Acct. 2'!$R$20
Name PreferredEquityWeight: 'Q1 - CAP Acct. 2'!$I$24
Name Probabilities: Scenario!$P$19:$P$21
Name ScenarioTable: Scenario!$B$19:$O$23
Name SellingCost: Inputs!$C$15
Name SoftCost: 'Provided - CAP Acct. 1'!$H$10

Sheet Instructions
B2: Exam 1
B3: Comparing Complex Deal Structures
B5: Instructions

Sheet Inputs
B2: =Instructions!B3 -> Comparing Complex Deal Structures
B4: Inputs - Income
B6: Building Name | C6: Hotel "Excel'sior" | D6: Hotel Assumptions
B7: Address | C7: Geeky Valley | D7: Number of Rooms | F7: 250
B8: City | C8: Brainville | D8: Days Open | F8: 365
B9: State | C9: CPU | D9: Historical Occupancy | F9: =C23 -> 0.7
D10: Transient | F10: 0.6
B11: Analysis Begin Date | C11: 44197 | D11: Group | F11: 0.4
B12: Holding Period | C12: 5 | D12: Average Rate (ADR) | F12: =SUMPRODUCT(F10:F11,F13:F14) -> 167
B13: Discount Rate - Hotel | C13: 0.1 | D13: Transient | F13: =C27 -> 185
B14: Terminal Cap Rate - Hotel | C14: =Scenario!Q9 -> 0.085 | D14: Group | F14: =C28 -> 140
B15: Selling Cost | C15: 0.03 | D15: F&B % of Room Rev | F15: =SUMPRODUCT(F10:F11,F16:F17) -> 0.36
D16: Transient | F16: 0.2
D17: Group | F17: 0.6
D18: Miscellaneous | F18: 0.04
B21: Hotel Forecast
C22: =YEAR(C11) -> 2021 | D22: =C22+1 -> 2022 | E22: =D22+1 -> 2023 | F22: =E22+1 -> 2024 | G22: =F22+1 -> 2025 | H22: =G22+1 -> 2026
B23: Occupancy | C23: =Scenario!E9 -> 0.7 | D23: =Scenario!F9 -> 0.75 | E23: =Scenario!G9 -> 0.79 | F23: =Scenario!H9 -> 0.81 | G23: =Scenario!I9 -> 0.79 | H23: =Scenario!J9 -> 0.8
B24: Transient Occupancy Weight | C24: 0.6 | D24: 0.65 | E24: 0.55 | F24: 0.4 | G24: 0.55 | H24: 0.7
B25: Group Occupancy Weight | C25: 0.4 | D25: 0.35 | E25: 0.45 | F25: 0.6 | G25: 0.45 | H25: 0.3
B26: ADR Overall | C26: 164 | D26: 167.25 | E26: 168.65 | F26: 170 | G26: 174.25 | H26: 183
B27: Transient ADR | C27: =Scenario!K9 -> 185 | D27: =Scenario!L9 -> 190 | E27: =Scenario!M9 -> 188 | F27: =Scenario!N9 -> 185 | G27: =Scenario!O9 -> 191 | H27: =Scenario!P9 -> 192
B28: Group ADR | C28: 140 | D28: 138 | E28: 145 | F28: 160 | G28: 155 | H28: 155
B29: FB % of Room Rev | C29: 0.36 | D29: 0.34 | E29: 0.38 | F29: 0.44 | G29: 0.38 | H29: 0.32
B30: Transient FB % of Room Rev | C30: 0.2 | D30: 0.2 | E30: 0.2 | F30: 0.2 | G30: 0.2 | H30: 0.2
B31: Group FB % of Room Rev | C31: 0.6 | D31: 0.6 | E31: 0.6 | F31: 0.6 | G31: 0.6 | H31: 0.6
B32: Inflation | C32: 0.02 | D32: 0.02 | E32: 0.02 | F32: 0.02 | G32: 0.02 | H32: 0.02
B34: Graph - Hotel | C34: =YEAR(C11) -> 2021 | D34: =C34+1 -> 2022 | E34: =D34+1 -> 2023 | F34: =E34+1 -> 2024 | G34: =F34+1 -> 2025 | H34: =G34+1 -> 2026
B35: Occupancy | C35: =VLOOKUP(GraphVariable,HotelForecastTable,MATCH(C22,$B$22:$H$22,0),0) -> 0.7 | D35: =VLOOKUP(GraphVariable,HotelForecastTable,MATCH(D22,$B$22:$H$22,0),0) -> 0.75 | E35: =VLOOKUP(GraphVariable,HotelForecastTable,MATCH(E22,$B$22:$H$22,0),0) -> 0.79 | F35: =VLOOKUP(GraphVariable,HotelForecastTable,MATCH(F22,$B$22:$H$22,0),0) -> 0.81 | G35: =VLOOKUP(GraphVariable,HotelForecastTable,MATCH(G22,$B$22:$H$22,0),0) -> 0.79 | H35: =VLOOKUP(GraphVariable,HotelForecastTable,MATCH(H22,$B$22:$H$22,0),0) -> 0.8
B36: REVPAR | C36: =C23*C26 -> 114.8 | D36: =D23*D26 -> 125.4375 | E36: =E23*E26 -> 133.2335 | F36: =F23*F26 -> 137.7 | G36: =G23*G26 -> 137.6575 | H36: =H23*H26 -> 146.4
B37: ="Hotel - "&GraphVariable -> Hotel - Occupancy
B55: Inputs - Operating Expenses
B57: Hotel Operating Expenses
C59: Historical | E59: Mix | H59: Credit
B60: DISTRIBUTED | C60: Dollar Amount | D60: % Rev | E60: PAR | F60: POR | G60: % of Rev | H60: PAR | I60: POR | J60: % Rev
B61: Rooms | C61: =NOI!C12*D61 -> 3200137.5 | D61: 0.3 | E61: 0.2 | F61: 0.2 | G61: 0.6 | H61: =$C61*E61/(NumberRooms*DaysOpen) -> 7.014 | I61: =C61*F61/(DaysOpen*NumberRooms*HistOccupancy) -> 10.02 | J61: =D61*G61 -> 0.18
B62: Total F&B | C62: =NOI!C26*D62 -> 2851380 | D62: 0.8 | E62: 0.2 | F62: 0 | G62: 0.8 | H62: =$C62*E62/(NumberRooms*DaysOpen) -> 6.2496 | I62: =C62*F62/(DaysOpen*NumberRooms*HistOccupancy) -> 0 | J62: =D62*G62 -> 0.64
B63: Miscellaneous | C63: =NOI!C29*D63 -> 298679.5 | D63: 0.7 | E63: 0.2 | F63: 0 | G63: 0.8 | H63: =$C63*E63/(NumberRooms*DaysOpen) -> 0.65464 | I63: =C63*F63/(DaysOpen*NumberRooms*HistOccupancy) -> 0 | J63: =D63*G63 -> 0.56
B64: * There are no distributed expenses for the commercial space
C66: Historical | E66: Mix | H66: Credit
B67: UNDISTRIBUTED | C67: Dollar Amount | D67: % Rev | E67: PAR | F67: POR | G67: % | H67: PAR | I67: POR | J67: % Rev
B68: Administrative & General | C68: =NOI!$C$33*Inputs!D68 -> 1465803.5 | D68: 0.1 | E68: 0.7 | F68: 0 | G68: 0.3 | H68: =$C68*E68/(NumberRooms*DaysOpen) -> 11.24452 | I68: =C68*F68/(DaysOpen*NumberRooms*HistOccupancy) -> 0 | J68: =D68*G68 -> 0.03
B69: Sales & Marketing | C69: =NOI!$C$33*Inputs!D69 -> 732901.75 | D69: 0.05 | E69: 0.35 | F69: 0.15 | G69: 0.5 | H69: =$C69*E69/(NumberRooms*DaysOpen) -> 2.81113 | I69: =C69*F69/(DaysOpen*NumberRooms*HistOccupancy) -> 1.7211 | J69: =D69*G69 -> 0.025
B70: Royalty Fees | C70: =NOI!$C$33*Inputs!D70 -> 0 | D70: 0 | E70: 0 | F70: 0 | G70: 1 | H70: =$C70*E70/(NumberRooms*DaysOpen) -> 0 | I70: =C70*F70/(DaysOpen*NumberRooms*HistOccupancy) -> 0 | J70: =D70*G70 -> 0
B71: Repairs & Maintenance | C71: =NOI!$C$33*Inputs!D71 -> 732901.75 | D71: 0.05 | E71: 0.45 | F71: 0 | G71: 0.55 | H71: =$C71*E71/(NumberRooms*DaysOpen) -> 3.61431 | I71: =C71*F71/(DaysOpen*NumberRooms*HistOccupancy) -> 0 | J71: =D71*G71 -> 0.0275
B72: Utilities | C72: =NOI!$C$33*Inputs!D72 -> 586321.4 | D72: 0.04 | E72: 0.25 | F72: 0.35 | G72: 0.4 | H72: =$C72*E72/(NumberRooms*DaysOpen) -> 1.60636 | I72: =C72*F72/(DaysOpen*NumberRooms*HistOccupancy) -> 3.21272 | J72: =D72*G72 -> 0.016
B73: Base Management Fee* (%EGI) | C73: =NOI!$C$33*Inputs!D73 -> 366450.88 | D73: 0.025 | E73: 0 | F73: 0 | G73: 1 | H73: =$C73*E73/(NumberRooms*DaysOpen) -> 0 | I73: =C73*F73/(DaysOpen*NumberRooms*HistOccupancy) -> 0 | J73: =D73*G73 -> 0.025
B74: Incentive Management Fee* | C74: =NOI!$C$33*Inputs!D74 -> 0 | D74: 0 | E74: 0 | F74: 0 | G74: 0 | H74: =$C74*E74/(NumberRooms*DaysOpen) -> 0 | I74: =C74*F74/(DaysOpen*NumberRooms*HistOccupancy) -> 0 | J74: =D74*G74 -> 0
B75: *Management contracts will be defined later this semester. Only base fees are included here.
B77: FIXED EXPENSES
B78: Real Estate & Property Taxes | C78: =NOI!$C$33*Inputs!D78 -> 586321.4 | D78: 0.04 | E78: 1 | F78: 0 | G78: 0 | H78: =$C78*E78/(NumberRooms*DaysOpen) -> 6.42544 | I78: =C78*F78/(DaysOpen*NumberRooms*HistOccupancy) -> 0 | J78: =D78*G78 -> 0
B79: Insurance | C79: =NOI!$C$33*Inputs!D79 -> 87948.21 | D79: 0.006 | E79: 1 | F79: 0 | G79: 0 | H79: =$C79*E79/(NumberRooms*DaysOpen) -> 0.963816 | I79: =C79*F79/(DaysOpen*NumberRooms*HistOccupancy) -> 0 | J79: =D79*G79 -> 0
B80: Rent | C80: =NOI!$C$33*Inputs!D80 -> 109935.26 | D80: 0.0075 | E80: 1 | F80: 0 | G80: 0 | H80: =$C80*E80/(NumberRooms*DaysOpen) -> 1.20477 | I80: =C80*F80/(DaysOpen*NumberRooms*HistOccupancy) -> 0 | J80: =D80*G80 -> 0
B82: CAPITAL EXPENDITURES
B83: FF&E Reserve | C83: =NOI!$C$33*Inputs!D83 -> 586321.4 | D83: 0.04 | E83: 0 | F83: 0 | G83: 1 | H83: =$C83*E83/(NumberRooms*DaysOpen) -> 0 | I83: =C83*F83/(DaysOpen*NumberRooms*HistOccupancy) -> 0 | J83: =D83*G83 -> 0.04
B85: Roof Repair (year 1) | C85: =NOI!$C$33*Inputs!D85 -> 0 | D85: 0 | E85: 1 | F85: 0 | G85: 0

Sheet Construction
B2: =Inputs!B2 -> Comparing Complex Deal Structures
B4: Input: Construction Schedule
B6: $ Amount | E6: Months | Q6: Months
D7: Total | E7: =Inputs!C11-1 -> 44196 | F7: =EOMONTH(E7,1) -> 44227 | G7: =EOMONTH(F7,1) -> 44255 | H7: =EOMONTH(G7,1) -> 44286 | I7: =EOMONTH(H7,1) -> 44316 | J7: =EOMONTH(I7,1) -> 44347 | K7: =EOMONTH(J7,1) -> 44377 | L7: =EOMONTH(K7,1) -> 44408 | M7: =EOMONTH(L7,1) -> 44439 | ... AC7: =EOMONTH(AB7,1) -> 44926
B9: Land / Acquisition | D9: ='Provided - CAP Acct. 1'!H9 -> 5000000 | E9: =$D9*E37 -> 5000000 | F9: =$D9*F37 -> 0 | G9: =$D9*G37 -> 0 | H9: =$D9*H37 -> 0 | I9: =$D9*I37 -> 0 | J9: =$D9*J37 -> 0 | K9: =$D9*K37 -> 0 | L9: =$D9*L37 -> 0 | ... AC9: =$D9*AC37 -> 0 | AD9: x
B10: Finance & Legal | D10: 300000 | E10: =$D10*E38 -> 300000 | F10: =$D10*F38 -> 0 | G10: =$D10*G38 -> 0 | H10: =$D10*H38 -> 0 | I10: =$D10*I38 -> 0 | J10: =$D10*J38 -> 0 | K10: =$D10*K38 -> 0 | L10: =$D10*L38 -> 0 | ... AC10: =$D10*AC38 -> 0 | AD10: x
B11: Development | D11: 500000 | E11: =$D11*E39 -> 71428.571 | F11: =$D11*F39 -> 17857.143 | G11: =$D11*G39 -> 17857.143 | H11: =$D11*H39 -> 17857.143 | I11: =$D11*I39 -> 17857.143 | J11: =$D11*J39 -> 17857.143 | K11: =$D11*K39 -> 17857.143 | L11: =$D11*L39 -> 17857.143 | ... AC11: =$D11*AC39 -> 17857.143 | AD11: x
B12: Design & Engineering | D12: 1700000 | E12: =$D12*E40 -> 1020000 | F12: =$D12*F40 -> 136000 | G12: =$D12*G40 -> 136000 | H12: =$D12*H40 -> 136000 | I12: =$D12*I40 -> 136000 | J12: =$D12*J40 -> 136000 | K12: =$D12*K40 -> 0 | L12: =$D12*L40 -> 0 | ... AC12: =$D12*AC40 -> 0 | AD12: x
B13: Permits & Fees | D13: 1300000 | E13: =$D13*E41 -> 1300000 | F13: =$D13*F41 -> 0 | G13: =$D13*G41 -> 0 | H13: =$D13*H41 -> 0 | I13: =$D13*I41 -> 0 | J13: =$D13*J41 -> 0 | K13: =$D13*K41 -> 0 | L13: =$D13*L41 -> 0 | ... AC13: =$D13*AC41 -> 0 | AD13: x
B14: FF&E (Hard Costs) | D14: 1800000 | E14: =$D14*E42 -> 0 | F14: =$D14*F42 -> 0 | G14: =$D14*G42 -> 0 | H14: =$D14*H42 -> 0 | I14: =$D14*I42 -> 0 | J14: =$D14*J42 -> 0 | K14: =$D14*K42 -> 0 | L14: =$D14*L42 -> 0 | ... AC14: =$D14*AC42 -> 0 | AD14: x
B15: Hard Costs | D15: =SUM(D16:D24) -> 15070000 | E15: =SUM(E16:E24) -> 183700 | F15: =SUM(F16:F24) -> 139700 | G15: =SUM(G16:G24) -> 139700 | H15: =SUM(H16:H24) -> 161700 | I15: =SUM(I16:I24) -> 145200 | J15: =SUM(J16:J24) -> 99000 | K15: =SUM(K16:K24) -> 411631.58 | ... AC15: =SUM(AC16:AC24) -> 992431.58 | AD15: x
B16: Pre-Construction Services | D16: 100000 | E16: =$D16*E44 -> 50000 | F16: =$D16*F44 -> 10000 | G16: =$D16*G44 -> 10000 | H16: =$D16*H44 -> 10000 | I16: =$D16*I44 -> 20000 | J16: =$D16*J44 -> 0 | K16: =$D16*K44 -> 0 | L16: =$D16*L44 -> 0 | ... AC16: =$D16*AC44 -> 0 | AD16: x
B17: Demolition/Remediation | D17: 400000 | E17: =$D17*E45 -> 72000 | F17: =$D17*F45 -> 72000 | G17: =$D17*G45 -> 72000 | H17: =$D17*H45 -> 72000 | I17: =$D17*I45 -> 112000 | J17: =$D17*J45 -> 0 | K17: =$D17*K45 -> 0 | L17: =$D17*L45 -> 0 | ... AC17: =$D17*AC45 -> 0 | AD17: x
B18: Tower Super Structure | D18: 6000000 | E18: =$D18*E46 -> 0 | F18: =$D18*F46 -> 0 | G18: =$D18*G46 -> 0 | H18: =$D18*H46 -> 0 | I18: =$D18*I46 -> 0 | J18: =$D18*J46 -> 0 | K18: =$D18*K46 -> 284210.53 | L18: =$D18*L46 -> 284210.53 | ... AC18: =$D18*AC46 -> 884210.53 | AD18: x
B19: B-1 Lobby & Functions | D19: 3600000 | E19: =$D19*E47 -> 0 | F19: =$D19*F47 -> 0 | G19: =$D19*G47 -> 0 | H19: =$D19*H47 -> 0 | I19: =$D19*I47 -> 0 | J19: =$D19*J47 -> 0 | K19: =$D19*K47 -> 0 | L19: =$D19*L47 -> 0 | ... AC19: =$D19*AC47 -> 0 | AD19: x
B20: Parking Garage | D20: 2300000 | E20: =$D20*E48 -> 0 | F20: =$D20*F48 -> 0 | G20: =$D20*G48 -> 0 | H20: =$D20*H48 -> 0 | I20: =$D20*I48 -> 0 | J20: =$D20*J48 -> 0 | K20: =$D20*K48 -> 0 | L20: =$D20*L48 -> 207000 | ... AC20: =$D20*AC48 -> 0 | AD20: x
B21: Site Utilities | D21: 1000000 | E21: =$D21*E49 -> 0 | F21: =$D21*F49 -> 0 | G21: =$D21*G49 -> 0 | H21: =$D21*H49 -> 0 | I21: =$D21*I49 -> 0 | J21: =$D21*J49 -> 90000 | K21: =$D21*K49 -> 90000 | L21: =$D21*L49 -> 90000 | ... AC21: =$D21*AC49 -> 0 | AD21: x
B22: Off Site / Street Improvements | D22: 100000 | E22: =$D22*E50 -> 0 | F22: =$D22*F50 -> 0 | G22: =$D22*G50 -> 0 | H22: =$D22*H50 -> 0 | I22: =$D22*I50 -> 0 | J22: =$D22*J50 -> 0 | K22: =$D22*K50 -> 0 | L22: =$D22*L50 -> 0 | ... AC22: =$D22*AC50 -> 18000 | AD22: x
B23: Adjacent Property Mitigation Measures | D23: 200000 | E23: =$D23*E51 -> 45000 | F23: =$D23*F51 -> 45000 | G23: =$D23*G51 -> 45000 | H23: =$D23*H51 -> 65000 | I23: =$D23*I51 -> 0 | J23: =$D23*J51 -> 0 | K23: =$D23*K51 -> 0 | L23: =$D23*L51 -> 0 | ... AC23: =$D23*AC51 -> 0 | AD23: x
B24: General Conditions and Fees | C24: 0.1 | D24: =SUM(D16:D23)*C24 -> 1370000 | E24: =SUM(E16:E23)*$C24 -> 16700 | F24: =SUM(F16:F23)*$C24 -> 12700 | G24: =SUM(G16:G23)*$C24 -> 12700 | H24: =SUM(H16:H23)*$C24 -> 14700 | I24: =SUM(I16:I23)*$C24 -> 13200 | J24: =SUM(J16:J23)*$C24 -> 9000 | K24: =SUM(K16:K23)*$C24 -> 37421.053 | L24: =SUM(L16:L23)*$C24 -> 58121.053 | ... AC24: =SUM(AC16:AC23)*$C24 -> 90221.053 | AD24: x
B25: OS&E - Technology | D25: 700000 | E25: =$D25*E53 -> 0 | F25: =$D25*F53 -> 0 | G25: =$D25*G53 -> 0 | H25: =$D25*H53 -> 0 | I25: =$D25*I53 -> 0 | J25: =$D25*J53 -> 0 | K25: =$D25*K53 -> 0 | L25: =$D25*L53 -> 0 | ... AC25: =$D25*AC53 -> 0 | AD25: x
B26: Pre-Opening - Working Capital | D26: 800000 | E26: =$D26*E54 -> 0 | F26: =$D26*F54 -> 0 | G26: =$D26*G54 -> 0 | H26: =$D26*H54 -> 0 | I26: =$D26*I54 -> 0 | J26: =$D26*J54 -> 0 | K26: =$D26*K54 -> 0 | L26: =$D26*L54 -> 0 | ... AC26: =$D26*AC54 -> 200000 | AD26: x
B27: Subtotal | D27: =SUM(D9:D15,D25:D26) -> 27170000 | E27: =SUM(E9:E15,E25:E26) -> 7875128.6 | F27: =SUM(F9:F15,F25:F26) -> 293557.14 | G27: =SUM(G9:G15,G25:G26) -> 293557.14 | H27: =SUM(H9:H15,H25:H26) -> 315557.14 | I27: =SUM(I9:I15,I25:I26) -> 299057.14 | J27: =SUM(J9:J15,J25:J26) -> 252857.14 | K27: =SUM(K9:K15,K25:K26) -> 429488.72 | ... AC27: =SUM(AC9:AC15,AC25:AC26) -> 1210288.7 | AD27: x
B29: Escalation | C29: 0.03 | D29: =C29*(D27-D9) -> 665100 | E29: =$C29*SUM(E10:E15,E25:E26) -> 86253.857 | F29: =$C29*SUM(F10:F15,F25:F26) -> 8806.7143 | G29: =$C29*SUM(G10:G15,G25:G26) -> 8806.7143 | H29: =$C29*SUM(H10:H15,H25:H26) -> 9466.7143 | I29: =$C29*SUM(I10:I15,I25:I26) -> 8971.7143 | J29: =$C29*SUM(J10:J15,J25:J26) -> 7585.7143 | K29: =$C29*SUM(K10:K15,K25:K26) -> 12884.662 | L29: =$C29*SUM(L10:L15,L25:L26) -> 19715.662 | ... AC29: =$C29*SUM(AC10:AC15,AC25:AC26) -> 36308.662 | AD29: x
B30: Project Contingency | C30: 0.03 | D30: =C30*(D27+D29-D9) -> 685053 | E30: =$C30*SUM(E10:E15,E25:E26,E29) -> 88841.473 | F30: =$C30*SUM(F10:F15,F25:F26,F29) -> 9070.9157 | G30: =$C30*SUM(G10:G15,G25:G26,G29) -> 9070.9157 | H30: =$C30*SUM(H10:H15,H25:H26,H29) -> 9750.7157 | I30: =$C30*SUM(I10:I15,I25:I26,I29) -> 9240.8657 | J30: =$C30*SUM(J10:J15,J25:J26,J29) -> 7813.2857 | K30: =$C30*SUM(K10:K15,K25:K26,K29) -> 13271.202 | L30: =$C30*SUM(L10:L15,L25:L26,L29) -> 20307.132 | ... AC30: =$C30*SUM(AC10:AC15,AC25:AC26,AC29) -> 37397.922 | AD30: x
B32: Total Costs | D32: =SUM(D27,D29:D30) -> 28520153 | E32: =SUM(E27,E29:E30) -> 8050223.9 | F32: =SUM(F27,F29:F30) -> 311434.77 | G32: =SUM(G27,G29:G30) -> 311434.77 | H32: =SUM(H27,H29:H30) -> 334774.57 | I32: =SUM(I27,I29:I30) -> 317269.72 | J32: =SUM(J27,J29:J30) -> 268256.14 | K32: =SUM(K27,K29:K30) -> 455644.58 | ... AC32: =SUM(AC27,AC29:AC30) -> 1283995.3
B34: % Allocation
E35: =E6 -> Months | Q35: =Q6 -> Months
D36: Total | E36: =E7 -> 44196 | F36: =F7 -> 44227 | G36: =G7 -> 44255 | H36: =H7 -> 44286 | I36: =I7 -> 44316 | J36: =J7 -> 44347 | K36: =K7 -> 44377 | L36: =L7 -> 44408 | ... AC36: =AC7 -> 44926 | AD36: x
B37: Land / Acquisition | D37: =SUM(E37:AC37) -> 1 | E37: 1 | AD37: x
B38: Finance & Legal | D38: =SUM(E38:AC38) -> 1 | E38: 1 | AD38: x
B39: Development | D39: =SUM(E39:AC39) -> 1 | E39: 0.14285714 | F39: =1/28 -> 0.035714286 | G39: =1/28 -> 0.035714286 | H39: =1/28 -> 0.035714286 | I39: =1/28 -> 0.035714286 | J39: =1/28 -> 0.035714286 | K39: =1/28 -> 0.035714286 | L39: =1/28 -> 0.035714286 | M39: =1/28 -> 0.035714286 | ... AC39: =1/28 -> 0.035714286 | AD39: x
B40: Design & Engineering | D40: =SUM(E40:AC40) -> 1 | E40: 0.6 | F40: 0.08 | G40: 0.08 | H40: 0.08 | I40: 0.08 | J40: 0.08 | AD40: x
B41: Permits & Fees | D41: =SUM(E41:AC41) -> 1 | E41: 1 | AD41: x
B42: FF&E (Hard Costs) | D42: =SUM(E42:AC42) -> 1 | V42: 0.2 | W42: 0.2 | X42: 0.2 | Y42: 0.2 | Z42: 0.2 | AD42: x
B43: Hard Costs
B44: Pre-Construction Services | D44: =SUM(E44:AC44) -> 1 | E44: 0.5 | F44: 0.1 | G44: 0.1 | H44: 0.1 | I44: 0.2 | AD44: x
B45: Demolition/Remediation | D45: =SUM(E45:AC45) -> 1 | E45: =90%/5 -> 0.18 | F45: =90%/5 -> 0.18 | G45: =90%/5 -> 0.18 | H45: =90%/5 -> 0.18 | I45: 0.28 | AD45: x
B46: Tower Super Structure | D46: =SUM(E46:AC46) -> 1 | K46: =0.9/19 -> 0.047368421 | L46: =0.9/19 -> 0.047368421 | M46: =0.9/19 -> 0.047368421 | N46: =0.9/19 -> 0.047368421 | O46: =0.9/19 -> 0.047368421 | P46: =0.9/19 -> 0.047368421 | Q46: =0.9/19 -> 0.047368421 | R46: =0.9/19 -> 0.047368421 | ... AB46: =0.9/19 -> 0.047368421 | AC46: 0.14736842 | AD46: x
B47: B-1 Lobby & Functions | D47: =SUM(E47:AC47) -> 1 | R47: =0.9/10 -> 0.09 | S47: =0.9/10 -> 0.09 | T47: =0.9/10 -> 0.09 | U47: =0.9/10 -> 0.09 | V47: =0.9/10 -> 0.09 | W47: =0.9/10 -> 0.09 | X47: =0.9/10 -> 0.09 | Y47: =0.9/10 -> 0.09 | Z47: =0.9/10 -> 0.09 | AA47: 0.19 | AD47: x
B48: Parking Garage | D48: =SUM(E48:AC48) -> 1 | L48: =0.9/10 -> 0.09 | M48: =0.9/10 -> 0.09 | N48: =0.9/10 -> 0.09 | O48: =0.9/10 -> 0.09 | P48: =0.9/10 -> 0.09 | Q48: =0.9/10 -> 0.09 | R48: =0.9/10 -> 0.09 | S48: =0.9/10 -> 0.09 | T48: =0.9/10 -> 0.09 | U48: 0.19 | AD48: x
B49: Site Utilities | D49: =SUM(E49:AC49) -> 1 | J49: =0.9/10 -> 0.09 | K49: =0.9/10 -> 0.09 | L49: =0.9/10 -> 0.09 | M49: =0.9/10 -> 0.09 | N49: =0.9/10 -> 0.09 | O49: =0.9/10 -> 0.09 | P49: =0.9/10 -> 0.09 | Q49: =0.9/10 -> 0.09 | R49: =0.9/10 -> 0.09 | S49: 0.19 | AD49: x
B50: Off Site / Street Improvements | D50: =SUM(E50:AC50) -> 1 | Y50: 0.28 | Z50: =0.9/5 -> 0.18 | AA50: =0.9/5 -> 0.18 | AB50: =0.9/5 -> 0.18 | AC50: =0.9/5 -> 0.18 | AD50: x
B51: Adjacent Property Mitigation Measures | D51: =SUM(E51:AC51) -> 1 | E51: =0.9/4 -> 0.225 | F51: =0.9/4 -> 0.225 | G51: =0.9/4 -> 0.225 | H51: =0.9/4+10% -> 0.325 | AD51: x
B52: GC & Fee
B53: OS&E - Technology | D53: =SUM(E53:AC53) -> 1 | V53: 0.2 | W53: 0.2 | X53: 0.2 | Y53: 0.2 | Z53: 0.2 | AD53: x
B54: Pre-Opening - Working Capital | D54: =SUM(E54:AC54) -> 1 | Z54: 0.25 | AA54: 0.25 | AB54: 0.25 | AC54: 0.25 | AD54: x

Sheet Libor
B2: =Inputs!B2 -> Comparing Complex Deal Structures
B4: Input: Forward Curves
B7: Forward Curves
C9: =Construction!E36 -> 44196 | D9: =EOMONTH(C9,1) -> 44227 | E9: =EOMONTH(D9,1) -> 44255 | F9: =EOMONTH(E9,1) -> 44286 | G9: =EOMONTH(F9,1) -> 44316 | H9: =EOMONTH(G9,1) -> 44347 | I9: =EOMONTH(H9,1) -> 44377 | J9: =EOMONTH(I9,1) -> 44408 | K9: =EOMONTH(J9,1) -> 44439 | ... DS9: =EOMONTH(DR9,1) -> 47848
B11: 1 Month USD LIBOR Forward Curve | C11: 0.0014925 | D11: 0.0015746 | E11: 0.0016548 | F11: 0.0017305 | G11: 0.001734 | H11: 0.0016393 | I11: 0.0014936 | J11: 0.0013758 | K11: 0.0013131 | L11: 0.0013266 | M11: 0.0013896 | N11: 0.0014629 | O11: 0.0015439 | P11: 0.0016185 | Q11: 0.0016576 | R11: 0.0016731 | S11: 0.0016505 | T11: 0.001572 | U11: 0.0014832 | V11: 0.0014183 | W11: 0.0013636 | X11: 0.0013674 | Y11: 0.001432 | Z11: 0.0015107 | AA11: 0.0016359 | AB11: 0.0017925 | AC11: 0.0019195 | AD11: 0.002075 | AE11: 0.0022303 | AF11: 0.0023571 | AG11: 0.0024913 | AH11: 0.0026353 | AI11: 0.0027579 | AJ11: 0.0028946 | AK11: 0.003043 | AL11: 0.0031805 | AM11: 0.0033303 | AN11: 0.0034998 | AO11: 0.0036478 | AP11: 0.0038258 | AQ11: 0.004018 | AR11: 0.0041911 | AS11: 0.0043829 | AT11: 0.0045864 | AU11: 0.0047821 | AV11: 0.0049875 | AW11: 0.0052026 | AX11: 0.0054099 | AY11: 0.0056248 | AZ11: 0.0058518 | BA11: 0.0060465 | BB11: 0.0062646 | BC11: 0.006485 | BD11: 0.0066765 | BE11: 0.0068779 | BF11: 0.007081 | BG11: 0.0072712 | BH11: 0.0074647 | BI11: 0.0076678 | BJ11: 0.0078446 | BK11: 0.0080317 | BL11: 0.0082283 | BM11: 0.0083824 | BN11: 0.0085734 | BO11: 0.0087551 | BP11: 0.0089056 | BQ11: 0.009063 | BR11: 0.0092272 | BS11: 0.0093634 | BT11: 0.009509 | BU11: 0.0096645 | BV11: 0.0097949 | BW11: 0.0099351 | BX11: 0.010087 | BY11: 0.0102117 | BZ11: 0.0103548 | CA11: 0.0105052 | CB11: 0.0106149 | CC11: 0.0107642 | CD11: 0.0109069 | CE11: 0.0110244 | CF11: 0.0111505 | CG11: 0.0112862 | CH11: 0.0113958 | CI11: 0.0115155 | CJ11: 0.0116474 | CK11: 0.0117483 | CL11: 0.0118728 | CM11: 0.0120014 | CN11: 0.0120994 | CO11: 0.0122048 | CP11: 0.0123179 | CQ11: 0.0124019 | CR11: 0.0124959 | CS11: 0.0125986 | CT11: 0.0126789 | CU11: 0.0127668 | CV11: 0.0128674 | CW11: 0.0129406 | CX11: 0.0130316 | CY11: 0.0131334 | CZ11: 0.0132106 | DA11: 0.0133028 | DB11: 0.0134077 | DC11: 0.0134955 | DD11: 0.0135942 | DE11: 0.0137042 | DF11: 0.0137959 | DG11: 0.0138951 | DH11: 0.0140044 | DI11: 0.0140822 | DJ11: 0.0141723 | DK11: 0.0142638 | DL11: 0.0143205 | DM11: 0.0143813 | DN11: 0.014445 | DO11: 0.0144799 | DP11: 0.0145181 | DQ11: 0.0145623 | DR11: 0.0145799 | DS11: 0.0146052
B12: 3 Month USD LIBOR Forward Curve | C12: 0.0021475 | D12: 0.0021992 | E12: 0.0022525 | F12: 0.0023009 | G12: 0.002192 | H12: 0.0020936 | I12: 0.0019847 | J12: 0.0019824 | K12: 0.0019799 | L12: 0.0019778 | M12: 0.0020345 | N12: 0.0020929 | O12: 0.0021459 | P12: 0.0022904 | Q12: 0.0024348 | R12: 0.0025746 | S12: 0.0026436 | T12: 0.0027021 | U12: 0.0027627 | V12: 0.0028301 | W12: 0.002902 | X12: 0.0029671 | Y12: 0.0030416 | Z12: 0.003116 | AA12: 0.0031881 | AB12: 0.003294 | AC12: 0.0033838 | AD12: 0.0034832 | AE12: 0.0036139 | AF12: 0.0037283 | AG12: 0.0038508 | AH12: 0.0039962 | AI12: 0.0041464 | AJ12: 0.0042917 | AK12: 0.0044764 | AL12: 0.0046387 | AM12: 0.0048066 | AN12: 0.0049971 | AO12: 0.0051697 | AP12: 0.0053542 | AQ12: 0.0055518 | AR12: 0.0057366 | AS12: 0.0059342 | AT12: 0.0061428 | AU12: 0.0063447 | AV12: 0.0065465 | AW12: 0.0067595 | AX12: 0.0069724 | AY12: 0.0071923 | AZ12: 0.0073906 | BA12: 0.0075958 | BB12: 0.0078146 | BC12: 0.0080121 | BD12: 0.0081965 | BE12: 0.0084137 | BF12: 0.0085909 | BG12: 0.0087871 | BH12: 0.0089896 | BI12: 0.0091657 | BJ12: 0.0093539 | BK12: 0.0095422 | BL12: 0.0097121 | BM12: 0.0098821 | BN12: 0.0100577 | BO12: 0.0102206 | BP12: 0.0103679 | BQ12: 0.0105361 | BR12: 0.0106768 | BS12: 0.0108271 | BT12: 0.0109775 | BU12: 0.0111109 | BV12: 0.0112576 | BW12: 0.0113821 | BX12: 0.0115186 | BY12: 0.0116596 | BZ12: 0.0117874 | CA12: 0.0119273 | CB12: 0.0120536 | CC12: 0.0121935 | CD12: 0.0123276 | CE12: 0.0124752 | CF12: 0.0126003 | CG12: 0.0127377 | CH12: 0.0128795 | CI12: 0.013008 | CJ12: 0.0131311 | CK12: 0.0132542 | CL12: 0.0133733 | CM12: 0.0134906 | CN12: 0.0135901 | CO12: 0.0136967 | CP12: 0.0137896 | CQ12: 0.0138856 | CR12: 0.0139785 | CS12: 0.0140645 | CT12: 0.01414 | CU12: 0.0142182 | CV12: 0.0143079 | CW12: 0.0143892 | CX12: 0.0144761 | CY12: 0.0145711 | CZ12: 0.0146569 | DA12: 0.0147518 | DB12: 0.0148551 | DC12: 0.0149487 | DD12: 0.0150455 | DE12: 0.0151539 | DF12: 0.0152555 | DG12: 0.0153571 | DH12: 0.0154382 | DI12: 0.0155166 | DJ12: 0.0156028 | DK12: 0.0156635 | DL12: 0.0157221 | DM12: 0.0157869 | DN12: 0.015828 | DO12: 0.0158678 | DP12: 0.0159075 | DQ12: 0.0159258 | DR12: 0.015944 | DS12: 0.0159628

Sheet Diagram 1
B2: =Instructions!B3 -> Comparing Complex Deal Structures
B4: Deal Structure 1: Profit Sharing at the Joint Venture Level

Sheet Diagram 2
B2: =Instructions!B3 -> Comparing Complex Deal Structures
B4: Deal Structure 2: Profit Sharing at the Joint Venture Level

Sheet Scenario
B2: =Inputs!B2 -> Comparing Complex Deal Structures
E3: ="Vacancy Rate - "&E4 -> Vacancy Rate - Best Case
B4: Scenarios | C4: Scenario in Model | E4: =D9 -> Best Case
E7: Occupancy | K7: Transient ADR
B8: Label | C8: Case # | D8: Scenario In Model | E8: =C17 -> 2021 | F8: =D17 -> 2022 | G8: =E17 -> 2023 | H8: =F17 -> 2024 | I8: =G17 -> 2025 | J8: =H17 -> 2026 | K8: =I17 -> 2021 | L8: =J17 -> 2022 | ... Q8: =O17 -> Terminal Cap Rate
B9: Running Case in Model | C9: 1 | D9: =OFFSET(D$10,$C$9,0) -> Best Case | E9: =OFFSET(E$10,$C$9,0) -> 0.7 | F9: =OFFSET(F$10,$C$9,0) -> 0.75 | G9: =OFFSET(G$10,$C$9,0) -> 0.79 | H9: =OFFSET(H$10,$C$9,0) -> 0.81 | I9: =OFFSET(I$10,$C$9,0) -> 0.79 | J9: =OFFSET(J$10,$C$9,0) -> 0.8 | K9: =OFFSET(K$10,$C$9,0) -> 185 | ... Q9: =OFFSET(Q$10,$C$9,0) -> 0.085
E10: 3 | T10: =NOW() -> 46154.603
C11: 1 | D11: Best Case | E11: =VLOOKUP($D11,ScenarioTable,C$18,0) -> 0.7 | F11: =VLOOKUP($D11,ScenarioTable,D$18,0) -> 0.75 | G11: =VLOOKUP($D11,ScenarioTable,E$18,0) -> 0.79 | H11: =VLOOKUP($D11,ScenarioTable,F$18,0) -> 0.81 | I11: =VLOOKUP($D11,ScenarioTable,G$18,0) -> 0.79 | J11: =VLOOKUP($D11,ScenarioTable,H$18,0) -> 0.8 | K11: =VLOOKUP($D11,ScenarioTable,I$18,0) -> 185 | L11: =VLOOKUP($D11,ScenarioTable,J$18,0) -> 190 | ... Q11: =VLOOKUP($D11,ScenarioTable,O$18,0) -> 0.085 | S11: =C11 -> 1 | T11: 46154.603
C12: 2 | D12: Most Likely Case | E12: =VLOOKUP($D12,ScenarioTable,C$18,0) -> 0.69 | F12: =VLOOKUP($D12,ScenarioTable,D$18,0) -> 0.65 | G12: =VLOOKUP($D12,ScenarioTable,E$18,0) -> 0.6 | H12: =VLOOKUP($D12,ScenarioTable,F$18,0) -> 0.68 | I12: =VLOOKUP($D12,ScenarioTable,G$18,0) -> 0.71 | J12: =VLOOKUP($D12,ScenarioTable,H$18,0) -> 0.68 | K12: =VLOOKUP($D12,ScenarioTable,I$18,0) -> 180 | L12: =VLOOKUP($D12,ScenarioTable,J$18,0) -> 183 | ... Q12: =VLOOKUP($D12,ScenarioTable,O$18,0) -> 0.085 | S12: =C12 -> 2 | T12: 46154.603
C13: 3 | D13: Worst Case | E13: =VLOOKUP($D13,ScenarioTable,C$18,0) -> 0.68 | F13: =VLOOKUP($D13,ScenarioTable,D$18,0) -> 0.64 | G13: =VLOOKUP($D13,ScenarioTable,E$18,0) -> 0.59 | H13: =VLOOKUP($D13,ScenarioTable,F$18,0) -> 0.6 | I13: =VLOOKUP($D13,ScenarioTable,G$18,0) -> 0.62 | J13: =VLOOKUP($D13,ScenarioTable,H$18,0) -> 0.63 | K13: =VLOOKUP($D13,ScenarioTable,I$18,0) -> 175 | L13: =VLOOKUP($D13,ScenarioTable,J$18,0) -> 170 | ... Q13: =VLOOKUP($D13,ScenarioTable,O$18,0) -> 0.09 | S13: =C13 -> 3 | T13: 46154.603
T14: 46154.603
C16: Occupancy | I16: Transient ADR
B17: Scenario Table | C17: =Inputs!C22 -> 2021 | D17: =Inputs!D22 -> 2022 | E17: =Inputs!E22 -> 2023 | F17: =Inputs!F22 -> 2024 | G17: =Inputs!G22 -> 2025 | H17: =Inputs!H22 -> 2026 | I17: =C17 -> 2021 | J17: =D17 -> 2022 | K17: =E17 -> 2023 | L17: =F17 -> 2024 | M17: =G17 -> 2025 | N17: =H17 -> 2026 | O17: Terminal Cap Rate | P17: Probability of Scenario
B18: 1 | C18: =B18+1 -> 2 | D18: =C18+1 -> 3 | E18: =D18+1 -> 4 | F18: =E18+1 -> 5 | G18: =F18+1 -> 6 | H18: =G18+1 -> 7 | I18: =H18+1 -> 8 | J18: =I18+1 -> 9 | ... N18: =M18+1 -> 13 | O18: 14 | P18: a5
B19: Best Case | C19: 0.7 | D19: 0.75 | E19: 0.79 | F19: 0.81 | G19: 0.79 | H19: 0.8 | I19: 185 | J19: 190 | K19: 188 | L19: 185 | M19: 191 | N19: 192 | O19: 0.085 | P19: 0.35
B20: Most Likely Case | C20: 0.69 | D20: 0.65 | E20: 0.6 | F20: 0.68 | G20: 0.71 | H20: 0.68 | I20: 180 | J20: 183 | K20: 188 | L20: 185 | M20: 190 | N20: 195 | O20: 0.085 | P20: 0.5
B21: Worst Case | C21: 0.68 | D21: 0.64 | E21: 0.59 | F21: 0.6 | G21: 0.62 | H21: 0.63 | I21: 175 | J21: 170 | K21: 165 | L21: 165 | M21: 168 | N21: 170 | O21: 0.09 | P21: 0.15

Sheet Summary Analysis
B2: =Scenario!B2 -> Comparing Complex Deal Structures | H2: TO UPDATE DATA TABLES: F9
B4: Outputs | C4: Running Case | E4: =Scenario!C9 -> 1 | F4: 1
F5: 2
F6: 3
B7: Question 4: Data Tables
C9: 1
C10: 2
C11: 3
B12: Deal Structure 1 - Fulcrum Capital takes a preferred equity stake and Eagle Investments takes the LP Position.
C14: Net Equity Returns | F14: Co-Investor | I14: Sponsor - After Fees
C15: IRR | D15: CFx | E15: Net Profits | F15: IRR | G15: CFx | H15: Net Profits | I15: IRR | J15: CFx | K15: Net Profits
B16: Scenario | C16: ='Provided - CAP Acct. 1'!I121 -> 0.3335279 | D16: ='Provided - CAP Acct. 1'!I122 -> 2.9428465 | E16: ='Provided - CAP Acct. 1'!I123 -> 24229917 | F16: ='Q2 - Equity Waterfall 1'!E116 -> 0.22900502 | G16: ='Q2 - Equity Waterfall 1'!E117 -> 2.0323762 | H16: ='Q2 - Equity Waterfall 1'!E118 -> 11587612 | I16: ='Q2 - Equity Waterfall 1'!E126 -> 0.86798524 | J16: ='Q2 - Equity Waterfall 1'!E127 -> 12.735117 | K16: ='Q2 - Equity Waterfall 1'!E128 -> 13030711
B17: =Scenario!B19 -> Best Case | C17: =IF($E$4=$F4,$C$16,C17) -> 0.3335279 | D17: =IF($E$4=$F4,$D$16,D17) -> 2.9428465 | E17: =IF($E$4=$F4,$E$16,E17) -> 24229917 | F17: =IF($E$4=$F4,$F$16,F17) -> 0.22900502 | G17: =IF($E$4=$F4,$G$16,G17) -> 2.0323762 | H17: =IF($E$4=$F4,$H$16,H17) -> 11587612 | I17: =IF($E$4=$F4,$I$16,I17) -> 0.86798524 | J17: =IF($E$4=$F4,$J$16,J17) -> 12.735117 | K17: =IF($E$4=$F4,$K$16,K17) -> 13030711
B18: =Scenario!B20 -> Most Likely Case | C18: =IF($E$4=$F5,$C$16,C18) -> 0.13242428 | D18: =IF($E$4=$F5,$D$16,D18) -> 1.898842 | E18: =IF($E$4=$F5,$E$16,E18) -> 11209773 | F18: =IF($E$4=$F5,$F$16,F18) -> 0.094952723 | G18: =IF($E$4=$F5,$G$16,G18) -> 1.5683742 | H18: =IF($E$4=$F5,$H$16,H18) -> 6379554.2 | I18: =IF($E$4=$F5,$I$16,I18) -> 0.37545518 | J18: =IF($E$4=$F5,$J$16,J18) -> 5.8779076 | K18: =IF($E$4=$F5,$K$16,K18) -> 5416443.9
B19: =Scenario!B21 -> Worst Case | C19: =IF($E$4=$F6,$C$16,C19) -> -0.10244516 | D19: =IF($E$4=$F6,$D$16,D19) -> 0.5409178 | E19: =IF($E$4=$F6,$E$16,E19) -> -5859189.3 | F19: =IF($E$4=$F6,$F$16,F19) -> -0.085564022 | G19: =IF($E$4=$F6,$G$16,G19) -> 0.60101978 | H19: =IF($E$4=$F6,$H$16,H19) -> -4582906 | I19: =IF($E$4=$F6,$I$16,I19) -> -0.19872989 | J19: =IF($E$4=$F6,$J$16,J19) -> 0.44082445 | K19: =IF($E$4=$F6,$K$16,K19) -> -620910.28
B21: Expected Value | C21: =SUMPRODUCT(C17:C19,Probabilities) -> 0.16758013 | D21: =SUMPRODUCT(D17:D19,Probabilities) -> 2.060555 | E21: =SUMPRODUCT(E17:E19,Probabilities) -> 13206479 | F21: =SUMPRODUCT(F17:F19,Probabilities) -> 0.11479352 | G21: =SUMPRODUCT(G17:G19,Probabilities) -> 1.5856718 | H21: =SUMPRODUCT(H17:H19,Probabilities) -> 6558005.4 | I21: =SUMPRODUCT(I17:I19,Probabilities) -> 0.46171294 | J21: =SUMPRODUCT(J17:J19,Probabilities) -> 7.4623685 | K21: =SUMPRODUCT(K17:K19,Probabilities) -> 7175834.2
B23: Deal Structure 2 - SCP takes both a preferred equity AND Limited Partner (Co-Investor) stake.
C25: Net Equity Returns | F25: Co-Investor - After Pref Equity | I25: Sponsor - After Fees
C26: IRR | D26: CFx | E26: Net Profits | F26: IRR | G26: CFx | H26: Net Profits | I26: IRR | J26: CFx | K26: Net Profits
B27: Scenario | C27: ='Q1 - CAP Acct. 2'!I122 -> 0.36700209 | D27: ='Q1 - CAP Acct. 2'!I123 -> 2.8681056 | E27: ='Q1 - CAP Acct. 2'!I124 -> 23221117 | F27: ='Q3 - Equity Waterfall 2'!E145 -> 0.21543372 | G27: ='Q3 - Equity Waterfall 2'!E146 -> 1.8081024 | H27: ='Q3 - Equity Waterfall 2'!E147 -> 13016197 | I27: ='Q3 - Equity Waterfall 2'!E135 -> 0.94643975 | J27: ='Q3 - Equity Waterfall 2'!E136 -> 12.227224 | K27: ='Q3 - Equity Waterfall 2'!E137 -> 12390623
B28: =B17 -> Best Case | C28: =IF($E$4=$F4,$C$27,C28) -> 0.36700209 | D28: =IF($E$4=$F4,$D$27,D28) -> 2.8681056 | E28: =IF($E$4=$F4,$E$27,E28) -> 23221117 | F28: =IF($E$4=$F4,$F$27,F28) -> 0.21543372 | G28: =IF($E$4=$F4,$G$27,G28) -> 1.8081024 | H28: =IF($E$4=$F4,$H$27,H28) -> 13016197 | I28: =IF($E$4=$F4,$I$27,I28) -> 0.94643975 | J28: =IF($E$4=$F4,$J$27,J28) -> 12.227224 | K28: =IF($E$4=$F4,$K$27,K28) -> 12390623
B29: =B18 -> Most Likely Case | C29: =IF($E$4=$F5,$C$27,C29) -> 0.13001292 | D29: =IF($E$4=$F5,$D$27,D29) -> 1.8167195 | E29: =IF($E$4=$F5,$E$27,E29) -> 10152070 | F29: =IF($E$4=$F5,$F$27,F29) -> 0.10351493 | G29: =IF($E$4=$F5,$G$27,G29) -> 1.5110477 | H29: =IF($E$4=$F5,$H$27,H29) -> 8231502.9 | I29: =IF($E$4=$F5,$I$27,I29) -> 0.36594853 | J29: =IF($E$4=$F5,$J$27,J29) -> 5.0084828 | K29: =IF($E$4=$F5,$K$27,K29) -> 4423853.8
B30: =B19 -> Worst Case | C30: =IF($E$4=$F6,$C$27,C30) -> -0.15412311 | D30: =IF($E$4=$F6,$D$27,D30) -> 0.41458989 | E30: =IF($E$4=$F6,$E$27,E30) -> -7447462 | F30: =IF($E$4=$F6,$F$27,F30) -> -0.051213007 | G30: =IF($E$4=$F6,$G$27,G30) -> 0.78986162 | H30: =IF($E$4=$F6,$H$27,H30) -> -3384722.8 | I30: =IF($E$4=$F6,$I$27,I30) -> -0.22866605 | J30: =IF($E$4=$F6,$J$27,J30) -> 0.40489895 | K30: =IF($E$4=$F6,$K$27,K30) -> -656767.2
B32: Expected Value | C32: =SUMPRODUCT(C28:C30,Probabilities) -> 0.17033873 | D32: =SUMPRODUCT(D28:D30,Probabilities) -> 1.9743852 | E32: =SUMPRODUCT(E28:E30,Probabilities) -> 12086307 | F32: =SUMPRODUCT(F28:F30,Probabilities) -> 0.11947732 | G32: =SUMPRODUCT(G28:G30,Probabilities) -> 1.5068389 | H32: =SUMPRODUCT(H28:H30,Probabilities) -> 8163711.9 | I32: =SUMPRODUCT(I28:I30,Probabilities) -> 0.47992827 | J32: =SUMPRODUCT(J28:J30,Probabilities) -> 6.8445047 | K32: =SUMPRODUCT(K28:K30,Probabilities) -> 6450129.8
B34: Question 5: Comparing Net Equity Returns
B36: Capital Structure Analysis - Risk Adjusted Returns
B38: =B12 -> Deal Structure 1 - Fulcrum Capital takes a preferred equity stake and Eagle Investments takes the LP Position.
B40: Scenario | C40: Returns | D40: Probability | E40: Deviation | F40: Sq. Deviation | G40: Product
B41: =B17 -> Best Case | C41: =C17 -> 0.3335279 | D41: =Scenario!P19 -> 0.35 | E41: =C41-$C$44 -> 0.16594777 | F41: =E41^2 -> 0.027538663 | G41: =D41*F41 -> 0.0096385322
B42: =B18 -> Most Likely Case | C42: =C18 -> 0.13242428 | D42: =Scenario!P20 -> 0.5 | E42: =C42-$C$44 -> -0.035155855 | F42: =E42^2 -> 0.0012359341 | G42: =D42*F42 -> 0.00061796706
B43: =B19 -> Worst Case | C43: =C19 -> -0.10244516 | D43: =Scenario!P21 -> 0.15 | E43: =C43-$C$44 -> -0.27002529 | F43: =E43^2 -> 0.072913657 | G43: =D43*F43 -> 0.010937048
B44: Expected Returns | C44: =SUMPRODUCT(C41:C43,D41:D43) -> 0.16758013
B45: Standard Deviation | C45: =SQRT(SUM(G41:G43)) -> 0.14558004
B46: Returns per Unit of Risk | C46: =C44/C45 -> 1.1511203
B48: =B23 -> Deal Structure 2 - SCP takes both a preferred equity AND Limited Partner (Co-Investor) stake.
B50: Scenario | C50: Returns | D50: Probability | E50: Deviation | F50: Sq. Deviation | G50: Product
B51: =B41 -> Best Case | C51: =C28 -> 0.36700209 | D51: =Scenario!P19 -> 0.35 | E51: =C51-$C$54 -> 0.19666336 | F51: =E51^2 -> 0.038676478 | G51: =D51*F51 -> 0.013536767
B52: =B42 -> Most Likely Case | C52: =C29 -> 0.13001292 | D52: =Scenario!P20 -> 0.5 | E52: =C52-$C$54 -> -0.040325803 | F52: =E52^2 -> 0.0016261704 | G52: =D52*F52 -> 0.00081308519
B53: =B43 -> Worst Case | C53: =C30 -> -0.15412311 | D53: =Scenario!P21 -> 0.15 | E53: =C53-$C$54 -> -0.32446183 | F53: =E53^2 -> 0.10527548 | G53: =D53*F53 -> 0.015791322
B54: Expected Returns | C54: =SUMPRODUCT(C51:C53,D51:D53) -> 0.17033873
B55: Standard Deviation | C55: =SQRT(SUM(G51:G53)) -> 0.17361214
B56: Returns per Unit of Risk | C56: =C54/C55 -> 0.98114526
B59: Question 6: Comparing L.P.s (Co-Investors) Total Returns
B61: Impact of Partnership Structure on Co-Investor Position - Capital Structure Analysis - Risk Adjusted Returns
B63: =B38 -> Deal Structure 1 - Fulcrum Capital takes a preferred equity stake and Eagle Investments takes the LP Position.
B65: Scenario | C65: Returns | D65: Probability | E65: Deviation | F65: Sq. Deviation | G65: Product
B66: =B41 -> Best Case | C66: =F17 -> 0.22900502 | D66: =Scenario!P19 -> 0.35 | E66: =C66-$C$69 -> 0.11421151 | F66: =E66^2 -> 0.013044268 | G66: =D66*F66 -> 0.0045654938
B67: =B42 -> Most Likely Case | C67: =F18 -> 0.094952723 | D67: =Scenario!P20 -> 0.5 | E67: =C67-$C$69 -> -0.019840792 | F67: =E67^2 -> 0.00039365704 | G67: =D67*F67 -> 0.00019682852
B68: =B43 -> Worst Case | C68: =F19 -> -0.085564022 | D68: =Scenario!P21 -> 0.15 | E68: =C68-$C$69 -> -0.20035754 | F68: =E68^2 -> 0.040143143 | G68: =D68*F68 -> 0.0060214714
B69: Expected Returns | C69: =SUMPRODUCT(C66:C68,D66:D68) -> 0.11479352
B70: Standard Deviation | C70: =SQRT(SUM(G66:G68)) -> 0.10384505
B71: Returns per Unit of Risk | C71: =C69/C70 -> 1.1054308
B73: =B48 -> Deal Structure 2 - SCP takes both a preferred equity AND Limited Partner (Co-Investor) stake.
B75: Scenario | C75: Returns | D75: Probability | E75: Deviation | F75: Sq. Deviation | G75: Product
B76: =B66 -> Best Case | C76: =F28 -> 0.21543372 | D76: =Scenario!P19 -> 0.35 | E76: =C76-$C$79 -> 0.095956407 | F76: =E76^2 -> 0.009207632 | G76: =D76*F76 -> 0.0032226712
B77: =B67 -> Most Likely Case | C77: =F29 -> 0.10351493 | D77: =Scenario!P20 -> 0.5 | E77: =C77-$C$79 -> -0.015962388 | F77: =E77^2 -> 0.00025479784 | G77: =D77*F77 -> 0.00012739892
B78: =B68 -> Worst Case | C78: =F30 -> -0.051213007 | D78: =Scenario!P21 -> 0.15 | E78: =C78-$C$79 -> -0.17069032 | F78: =E78^2 -> 0.029135186 | G78: =D78*F78 -> 0.0043702779
B79: Expected Returns | C79: =SUMPRODUCT(C76:C78,D76:D78) -> 0.11947732
B80: Standard Deviation | C80: =SQRT(SUM(G76:G78)) -> 0.087865511
B81: Returns per Unit of Risk | C81: =C79/C80 -> 1.3597749
B83: Question 7: Comparing G.P.s (Sponsor) Total Returns
B85: Impact of Partnership Structure on Sponsor Position - Capital Structure Analysis - Risk Adjusted Returns
B87: =B63 -> Deal Structure 1 - Fulcrum Capital takes a preferred equity stake and Eagle Investments takes the LP Position.
B89: Scenario | C89: Returns | D89: Probability | E89: Deviation | F89: Sq. Deviation | G89: Product
B90: =B76 -> Best Case | C90: =I17 -> 0.86798524 | D90: =Scenario!P19 -> 0.35 | E90: =C90-$C$93 -> 0.4062723 | F90: =E90^2 -> 0.16505718 | G90: =D90*F90 -> 0.057770012
B91: =B77 -> Most Likely Case | C91: =I18 -> 0.37545518 | D91: =Scenario!P20 -> 0.5 | E91: =C91-$C$93 -> -0.086257758 | F91: =E91^2 -> 0.0074404008 | G91: =D91*F91 -> 0.0037202004
B92: =B78 -> Worst Case | C92: =I19 -> -0.19872989 | D92: =Scenario!P21 -> 0.15 | E92: =C92-$C$93 -> -0.66044283 | F92: =E92^2 -> 0.43618473 | G92: =D92*F92 -> 0.06542771
B93: Expected Returns | C93: =SUMPRODUCT(C90:C92,D90:D92) -> 0.46171294
B94: Standard Deviation | C94: =SQRT(SUM(G90:G92)) -> 0.35625542
B95: Returns per Unit of Risk | C95: =C93/C94 -> 1.2960166
B97: =B73 -> Deal Structure 2 - SCP takes both a preferred equity AND Limited Partner (Co-Investor) stake.
B99: Scenario | C99: Returns | D99: Probability | E99: Deviation | F99: Sq. Deviation | G99: Product
B100: =B90 -> Best Case | C100: =I28 -> 0.94643975 | D100: =Scenario!P19 -> 0.35 | E100: =C100-$C$103 -> 0.46651148 | F100: =E100^2 -> 0.21763297 | G100: =D100*F100 -> 0.076171538
B101: =B91 -> Most Likely Case | C101: =I29 -> 0.36594853 | D101: =Scenario!P20 -> 0.5 | E101: =C101-$C$103 -> -0.11397974 | F101: =E101^2 -> 0.012991382 | G101: =D101*F101 -> 0.0064956908
B102: =B92 -> Worst Case | C102: =I30 -> -0.22866605 | D102: =Scenario!P21 -> 0.15 | E102: =C102-$C$103 -> -0.70859432 | F102: =E102^2 -> 0.50210591 | G102: =D102*F102 -> 0.075315887
B103: Expected Returns | C103: =SUMPRODUCT(C100:C102,D100:D102) -> 0.47992827
B104: Standard Deviation | C104: =SQRT(SUM(G100:G102)) -> 0.3974709
B105: Returns per Unit of Risk | C105: =C103/C104 -> 1.2074551

Sheet NOI
B2: =Inputs!B2 -> Comparing Complex Deal Structures
B4: Model: Pro-Forma - Hotel | C4: Scenario in Model: | E4: =Scenario!E4 -> Best Case
C7: Years | K7: =C8 -> 2021 | O7: =D8 -> 2022 | S7: =E8 -> 2023 | W7: =F8 -> 2024 | AA7: =G8 -> 2025 | AE7: =H8 -> 2026
C8: =Inputs!C22 -> 2021 | D8: =Inputs!D22 -> 2022 | E8: =Inputs!E22 -> 2023 | F8: =Inputs!F22 -> 2024 | G8: =Inputs!G22 -> 2025 | H8: =Inputs!H22 -> 2026 | K8: % | L8: PAR | M8: POR | O8: % | P8: PAR | Q8: POR | S8: % | T8: PAR | U8: POR | W8: % | X8: PAR | Y8: POR | AA8: % | AB8: PAR | AC8: POR | AE8: % | AF8: PAR | AG8: POR
C9: 1 | D9: =C9+1 -> 2 | E9: =D9+1 -> 3 | F9: =E9+1 -> 4 | G9: =F9+1 -> 5 | H9: =G9+1 -> 6
B10: Inflation Adjustment | C10: {=PRODUCT(1+Inputs!$C$32:C32)} -> 1.02 | D10: {=PRODUCT(1+Inputs!$C$32:D32)} -> 1.0404 | E10: {=PRODUCT(1+Inputs!$C$32:E32)} -> 1.061208 | F10: {=PRODUCT(1+Inputs!$C$32:F32)} -> 1.0824322 | G10: {=PRODUCT(1+Inputs!$C$32:G32)} -> 1.1040808 | H10: {=PRODUCT(1+Inputs!$C$32:H32)} -> 1.1261624 | I10: x
B11: Hotel Revenue
B12: Rooms | C12: =SUMPRODUCT(C17:C18,C21:C22) -> 10667125 | D12: =SUMPRODUCT(D17:D18,D21:D22) -> 11757562 | E12: =SUMPRODUCT(E17:E18,E21:E22) -> 12157557 | F12: =SUMPRODUCT(F17:F18,F21:F22) -> 12565125 | G12: =SUMPRODUCT(G17:G18,G21:G22) -> 12600895 | H12: =SUMPRODUCT(H17:H18,H21:H22) -> 13205700 | I12: x | K12: =C12/C$31 -> 0.72773226 | L12: =C12/C$15 -> 116.9 | M12: =C12/C$16 -> 167 | O12: =D12/D$31 -> 0.7393954 | P12: =D12/D$15 -> 128.85 | Q12: =D12/D$16 -> 171.8 | S12: =E12/E$31 -> 0.71697006 | T12: =E12/E$15 -> 133.2335 | U12: =E12/E$16 -> 168.65 | W12: =F12/F$31 -> 0.68218299 | X12: =F12/F$15 -> 137.7 | Y12: =F12/F$16 -> 170 | AA12: =G12/G$31 -> 0.71448425 | AB12: =G12/G$15 -> 138.092 | AC12: =G12/G$16 -> 174.8 | AE12: =H12/H$31 -> 0.74470187 | AF12: =H12/H$15 -> 144.72 | AG12: =H12/H$16 -> 180.9
B13: Number of Rooms | C13: =NumberRooms -> 250 | D13: =NumberRooms -> 250 | E13: =NumberRooms -> 250 | F13: =NumberRooms -> 250 | G13: =NumberRooms -> 250 | H13: =NumberRooms -> 250 | I13: x
B14: Days Open | C14: =DaysOpen -> 365 | D14: =DaysOpen -> 365 | E14: =DaysOpen -> 365 | F14: =DaysOpen -> 365 | G14: =DaysOpen -> 365 | H14: =DaysOpen -> 365 | I14: x
B15: Annual Available Rooms | C15: =C13*C14 -> 91250 | D15: =D13*D14 -> 91250 | E15: =E13*E14 -> 91250 | F15: =F13*F14 -> 91250 | G15: =G13*G14 -> 91250 | H15: =H13*H14 -> 91250 | I15: x
B16: Occupied Rooms | C16: =SUM(C17:C18) -> 63875 | D16: =SUM(D17:D18) -> 68437.5 | E16: =SUM(E17:E18) -> 72087.5 | F16: =SUM(F17:F18) -> 73912.5 | G16: =SUM(G17:G18) -> 72087.5 | H16: =SUM(H17:H18) -> 73000 | I16: x
B17: Transient Occupied Rooms | C17: =C$15*Inputs!C$23*Inputs!C24 -> 38325 | D17: =D$15*Inputs!D$23*Inputs!D24 -> 44484.375 | E17: =E$15*Inputs!E$23*Inputs!E24 -> 39648.125 | F17: =F$15*Inputs!F$23*Inputs!F24 -> 29565 | G17: =G$15*Inputs!G$23*Inputs!G24 -> 39648.125 | H17: =H$15*Inputs!H$23*Inputs!H24 -> 51100 | I17: x
B18: Group Occupied Rooms | C18: =C$15*Inputs!C$23*Inputs!C25 -> 25550 | D18: =D$15*Inputs!D$23*Inputs!D25 -> 23953.125 | E18: =E$15*Inputs!E$23*Inputs!E25 -> 32439.375 | F18: =F$15*Inputs!F$23*Inputs!F25 -> 44347.5 | G18: =G$15*Inputs!G$23*Inputs!G25 -> 32439.375 | H18: =H$15*Inputs!H$23*Inputs!H25 -> 21900 | I18: x
B19: Occupancy | C19: =C16/C15 -> 0.7 | D19: =D16/D15 -> 0.75 | E19: =E16/E15 -> 0.79 | F19: =F16/F15 -> 0.81 | G19: =G16/G15 -> 0.79 | H19: =H16/H15 -> 0.8 | I19: x
B20: Average Rate (ADR) | C20: =Inputs!C26 -> 164 | D20: =Inputs!D26 -> 167.25 | E20: =Inputs!E26 -> 168.65 | F20: =Inputs!F26 -> 170 | G20: =Inputs!G26 -> 174.25 | H20: =Inputs!H26 -> 183 | I20: x
B21: ADR Transient | C21: =Inputs!C27 -> 185 | D21: =Inputs!D27 -> 190 | E21: =Inputs!E27 -> 188 | F21: =Inputs!F27 -> 185 | G21: =Inputs!G27 -> 191 | H21: =Inputs!H27 -> 192 | I21: x
B22: ADR Group | C22: =Inputs!C28 -> 140 | D22: =Inputs!D28 -> 138 | E22: =Inputs!E28 -> 145 | F22: =Inputs!F28 -> 160 | G22: =Inputs!G28 -> 155 | H22: =Inputs!H28 -> 155 | I22: x
B23: % Change | D23: =(D20/C20)-1 -> 0.019817073 | E23: =(E20/D20)-1 -> 0.0083707025 | F23: =(F20/E20)-1 -> 0.0080047436 | G23: =(G20/F20)-1 -> 0.025 | H23: =(H20/G20)-1 -> 0.050215208 | I23: x
B24: RevPAR | C24: =C19*C20 -> 114.8 | D24: =D19*D20 -> 125.4375 | E24: =E19*E20 -> 133.2335 | F24: =F19*F20 -> 137.7 | G24: =G19*G20 -> 137.6575 | H24: =H19*H20 -> 146.4 | I24: x
B25: % Change | D25: =(D24/C24)-1 -> 0.09266115 | E25: =(E24/D24)-1 -> 0.062150473 | F25: =(F24/E24)-1 -> 0.033523851 | G25: =(G24/F24)-1 -> -0.00030864198 | H25: =(H24/G24)-1 -> 0.063509071 | I25: x
B26: Total F&B | C26: =SUM(C27:C28) -> 3564225 | D26: =SUM(D27:D28) -> 3673725 | E26: =SUM(E27:E28) -> 4312995.1 | F26: =SUM(F27:F28) -> 5351265 | G26: =SUM(G27:G28) -> 4531420.2 | H26: =SUM(H27:H28) -> 3998940 | I26: x | K26: =C26/C$31 -> 0.24315845 | L26: =C26/C$15 -> 39.06 | M26: =C26/C$16 -> 55.8 | O26: =D26/D$31 -> 0.23102878 | P26: =D26/D$15 -> 40.26 | Q26: =D26/D$16 -> 53.68 | S26: =E26/E$31 -> 0.25435113 | T26: =E26/E$15 -> 47.2657 | U26: =E26/E$16 -> 59.83 | W26: =F26/F$31 -> 0.2905297 | X26: =F26/F$15 -> 58.644 | Y26: =F26/F$16 -> 72.4 | AA26: =G26/G$31 -> 0.25693638 | AB26: =G26/G$15 -> 49.6594 | AC26: =G26/G$16 -> 62.86 | AE26: =H26/H$31 -> 0.22551005 | AF26: =H26/H$15 -> 43.824 | AG26: =H26/H$16 -> 54.78
B27: FB Transient | C27: =C17*C21*Inputs!C30 -> 1418025 | D27: =D17*D21*Inputs!D30 -> 1690406.2 | E27: =E17*E21*Inputs!E30 -> 1490769.5 | F27: =F17*F21*Inputs!F30 -> 1093905 | G27: =G17*G21*Inputs!G30 -> 1514558.4 | H27: =H17*H21*Inputs!H30 -> 1962240 | I27: x
B28: FB Group | C28: =C18*C22*Inputs!C31 -> 2146200 | D28: =D18*D22*Inputs!D31 -> 1983318.8 | E28: =E18*E22*Inputs!E31 -> 2822225.6 | F28: =F18*F22*Inputs!F31 -> 4257360 | G28: =G18*G22*Inputs!G31 -> 3016861.9 | H28: =H18*H22*Inputs!H31 -> 2036700 | I28: x
B29: Miscellaneous | C29: =C12*MiscRate -> 426685 | D29: =D12*MiscRate -> 470302.5 | E29: =E12*MiscRate -> 486302.28 | F29: =F12*MiscRate -> 502605 | G29: =G12*MiscRate -> 504035.8 | H29: =H12*MiscRate -> 528228 | I29: x | K29: =C29/C$31 -> 0.029109291 | L29: =C29/C$15 -> 4.676 | M29: =C29/C$16 -> 6.68 | O29: =D29/D$31 -> 0.029575816 | P29: =D29/D$15 -> 5.154 | Q29: =D29/D$16 -> 6.872 | S29: =E29/E$31 -> 0.028678803 | T29: =E29/E$15 -> 5.32934 | U29: =E29/E$16 -> 6.746 | W29: =F29/F$31 -> 0.027287319 | X29: =F29/F$15 -> 5.508 | Y29: =F29/F$16 -> 6.8 | AA29: =G29/G$31 -> 0.02857937 | AB29: =G29/G$15 -> 5.52368 | AC29: =G29/G$16 -> 6.992 | AE29: =H29/H$31 -> 0.029788075 | AF29: =H29/H$15 -> 5.7888 | AG29: =H29/H$16 -> 7.236
B31: Total Hotel Revenue | C31: =SUM(C12,C26,C29) -> 14658035 | D31: =SUM(D12,D26,D29) -> 15901590 | E31: =SUM(E12,E26,E29) -> 16956854 | F31: =SUM(F12,F26,F29) -> 18418995 | G31: =SUM(G12,G26,G29) -> 17636351 | H31: =SUM(H12,H26,H29) -> 17732868 | I31: x
B33: Effective Gross Income (EGI) | C33: =SUM(C31) -> 14658035 | D33: =SUM(D31) -> 15901590 | E33: =SUM(E31) -> 16956854 | F33: =SUM(F31) -> 18418995 | G33: =SUM(G31) -> 17636351 | H33: =SUM(H31) -> 17732868 | I33: x | K33: =C33/C$31 -> 1 | L33: =C33/C$15 -> 160.636 | M33: =C33/C$16 -> 229.48 | O33: =D33/D$31 -> 1 | P33: =D33/D$15 -> 174.264 | Q33: =D33/D$16 -> 232.352 | S33: =E33/E$31 -> 1 | T33: =E33/E$15 -> 185.82854 | U33: =E33/E$16 -> 235.226 | W33: =F33/F$31 -> 1 | X33: =F33/F$15 -> 201.852 | Y33: =F33/F$16 -> 249.2 | AA33: =G33/G$31 -> 1 | AB33: =G33/G$15 -> 193.27508 | AC33: =G33/G$16 -> 244.652 | AE33: =H33/H$31 -> 1 | AF33: =H33/H$15 -> 194.3328 | AG33: =H33/H$16 -> 242.916
B35: Operating Expenses
B36: DISTRIBUTED
B37: Rooms | C37: =C$12*Inputs!$J61+(Inputs!$H61*C$15+Inputs!$I61*C$16)*C$10 -> 3225738.6 | D37: =D$12*Inputs!$J61+(Inputs!$H61*D$15+Inputs!$I61*D$16)*D$10 -> 3495693.7 | E37: =E$12*Inputs!$J61+(Inputs!$H61*E$15+Inputs!$I61*E$16)*E$10 -> 3634090.9 | F37: =F$12*Inputs!$J61+(Inputs!$H61*F$15+Inputs!$I61*F$16)*F$10 -> 3756161.6 | G37: =G$12*Inputs!$J61+(Inputs!$H61*G$15+Inputs!$I61*G$16)*G$10 -> 3772299.2 | H37: =H$12*Inputs!$J61+(Inputs!$H61*H$15+Inputs!$I61*H$16)*H$10 -> 3921543.7 | I37: x | K37: =C37/C$12 -> 0.3024 | L37: =C37/C$15 -> 35.35056 | M37: =C37/C$16 -> 50.5008 | O37: =D37/D$12 -> 0.29731449 | P37: =D37/D$15 -> 38.308972 | Q37: =D37/D$16 -> 51.078629 | S37: =E37/E$12 -> 0.29891621 | T37: =E37/E$15 -> 39.825653 | U37: =E37/E$16 -> 50.412219 | W37: =F37/F$12 -> 0.29893548 | X37: =F37/F$15 -> 41.163415 | Y37: =F37/F$16 -> 50.819031 | AA37: =G37/G$12 -> 0.29936756 | AB37: =G37/G$15 -> 41.340266 | AC37: =G37/G$16 -> 52.32945 | AE37: =H37/H$12 -> 0.29695841 | AF37: =H37/H$15 -> 42.975821 | AG37: =H37/H$16 -> 53.719776
B38: Total F&B | C38: =C$26*Inputs!$J62+(Inputs!$H62*C$15+Inputs!$I62*C$16)*C$10 -> 2862785.5 | D38: =D$26*Inputs!$J62+(Inputs!$H62*D$15+Inputs!$I62*D$16)*D$10 -> 2944499.2 | E38: =E$26*Inputs!$J62+(Inputs!$H62*E$15+Inputs!$I62*E$16)*E$10 -> 3365498.3 | F38: =F$26*Inputs!$J62+(Inputs!$H62*F$15+Inputs!$I62*F$16)*F$10 -> 4042094.7 | G38: =G$26*Inputs!$J62+(Inputs!$H62*G$15+Inputs!$I62*G$16)*G$10 -> 3529739.7 | H38: =H$26*Inputs!$J62+(Inputs!$H62*H$15+Inputs!$I62*H$16)*H$10 -> 3201545 | I38: x | K38: =C38/C$26 -> 0.8032 | L38: =C38/C$15 -> 31.372992 | M38: =C38/C$16 -> 44.81856 | O38: =D38/D$26 -> 0.80150233 | P38: =D38/D$15 -> 32.268484 | Q38: =D38/D$16 -> 43.024645 | S38: =E38/E$26 -> 0.78031582 | T38: =E38/E$15 -> 36.882174 | U38: =E38/E$16 -> 46.686296 | W38: =F38/F$26 -> 0.75535311 | X38: =F38/F$15 -> 44.296928 | Y38: =F38/F$16 -> 54.687565 | AA38: =G38/G$26 -> 0.77894778 | AB38: =G38/G$15 -> 38.682079 | AC38: =G38/G$16 -> 48.964657 | AE38: =H38/H$26 -> 0.80059841 | AF38: =H38/H$15 -> 35.085425 | AG38: =H38/H$16 -> 43.856781
B39: Miscellaneous | C39: =C$29*Inputs!$J63+(Inputs!$H63*C$15+Inputs!$I63*C$16)*C$10 -> 299874.22 | D39: =D$29*Inputs!$J63+(Inputs!$H63*D$15+Inputs!$I63*D$16)*D$10 -> 325518.63 | E39: =E$29*Inputs!$J63+(Inputs!$H63*E$15+Inputs!$I63*E$16)*E$10 -> 335721.49 | F39: =F$29*Inputs!$J63+(Inputs!$H63*F$15+Inputs!$I63*F$16)*F$10 -> 346118.86 | G39: =G$29*Inputs!$J63+(Inputs!$H63*G$15+Inputs!$I63*G$16)*G$10 -> 348213.31 | H39: =H$29*Inputs!$J63+(Inputs!$H63*H$15+Inputs!$I63*H$16)*H$10 -> 363080.01 | I39: x | K39: =C39/C$29 -> 0.7028 | L39: =C39/C$15 -> 3.2862928 | M39: =C39/C$16 -> 4.694704 | O39: =D39/D$29 -> 0.69214735 | P39: =D39/D$15 -> 3.5673275 | Q39: =D39/D$16 -> 4.7564366 | S39: =E39/E$29 -> 0.69035558 | T39: =E39/E$15 -> 3.6791396 | U39: =E39/E$16 -> 4.6571387 | W39: =F39/F$29 -> 0.68864985 | X39: =F39/F$15 -> 3.7930834 | Y39: =F39/F$16 -> 4.682819 | AA39: =G39/G$29 -> 0.69085035 | AB39: =G39/G$15 -> 3.8160363 | AC39: =G39/G$16 -> 4.8304256 | AE39: =H39/H$29 -> 0.68735471 | AF39: =H39/H$15 -> 3.978959 | AG39: =H39/H$16 -> 4.9736987
B40: TOTAL DEPT EXPENSE | C40: =SUM(C37:C39) -> 6388398.3 | D40: =SUM(D37:D39) -> 6765711.4 | E40: =SUM(E37:E39) -> 7335310.7 | F40: =SUM(F37:F39) -> 8144375.2 | G40: =SUM(G37:G39) -> 7650252.3 | H40: =SUM(H37:H39) -> 7486168.7 | I40: x | K40: =C40/C33 -> 0.43582911 | L40: =C40/C$15 -> 70.009845 | M40: =C40/C$16 -> 100.01406 | O40: =D40/D33 -> 0.4254739 | P40: =D40/D$15 -> 74.144783 | Q40: =D40/D$16 -> 98.859711 | S40: =E40/E33 -> 0.43258676 | T40: =E40/E$15 -> 80.386966 | U40: =E40/E$16 -> 101.75565 | W40: =F40/F33 -> 0.44217261 | X40: =F40/F$15 -> 89.253426 | Y40: =F40/F$16 -> 110.18942 | AA40: =G40/G33 -> 0.4337775 | AB40: =G40/G$15 -> 83.838381 | AC40: =G40/G$16 -> 106.12453 | AE40: =H40/H33 -> 0.42216345 | AF40: =H40/H$15 -> 82.040205 | AG40: =H40/H$16 -> 102.55026
B42: PROFIT
B43: Rooms | C43: =C12-C37 -> 7441386.4 | D43: =D12-D37 -> 8261868.8 | E43: =E12-E37 -> 8523466 | F43: =F12-F37 -> 8808963.4 | G43: =G12-G37 -> 8828595.8 | H43: =H12-H37 -> 9284156.3 | I43: x | K43: =1-K37 -> 0.6976 | L43: =C43/C$15 -> 81.54944 | M43: =C43/C$16 -> 116.4992 | O43: =1-O37 -> 0.70268551 | P43: =D43/D$15 -> 90.541028 | Q43: =D43/D$16 -> 120.72137 | S43: =1-S37 -> 0.70108379 | T43: =E43/E$15 -> 93.407847 | U43: =E43/E$16 -> 118.23778 | W43: =1-W37 -> 0.70106452 | X43: =F43/F$15 -> 96.536585 | Y43: =F43/F$16 -> 119.18097 | AA43: =1-AA37 -> 0.70063244 | AB43: =G43/G$15 -> 96.751734 | AC43: =G43/G$16 -> 122.47055 | AE43: =1-AE37 -> 0.70304159 | AF43: =H43/H$15 -> 101.74418 | AG43: =H43/H$16 -> 127.18022
B44: Total F&B | C44: =C26-C38 -> 701439.48 | D44: =D26-D38 -> 729225.85 | E44: =E26-E38 -> 947496.79 | F44: =F26-F38 -> 1309170.3 | G44: =G26-G38 -> 1001680.5 | H44: =H26-H38 -> 797395 | I44: x | K44: =1-K38 -> 0.1968 | L44: =C44/C$15 -> 7.687008 | M44: =C44/C$16 -> 10.98144 | O44: =1-O38 -> 0.19849767 | P44: =D44/D$15 -> 7.9915162 | Q44: =D44/D$16 -> 10.655355 | S44: =1-S38 -> 0.21968418 | T44: =E44/E$15 -> 10.383526 | U44: =E44/E$16 -> 13.143704 | W44: =1-W38 -> 0.24464689 | X44: =F44/F$15 -> 14.347072 | Y44: =F44/F$16 -> 17.712435 | AA44: =1-AA38 -> 0.22105222 | AB44: =G44/G$15 -> 10.977321 | AC44: =G44/G$16 -> 13.895343 | AE44: =1-AE38 -> 0.19940159 | AF44: =H44/H$15 -> 8.7385753 | AG44: =H44/H$16 -> 10.923219
B45: Miscellaneous | C45: =C29-C39 -> 126810.78 | D45: =D29-D39 -> 144783.87 | E45: =E29-E39 -> 150580.79 | F45: =F29-F39 -> 156486.14 | G45: =G29-G39 -> 155822.49 | H45: =H29-H39 -> 165147.99 | I45: x | K45: =1-K39 -> 0.2972 | L45: =C45/C$15 -> 1.3897072 | M45: =C45/C$16 -> 1.985296 | O45: =1-O39 -> 0.30785265 | P45: =D45/D$15 -> 1.5866725 | Q45: =D45/D$16 -> 2.1155634 | S45: =1-S39 -> 0.30964442 | T45: =E45/E$15 -> 1.6502004 | U45: =E45/E$16 -> 2.0888613 | W45: =1-W39 -> 0.31135015 | X45: =F45/F$15 -> 1.7149166 | Y45: =F45/F$16 -> 2.117181 | AA45: =1-AA39 -> 0.30914965 | AB45: =G45/G$15 -> 1.7076437 | AC45: =G45/G$16 -> 2.1615744 | AE45: =1-AE39 -> 0.31264529 | AF45: =H45/H$15 -> 1.809841 | AG45: =H45/H$16 -> 2.2623013
B46: TOTAL DEPT PROFIT | C46: =SUM(C43:C45) -> 8269636.7 | D46: =SUM(D43:D45) -> 9135878.6 | E46: =SUM(E43:E45) -> 9621543.6 | F46: =SUM(F43:F45) -> 10274620 | G46: =SUM(G43:G45) -> 9986098.8 | H46: =SUM(H43:H45) -> 10246699 | I46: x | K46: =C46/C$33 -> 0.56417089 | L46: =C46/C$15 -> 90.626155 | M46: =C46/C$16 -> 129.46594 | O46: =D46/D$33 -> 0.5745261 | P46: =D46/D$15 -> 100.11922 | Q46: =D46/D$16 -> 133.49229 | S46: =E46/E$33 -> 0.56741324 | T46: =E46/E$15 -> 105.44157 | U46: =E46/E$16 -> 133.47035 | W46: =F46/F$33 -> 0.55782739 | X46: =F46/F$15 -> 112.59857 | Y46: =F46/F$16 -> 139.01058 | AA46: =G46/G$33 -> 0.5662225 | AB46: =G46/G$15 -> 109.4367 | AC46: =G46/G$16 -> 138.52747 | AE46: =H46/H$33 -> 0.57783655 | AF46: =H46/H$15 -> 112.2926 | AG46: =H46/H$16 -> 140.36574
B48: UNDISTRIBUTED
B49: Administrative & General | C49: =C$33*Inputs!$J68+(Inputs!$H68*C$15+Inputs!$I68*C$16)*C$10 -> 1486324.7 | D49: =D$33*Inputs!$J68+(Inputs!$H68*D$15+Inputs!$I68*D$16)*D$10 -> 1544563.1 | E49: =E$33*Inputs!$J68+(Inputs!$H68*E$15+Inputs!$I68*E$16)*E$10 -> 1597571.3 | F49: =F$33*Inputs!$J68+(Inputs!$H68*F$15+Inputs!$I68*F$16)*F$10 -> 1663212.8 | G49: =G$33*Inputs!$J68+(Inputs!$H68*G$15+Inputs!$I68*G$16)*G$10 -> 1661946.4 | H49: =H$33*Inputs!$J68+(Inputs!$H68*H$15+Inputs!$I68*H$16)*H$10 -> 1687499 | I49: x | K49: =C49/C$33 -> 0.1014 | L49: =C49/C$15 -> 16.28849 | M49: =C49/C$16 -> 23.269272 | O49: =D49/D$33 -> 0.097132618 | P49: =D49/D$15 -> 16.926719 | Q49: =D49/D$16 -> 22.568958 | S49: =E49/E$33 -> 0.094213896 | T49: =E49/E$15 -> 17.507631 | U49: =E49/E$16 -> 22.161558 | W49: =F49/F$33 -> 0.090298784 | X49: =F49/F$15 -> 18.22699 | Y49: =F49/F$16 -> 22.502457 | AA49: =G49/G$33 -> 0.094234141 | AB49: =G49/G$15 -> 18.213111 | AC49: =G49/G$16 -> 23.054571 | AE49: =H49/H$33 -> 0.095162216 | AF49: =H49/H$15 -> 18.49314 | AG49: =H49/H$16 -> 23.116425
B50: Sales & Marketing | C50: =C$33*Inputs!$J69+(Inputs!$H69*C$15+Inputs!$I69*C$16)*C$10 -> 740230.77 | D50: =D$33*Inputs!$J69+(Inputs!$H69*D$15+Inputs!$I69*D$16)*D$10 -> 786965 | E50: =E$33*Inputs!$J69+(Inputs!$H69*E$15+Inputs!$I69*E$16)*E$10 -> 827801.64 | F50: =F$33*Inputs!$J69+(Inputs!$H69*F$15+Inputs!$I69*F$16)*F$10 -> 875832.69 | G50: =G$33*Inputs!$J69+(Inputs!$H69*G$15+Inputs!$I69*G$16)*G$10 -> 861105.82 | H50: =H$33*Inputs!$J69+(Inputs!$H69*H$15+Inputs!$I69*H$16)*H$10 -> 873691.33 | I50: x | K50: =C50/C$33 -> 0.0505 | L50: =C50/C$15 -> 8.112118 | M50: =C50/C$16 -> 11.58874 | O50: =D50/D$33 -> 0.049489705 | P50: =D50/D$15 -> 8.624274 | Q50: =D50/D$16 -> 11.499032 | S50: =E50/E$33 -> 0.048818114 | T50: =E50/E$15 -> 9.0717988 | U50: =E50/E$16 -> 11.48329 | W50: =F50/F$33 -> 0.047550514 | X50: =F50/F$15 -> 9.5981665 | Y50: =F50/F$16 -> 11.849588 | AA50: =G50/G$33 -> 0.048825623 | AB50: =G50/G$15 -> 9.4367761 | AC50: =G50/G$16 -> 11.945286 | AE50: =H50/H$33 -> 0.049269601 | AF50: =H50/H$15 -> 9.5746995 | AG50: =H50/H$16 -> 11.968374
B51: Royalty Fees | C51: =C$33*Inputs!$J70+(Inputs!$H70*C$15+Inputs!$I70*C$16)*C$10 -> 0 | D51: =D$33*Inputs!$J70+(Inputs!$H70*D$15+Inputs!$I70*D$16)*D$10 -> 0 | E51: =E$33*Inputs!$J70+(Inputs!$H70*E$15+Inputs!$I70*E$16)*E$10 -> 0 | F51: =F$33*Inputs!$J70+(Inputs!$H70*F$15+Inputs!$I70*F$16)*F$10 -> 0 | G51: =G$33*Inputs!$J70+(Inputs!$H70*G$15+Inputs!$I70*G$16)*G$10 -> 0 | H51: =H$33*Inputs!$J70+(Inputs!$H70*H$15+Inputs!$I70*H$16)*H$10 -> 0 | I51: x | K51: =C51/C$33 -> 0 | L51: =C51/C$15 -> 0 | M51: =C51/C$16 -> 0 | O51: =D51/D$33 -> 0 | P51: =D51/D$15 -> 0 | Q51: =D51/D$16 -> 0 | S51: =E51/E$33 -> 0 | T51: =E51/E$15 -> 0 | U51: =E51/E$16 -> 0 | W51: =F51/F$33 -> 0 | X51: =F51/F$15 -> 0 | Y51: =F51/F$16 -> 0 | AA51: =G51/G$33 -> 0 | AB51: =G51/G$15 -> 0 | AC51: =G51/G$16 -> 0 | AE51: =H51/H$33 -> 0 | AF51: =H51/H$15 -> 0 | AG51: =H51/H$16 -> 0
B52: Repairs & Maintenance | C52: =C$33*Inputs!$J71+(Inputs!$H71*C$15+Inputs!$I71*C$16)*C$10 -> 739497.87 | D52: =D$33*Inputs!$J71+(Inputs!$H71*D$15+Inputs!$I71*D$16)*D$10 -> 780423.67 | E52: =E$33*Inputs!$J71+(Inputs!$H71*E$15+Inputs!$I71*E$16)*E$10 -> 816306.03 | F52: =F$33*Inputs!$J71+(Inputs!$H71*F$15+Inputs!$I71*F$16)*F$10 -> 863514.75 | G52: =G$33*Inputs!$J71+(Inputs!$H71*G$15+Inputs!$I71*G$16)*G$10 -> 849131.89 | H52: =H$33*Inputs!$J71+(Inputs!$H71*H$15+Inputs!$I71*H$16)*H$10 -> 859068.75 | I52: x | K52: =C52/C$33 -> 0.05045 | L52: =C52/C$15 -> 8.1040862 | M52: =C52/C$16 -> 11.577266 | O52: =D52/D$33 -> 0.049078342 | P52: =D52/D$15 -> 8.5525881 | Q52: =D52/D$16 -> 11.403451 | S52: =E52/E$33 -> 0.048140181 | T52: =E52/E$15 -> 8.9458195 | U52: =E52/E$16 -> 11.323822 | W52: =F52/F$33 -> 0.046881752 | X52: =F52/F$15 -> 9.4631754 | Y52: =F52/F$16 -> 11.682933 | AA52: =G52/G$33 -> 0.048146688 | AB52: =G52/G$15 -> 9.305555 | AC52: =G52/G$16 -> 11.779184 | AE52: =H52/H$33 -> 0.048444998 | AF52: =H52/H$15 -> 9.4144521 | AG52: =H52/H$16 -> 11.768065
B53: Utilities | C53: =C$33*Inputs!$J72+(Inputs!$H72*C$15+Inputs!$I72*C$16)*C$10 -> 593357.26 | D53: =D$33*Inputs!$J72+(Inputs!$H72*D$15+Inputs!$I72*D$16)*D$10 -> 635680.93 | E53: =E$33*Inputs!$J72+(Inputs!$H72*E$15+Inputs!$I72*E$16)*E$10 -> 672634.45 | F53: =F$33*Inputs!$J72+(Inputs!$H72*F$15+Inputs!$I72*F$16)*F$10 -> 710401.73 | G53: =G$33*Inputs!$J72+(Inputs!$H72*G$15+Inputs!$I72*G$16)*G$10 -> 699719.92 | H53: =H$33*Inputs!$J72+(Inputs!$H72*H$15+Inputs!$I72*H$16)*H$10 -> 712916.42 | I53: x | K53: =C53/C$33 -> 0.04048 | L53: =C53/C$15 -> 6.5025453 | M53: =C53/C$16 -> 9.2893504 | O53: =D53/D$33 -> 0.039975935 | P53: =D53/D$15 -> 6.9663664 | Q53: =D53/D$16 -> 9.2884885 | S53: =E53/E$33 -> 0.039667407 | T53: =E53/E$15 -> 7.3713364 | U53: =E53/E$16 -> 9.3308056 | W53: =F53/F$33 -> 0.038568973 | X53: =F53/F$15 -> 7.7852244 | Y53: =F53/F$16 -> 9.6113881 | AA53: =G53/G$33 -> 0.039674869 | AB53: =G53/G$15 -> 7.6681635 | AC53: =G53/G$16 -> 9.706536 | AE53: =H53/H$33 -> 0.040203109 | AF53: =H53/H$15 -> 7.8127827 | AG53: =H53/H$16 -> 9.7659784
B54: TOTAL UNDISTRIBUTED | C54: =SUM(C49:C53) -> 3559410.6 | D54: =SUM(D49:D53) -> 3747632.7 | E54: =SUM(E49:E53) -> 3914313.4 | F54: =SUM(F49:F53) -> 4112962 | G54: =SUM(G49:G53) -> 4071904 | H54: =SUM(H49:H53) -> 4133175.5 | I54: x | K54: =C54/C$33 -> 0.24283 | L54: =C54/C$15 -> 39.00724 | M54: =C54/C$16 -> 55.724628 | O54: =D54/D$33 -> 0.2356766 | P54: =D54/D$15 -> 41.069947 | Q54: =D54/D$16 -> 54.759929 | S54: =E54/E$33 -> 0.2308396 | T54: =E54/E$15 -> 42.896585 | U54: =E54/E$16 -> 54.299475 | W54: =F54/F$33 -> 0.22330002 | X54: =F54/F$15 -> 45.073556 | Y54: =F54/F$16 -> 55.646366 | AA54: =G54/G$33 -> 0.23088132 | AB54: =G54/G$15 -> 44.623606 | AC54: =G54/G$16 -> 56.485577 | AE54: =H54/H$33 -> 0.23307992 | AF54: =H54/H$15 -> 45.295074 | AG54: =H54/H$16 -> 56.618843
B56: HOUSE PROFIT | C56: =C46-C54 -> 4710226 | D56: =D46-D54 -> 5388245.9 | E56: =E46-E54 -> 5707230.2 | F56: =F46-F54 -> 6161657.8 | G56: =G46-G54 -> 5914194.7 | H56: =H46-H54 -> 6113523.8 | I56: x | K56: =C56/C$33 -> 0.32134089 | L56: =C56/C$15 -> 51.618915 | M56: =C56/C$16 -> 73.741308 | O56: =D56/D$33 -> 0.3388495 | P56: =D56/D$15 -> 59.04927 | Q56: =D56/D$16 -> 78.73236 | S56: =E56/E$33 -> 0.33657364 | T56: =E56/E$15 -> 62.544988 | U56: =E56/E$16 -> 79.170871 | W56: =F56/F$33 -> 0.33452736 | X56: =F56/F$15 -> 67.525017 | Y56: =F56/F$16 -> 83.364219 | AA56: =G56/G$33 -> 0.33534118 | AB56: =G56/G$15 -> 64.813093 | AC56: =G56/G$16 -> 82.04189 | AE56: =H56/H$33 -> 0.34475663 | AF56: =H56/H$15 -> 66.997521 | AG56: =H56/H$16 -> 83.746901
B58: Base Management Fee | C58: =C$33*Inputs!$J73+(Inputs!$H73*C$15+Inputs!$I73*C$16)*C$10 -> 366450.88 | D58: =D$33*Inputs!$J73+(Inputs!$H73*D$15+Inputs!$I73*D$16)*D$10 -> 397539.75 | E58: =E$33*Inputs!$J73+(Inputs!$H73*E$15+Inputs!$I73*E$16)*E$10 -> 423921.36 | F58: =F$33*Inputs!$J73+(Inputs!$H73*F$15+Inputs!$I73*F$16)*F$10 -> 460474.88 | G58: =G$33*Inputs!$J73+(Inputs!$H73*G$15+Inputs!$I73*G$16)*G$10 -> 440908.78 | H58: =H$33*Inputs!$J73+(Inputs!$H73*H$15+Inputs!$I73*H$16)*H$10 -> 443321.7 | I58: x | K58: =C58/C$33 -> 0.025 | L58: =C58/C$15 -> 4.0159 | M58: =C58/C$16 -> 5.737 | O58: =D58/D$33 -> 0.025 | P58: =D58/D$15 -> 4.3566 | Q58: =D58/D$16 -> 5.8088 | S58: =E58/E$33 -> 0.025 | T58: =E58/E$15 -> 4.6457135 | U58: =E58/E$16 -> 5.88065 | W58: =F58/F$33 -> 0.025 | X58: =F58/F$15 -> 5.0463 | Y58: =F58/F$16 -> 6.23 | AA58: =G58/G$33 -> 0.025 | AB58: =G58/G$15 -> 4.831877 | AC58: =G58/G$16 -> 6.1163 | AE58: =H58/H$33 -> 0.025 | AF58: =H58/H$15 -> 4.85832 | AG58: =H58/H$16 -> 6.0729
B59: Incentive Management Fee | C59: =C$33*Inputs!$J74+(Inputs!$H74*C$15+Inputs!$I74*C$16)*C$10 -> 0 | D59: =D$33*Inputs!$J74+(Inputs!$H74*D$15+Inputs!$I74*D$16)*D$10 -> 0 | E59: =E$33*Inputs!$J74+(Inputs!$H74*E$15+Inputs!$I74*E$16)*E$10 -> 0 | F59: =F$33*Inputs!$J74+(Inputs!$H74*F$15+Inputs!$I74*F$16)*F$10 -> 0 | G59: =G$33*Inputs!$J74+(Inputs!$H74*G$15+Inputs!$I74*G$16)*G$10 -> 0 | H59: =H$33*Inputs!$J74+(Inputs!$H74*H$15+Inputs!$I74*H$16)*H$10 -> 0 | I59: x | K59: =C59/C$33 -> 0 | L59: =C59/C$15 -> 0 | M59: =C59/C$16 -> 0 | O59: =D59/D$33 -> 0 | P59: =D59/D$15 -> 0 | Q59: =D59/D$16 -> 0 | S59: =E59/E$33 -> 0 | T59: =E59/E$15 -> 0 | U59: =E59/E$16 -> 0 | W59: =F59/F$33 -> 0 | X59: =F59/F$15 -> 0 | Y59: =F59/F$16 -> 0 | AA59: =G59/G$33 -> 0 | AB59: =G59/G$15 -> 0 | AC59: =G59/G$16 -> 0 | AE59: =H59/H$33 -> 0 | AF59: =H59/H$15 -> 0 | AG59: =H59/H$16 -> 0
B60: INCOME BEFORE FIXED | C60: =C56-SUM(C58:C59) -> 4343775.1 | D60: =D56-SUM(D58:D59) -> 4990706.1 | E60: =E56-SUM(E58:E59) -> 5283308.8 | F60: =F56-SUM(F58:F59) -> 5701182.9 | G60: =G56-SUM(G58:G59) -> 5473286 | H60: =H56-SUM(H58:H59) -> 5670202.1 | I60: x | K60: =C60/C$33 -> 0.29634089 | L60: =C60/C$15 -> 47.603015 | M60: =C60/C$16 -> 68.004308 | O60: =D60/D$33 -> 0.3138495 | P60: =D60/D$15 -> 54.69267 | Q60: =D60/D$16 -> 72.92356 | S60: =E60/E$33 -> 0.31157364 | T60: =E60/E$15 -> 57.899275 | U60: =E60/E$16 -> 73.290221 | W60: =F60/F$33 -> 0.30952736 | X60: =F60/F$15 -> 62.478717 | Y60: =F60/F$16 -> 77.134219 | AA60: =G60/G$33 -> 0.31034118 | AB60: =G60/G$15 -> 59.981216 | AC60: =G60/G$16 -> 75.92559 | AE60: =H60/H$33 -> 0.31975663 | AF60: =H60/H$15 -> 62.139201 | AG60: =H60/H$16 -> 77.674001
B62: FIXED EXPENSES
B63: Real Estate & Property Taxes | C63: =C$33*Inputs!$J78+(Inputs!$H78*C$15+Inputs!$I78*C$16)*C$10 -> 598047.83 | D63: =D$33*Inputs!$J78+(Inputs!$H78*D$15+Inputs!$I78*D$16)*D$10 -> 610008.78 | E63: =E$33*Inputs!$J78+(Inputs!$H78*E$15+Inputs!$I78*E$16)*E$10 -> 622208.96 | F63: =F$33*Inputs!$J78+(Inputs!$H78*F$15+Inputs!$I78*F$16)*F$10 -> 634653.14 | G63: =G$33*Inputs!$J78+(Inputs!$H78*G$15+Inputs!$I78*G$16)*G$10 -> 647346.2 | H63: =H$33*Inputs!$J78+(Inputs!$H78*H$15+Inputs!$I78*H$16)*H$10 -> 660293.13 | I63: x | K63: =C63/C$33 -> 0.0408 | L63: =C63/C$15 -> 6.5539488 | M63: =C63/C$16 -> 9.362784 | O63: =D63/D$33 -> 0.038361496 | P63: =D63/D$15 -> 6.6850278 | Q63: =D63/D$16 -> 8.9133704 | S63: =E63/E$33 -> 0.036693655 | T63: =E63/E$15 -> 6.8187283 | U63: =E63/E$16 -> 8.6313017 | W63: =F63/F$33 -> 0.034456448 | X63: =F63/F$15 -> 6.9551029 | Y63: =F63/F$16 -> 8.5865468 | AA63: =G63/G$33 -> 0.036705223 | AB63: =G63/G$15 -> 7.094205 | AC63: =G63/G$16 -> 8.9800063 | AE63: =H63/H$33 -> 0.037235552 | AF63: =H63/H$15 -> 7.2360891 | AG63: =H63/H$16 -> 9.0451113
B64: Insurance | C64: =C$33*Inputs!$J79+(Inputs!$H79*C$15+Inputs!$I79*C$16)*C$10 -> 89707.174 | D64: =D$33*Inputs!$J79+(Inputs!$H79*D$15+Inputs!$I79*D$16)*D$10 -> 91501.318 | E64: =E$33*Inputs!$J79+(Inputs!$H79*E$15+Inputs!$I79*E$16)*E$10 -> 93331.344 | F64: =F$33*Inputs!$J79+(Inputs!$H79*F$15+Inputs!$I79*F$16)*F$10 -> 95197.971 | G64: =G$33*Inputs!$J79+(Inputs!$H79*G$15+Inputs!$I79*G$16)*G$10 -> 97101.93 | H64: =H$33*Inputs!$J79+(Inputs!$H79*H$15+Inputs!$I79*H$16)*H$10 -> 99043.969 | I64: x | K64: =C64/C$33 -> 0.00612 | L64: =C64/C$15 -> 0.98309232 | M64: =C64/C$16 -> 1.4044176 | O64: =D64/D$33 -> 0.0057542244 | P64: =D64/D$15 -> 1.0027542 | Q64: =D64/D$16 -> 1.3370056 | S64: =E64/E$33 -> 0.0055040482 | T64: =E64/E$15 -> 1.0228092 | U64: =E64/E$16 -> 1.2946953 | W64: =F64/F$33 -> 0.0051684672 | X64: =F64/F$15 -> 1.0432654 | Y64: =F64/F$16 -> 1.287982 | AA64: =G64/G$33 -> 0.0055057835 | AB64: =G64/G$15 -> 1.0641307 | AC64: =G64/G$16 -> 1.3470009 | AE64: =H64/H$33 -> 0.0055853328 | AF64: =H64/H$15 -> 1.0854134 | AG64: =H64/H$16 -> 1.3567667
B65: Rent | C65: =C$33*Inputs!$J80+(Inputs!$H80*C$15+Inputs!$I80*C$16)*C$10 -> 112133.97 | D65: =D$33*Inputs!$J80+(Inputs!$H80*D$15+Inputs!$I80*D$16)*D$10 -> 114376.65 | E65: =E$33*Inputs!$J80+(Inputs!$H80*E$15+Inputs!$I80*E$16)*E$10 -> 116664.18 | F65: =F$33*Inputs!$J80+(Inputs!$H80*F$15+Inputs!$I80*F$16)*F$10 -> 118997.46 | G65: =G$33*Inputs!$J80+(Inputs!$H80*G$15+Inputs!$I80*G$16)*G$10 -> 121377.41 | H65: =H$33*Inputs!$J80+(Inputs!$H80*H$15+Inputs!$I80*H$16)*H$10 -> 123804.96 | I65: x | K65: =C65/C$33 -> 0.00765 | L65: =C65/C$15 -> 1.2288654 | M65: =C65/C$16 -> 1.755522 | O65: =D65/D$33 -> 0.0071927805 | P65: =D65/D$15 -> 1.2534427 | Q65: =D65/D$16 -> 1.6712569 | S65: =E65/E$33 -> 0.0068800603 | T65: =E65/E$15 -> 1.2785116 | U65: =E65/E$16 -> 1.6183691 | W65: =F65/F$33 -> 0.006460584 | X65: =F65/F$15 -> 1.3040818 | Y65: =F65/F$16 -> 1.6099775 | AA65: =G65/G$33 -> 0.0068822294 | AB65: =G65/G$15 -> 1.3301634 | AC65: =G65/G$16 -> 1.6837512 | AE65: =H65/H$33 -> 0.006981666 | AF65: =H65/H$15 -> 1.3567667 | AG65: =H65/H$16 -> 1.6959584
B66: TOTAL FIXED EXPENSES | C66: =SUM(C63:C65) -> 799888.97 | D66: =SUM(D63:D65) -> 815886.75 | E66: =SUM(E63:E65) -> 832204.48 | F66: =SUM(F63:F65) -> 848848.57 | G66: =SUM(G63:G65) -> 865825.55 | H66: =SUM(H63:H65) -> 883142.06 | I66: x | K66: =C66/C$33 -> 0.05457 | L66: =C66/C$15 -> 8.7659065 | M66: =C66/C$16 -> 12.522724 | O66: =D66/D$33 -> 0.051308501 | P66: =D66/D$15 -> 8.9412247 | Q66: =D66/D$16 -> 11.921633 | S66: =E66/E$33 -> 0.049077764 | T66: =E66/E$15 -> 9.1200491 | U66: =E66/E$16 -> 11.544366 | W66: =F66/F$33 -> 0.046085499 | X66: =F66/F$15 -> 9.3024501 | Y66: =F66/F$16 -> 11.484506 | AA66: =G66/G$33 -> 0.049093236 | AB66: =G66/G$15 -> 9.4884991 | AC66: =G66/G$16 -> 12.010758 | AE66: =H66/H$33 -> 0.049802551 | AF66: =H66/H$15 -> 9.6782691 | AG66: =H66/H$16 -> 12.097836
B68: EBITDA | C68: =C60-C66 -> 3543886.2 | D68: =D60-D66 -> 4174819.4 | E68: =E60-E66 -> 4451104.3 | F68: =F60-F66 -> 4852334.4 | G68: =G60-G66 -> 4607460.4 | H68: =H60-H66 -> 4787060 | I68: x | K68: =C68/C$33 -> 0.24177089 | L68: =C68/C$15 -> 38.837109 | M68: =C68/C$16 -> 55.481584 | O68: =D68/D$33 -> 0.262541 | P68: =D68/D$15 -> 45.751445 | Q68: =D68/D$16 -> 61.001927 | S68: =E68/E$33 -> 0.26249588 | T68: =E68/E$15 -> 48.779226 | U68: =E68/E$16 -> 61.745855 | W68: =F68/F$33 -> 0.26344186 | X68: =F68/F$15 -> 53.176267 | Y68: =F68/F$16 -> 65.649712 | AA68: =G68/G$33 -> 0.26124794 | AB68: =G68/G$15 -> 50.492717 | AC68: =G68/G$16 -> 63.914832 | AE68: =H68/H$33 -> 0.26995408 | AF68: =H68/H$15 -> 52.460932 | AG68: =H68/H$16 -> 65.576165
B70: CAPITAL EXPENDITURES
B71: FF&E Reserve | C71: =C$33*Inputs!$J83+(Inputs!$H83*C$15+Inputs!$I83*C$16)*C$10 -> 586321.4 | D71: =D$33*Inputs!$J83+(Inputs!$H83*D$15+Inputs!$I83*D$16)*D$10 -> 636063.6 | E71: =E$33*Inputs!$J83+(Inputs!$H83*E$15+Inputs!$I83*E$16)*E$10 -> 678274.17 | F71: =F$33*Inputs!$J83+(Inputs!$H83*F$15+Inputs!$I83*F$16)*F$10 -> 736759.8 | G71: =G$33*Inputs!$J83+(Inputs!$H83*G$15+Inputs!$I83*G$16)*G$10 -> 705454.04 | H71: =H$33*Inputs!$J83+(Inputs!$H83*H$15+Inputs!$I83*H$16)*H$10 -> 709314.72 | I71: x | K71: =C71/C$33 -> 0.04 | L71: =C71/C$15 -> 6.42544 | M71: =C71/C$16 -> 9.1792 | O71: =D71/D$33 -> 0.04 | P71: =D71/D$15 -> 6.97056 | Q71: =D71/D$16 -> 9.29408 | S71: =E71/E$33 -> 0.04 | T71: =E71/E$15 -> 7.4331416 | U71: =E71/E$16 -> 9.40904 | W71: =F71/F$33 -> 0.04 | X71: =F71/F$15 -> 8.07408 | Y71: =F71/F$16 -> 9.968 | AA71: =G71/G$33 -> 0.04 | AB71: =G71/G$15 -> 7.7310032 | AC71: =G71/G$16 -> 9.78608 | AE71: =H71/H$33 -> 0.04 | AF71: =H71/H$15 -> 7.773312 | AG71: =H71/H$16 -> 9.71664
B72: TOTAL CAP EXPENDITURES | C72: =SUM(C71) -> 586321.4 | D72: =SUM(D71) -> 636063.6 | E72: =SUM(E71) -> 678274.17 | F72: =SUM(F71) -> 736759.8 | G72: =SUM(G71) -> 705454.04 | H72: =SUM(H71) -> 709314.72 | I72: x | K72: =C72/C$33 -> 0.04 | L72: =C72/C$15 -> 6.42544 | M72: =C72/C$16 -> 9.1792 | O72: =D72/D$33 -> 0.04 | P72: =D72/D$15 -> 6.97056 | Q72: =D72/D$16 -> 9.29408 | S72: =E72/E$33 -> 0.04 | T72: =E72/E$15 -> 7.4331416 | U72: =E72/E$16 -> 9.40904 | W72: =F72/F$33 -> 0.04 | X72: =F72/F$15 -> 8.07408 | Y72: =F72/F$16 -> 9.968 | AA72: =G72/G$33 -> 0.04 | AB72: =G72/G$15 -> 7.7310032 | AC72: =G72/G$16 -> 9.78608 | AE72: =H72/H$33 -> 0.04 | AF72: =H72/H$15 -> 7.773312 | AG72: =H72/H$16 -> 9.71664
B74: NOI | C74: =C68-C72 -> 2957564.8 | D74: =D68-D72 -> 3538755.8 | E74: =E68-E72 -> 3772830.2 | F74: =F68-F72 -> 4115574.6 | G74: =G68-G72 -> 3902006.4 | H74: =H68-H72 -> 4077745.3 | I74: x | K74: =C74/C$33 -> 0.20177089 | L74: =C74/C$15 -> 32.411669 | M74: =C74/C$16 -> 46.302384 | O74: =D74/D$33 -> 0.222541 | P74: =D74/D$15 -> 38.780885 | Q74: =D74/D$16 -> 51.707847 | S74: =E74/E$33 -> 0.22249588 | T74: =E74/E$15 -> 41.346084 | U74: =E74/E$16 -> 52.336815 | W74: =F74/F$33 -> 0.22344186 | X74: =F74/F$15 -> 45.102187 | Y74: =F74/F$16 -> 55.681712 | AA74: =G74/G$33 -> 0.22124794 | AB74: =G74/G$15 -> 42.761714 | AC74: =G74/G$16 -> 54.128752 | AE74: =H74/H$33 -> 0.22995408 | AF74: =H74/H$15 -> 44.68762 | AG74: =H74/H$16 -> 55.859525
B76: Before Debt Service Cash Flow (BDSCF) | C76: =C74 -> 2957564.8 | D76: =D74 -> 3538755.8 | E76: =E74 -> 3772830.2 | F76: =F74 -> 4115574.6 | G76: =G74 -> 3902006.4 | H76: =H74 -> 4077745.3 | I76: x | K76: =C76/C$33 -> 0.20177089 | L76: =C76/C$15 -> 32.411669 | M76: =C76/C$16 -> 46.302384 | O76: =D76/D$33 -> 0.222541 | P76: =D76/D$15 -> 38.780885 | Q76: =D76/D$16 -> 51.707847 | S76: =E76/E$33 -> 0.22249588 | T76: =E76/E$15 -> 41.346084 | U76: =E76/E$16 -> 52.336815 | W76: =F76/F$33 -> 0.22344186 | X76: =F76/F$15 -> 45.102187 | Y76: =F76/F$16 -> 55.681712 | AA76: =G76/G$33 -> 0.22124794 | AB76: =G76/G$15 -> 42.761714 | AC76: =G76/G$16 -> 54.128752 | AE76: =H76/H$33 -> 0.22995408 | AF76: =H76/H$15 -> 44.68762 | AG76: =H76/H$16 -> 55.859525

Sheet Valuation
B2: =Inputs!B2 -> Comparing Complex Deal Structures
B4: Model: Valuation | C4: Scenario in Model: | E4: =Scenario!E4 -> Best Case
C7: Years
C8: =NOI!C8 -> 2021 | D8: =NOI!D8 -> 2022 | E8: =NOI!E8 -> 2023 | F8: =NOI!F8 -> 2024 | G8: =NOI!G8 -> 2025 | H8: =NOI!H8 -> 2026
B9: 0 | C9: 1 | D9: =C9+1 -> 2 | E9: =D9+1 -> 3 | F9: =E9+1 -> 4 | G9: =F9+1 -> 5 | H9: =G9+1 -> 6
B10: =NOI!B76 -> Before Debt Service Cash Flow (BDSCF)
B11: Hotel | C11: =NOI!C76 -> 2957564.8 | D11: =NOI!D76 -> 3538755.8 | E11: =NOI!E76 -> 3772830.2 | F11: =NOI!F76 -> 4115574.6 | G11: =NOI!G76 -> 3902006.4 | H11: =NOI!H76 -> 4077745.3 | I11: x
B13: Present Value Factor
B14: ="Hotel at "&TEXT(DiscountRateHotel,"0.00%") -> Hotel at 10.00% | C14: =1/(1+DiscountRateHotel)^C9 -> 0.90909091 | D14: =1/(1+DiscountRateHotel)^D9 -> 0.82644628 | E14: =1/(1+DiscountRateHotel)^E9 -> 0.7513148 | F14: =1/(1+DiscountRateHotel)^F9 -> 0.68301346 | G14: =1/(1+DiscountRateHotel)^G9 -> 0.62092132 | I14: x
B16: Present Value of Cash Flow
B17: Hotel | C17: =C11*C14 -> 2688695.3 | D17: =D11*D14 -> 2924591.6 | E17: =E11*E14 -> 2834583.1 | F17: =F11*F14 -> 2810992.8 | G17: =G11*G14 -> 2422839 | I17: x
B19: Resale Calculations:
B20: Hotel (as of the end of Yr. 5) | G20: =NOI!H76/TerminalCapRateHotel -> 47973474 | I20: x
B22: Selling Cost
B23: Hotel | G23: =G20*SellingCost -> 1439204.2 | I23: x
B25: Net Resale
B26: Hotel | G26: =G20-G23 -> 46534270 | I26: x
B29: Unlevered Value
B30: Hotel | D30: Share
B31: PV Cash flows | C31: =SUM(C17:G17) -> 13681702 | D31: =C31/$C$33 -> 0.32134909
B32: PV of Reversion | C32: =G26*G14 -> 28894121 | D32: =C32/$C$33 -> 0.67865091
B33: Total Unlevered Value | C33: =SUM(C31:C32) -> 42575822 | D33: =SUM(D31:D32) -> 1
B34: Unlevered Value Per Key | C34: =C33/NumberRooms -> 170303.29

Sheet Provided - CAP Acct. 1
F2: =Inputs!B2 -> Comparing Complex Deal Structures
F4: Model: Capital Accounts | I4: Scenario in Model: | K4: =Scenario!E4 -> Best Case | M4: Deal in Model: | O4: Case 1 - Eagle Investment & Fulcrum Capital
F6: SOURCES AND USES | O6: FINANCING ASSUMPTIONS
F8: USES | H8: $ | I8: Per Key | J8: SOURCES | L8: $ | M8: % | O8: CONSTRUCTION LOAN | S8: PERMANENT LOAN
F9: Land | H9: 5000000 | I9: =H9/NumberRooms -> 20000 | J9: Construction Loan | L9: =ConstLoanOBalance -> 12500000 | M9: =L9/H15 -> 0.42165409 | O9: Construction Loan Commitment | R9: 12500000 | S9: Permanent Loan Proceeds | V9: =V10/V11/V15 -> 35005242
F10: Soft Costs | H10: =SUM(Construction!D10:D13)+Construction!D26 -> 4600000 | I10: =H10/NumberRooms -> 18400 | J10: Preferred Equity | L10: =PreferredEquityOBalance -> 5000000 | M10: =L10/$H$15 -> 0.16866164 | O10: Loan Fees | R10: 0.01 | S10: NOI at Refi | V10: =INDEX($I$36:$CO$36,MATCH(V16,$I$28:$CO$28,FALSE)) -> 3772830.2
F11: Hard Costs | H11: =SUM(Construction!D14:D15,Construction!D25) -> 17570000 | I11: =H11/NumberRooms -> 70280 | J11: Common Equity | L11: =TotalUses-SUM(L9:L10) -> 12145153 | M11: =L11/$H$15 -> 0.40968427 | O11: Spread | R11: 0.045 | S11: DSCR | V11: 1.35
F12: Contingency and Escalation | H12: =SUM(Construction!D29:D30) -> 1350153 | I12: =H12/NumberRooms -> 5400.612 | J12: Sponsor | L12: =M12*$L$11 -> 1214515.3 | M12: 0.1 | O12: Origination | R12: =H18 -> 44196 | S12: Loan Fees | V12: 0.01
F13: Interest Reserve | H13: 1000000 | I13: =H13/NumberRooms -> 4000 | J13: Co-Investor | L13: =M13*$L$11 -> 10930638 | M13: =1-M12 -> 0.9 | O13: Maturity | Q13: 3 | R13: =EOMONTH(R12,Q13*12) -> 45291 | S13: Rate | V13: 0.07
F14: Loan Fees | H14: =R10*L9 -> 125000 | I14: =H14/NumberRooms -> 500 | O14: Type | R14: 360 | S14: Amortization (Years) | V14: 30
F15: Total Uses | H15: =SUM(H9:H14) -> 29645153 | I15: =H15/NumberRooms -> 118580.61 | J15: Total Sources | L15: =SUM(L9:L11) -> 29645153 | M15: =SUM(M9:M11) -> 1 | O15: Extension Fee | R15: 0.005 | S15: Mortgage Constant (%) | V15: =PMT(V13/12,V14*12,-1)*12 -> 0.079836299
O16: Exercise Extension? | Q16: DON’T EDIT | R16: =($Q$13=4)*1 -> 0 | S16: Origination | V16: =R13 -> 45291
F17: SCENARIO | J17: Exit Cap Rate | L17: =TerminalCapRateHotel -> 0.085 | O17: Extension Date | R17: =EOMONTH(R13,-12)*R16 -> 0 | S17: Maturity | T17: DON’T EDIT | U17: =DATEDIF(R13,V17,"y") -> 3 | V17: =ExitDate -> 46387
F18: Closing | H18: =Inputs!C11-1 -> 44196 | J18: Sales Costs | L18: =SellingCost -> 0.03 | O18: PREFERRED EQUITY | S18: Prepayment Fee | V18: 0.01
F19: Opening | H19: =EOMONTH(Construction!AC7,1) -> 44957 | J19: Gross Sales Proceeds | L19: =SUM(I52:CO52) -> 47973474 | O19: Preferred Equity | R19: 5000000 | S19: Prepay Loan? | U19: DON’T EDIT | V19: =IF(U17<=2, 1, 0) -> 0
F20: Sale Date | H20: =DATE(YEAR(H18) + HoldingPeriod + 1, MONTH(H18), DAY(H18)) -> 46387 | J20: Price per Key | L20: =L19/NumberRooms -> 191893.9 | O20: Preferred Equity Return | R20: 0.09
F22: Funding | H22: Position | I22: Weight
F23: =J11 -> Common Equity | H23: 1 | I23: 1
F24: =J10 -> Preferred Equity | H24: 2 | I24: 1
F25: =J9 -> Construction Loan | H25: 3 | I25: 1
H27: Year | I27: =YEAR(I28) -> 2020 | J27: =YEAR(J28) -> 2021 | K27: =YEAR(K28) -> 2021 | L27: =YEAR(L28) -> 2021 | M27: =YEAR(M28) -> 2021 | N27: =YEAR(N28) -> 2021 | O27: =YEAR(O28) -> 2021 | P27: =YEAR(P28) -> 2021 | ... CO27: =YEAR(CO28) -> 2027 | CP27: x
H28: Date | I28: =H18 -> 44196 | J28: =EOMONTH(I28,1) -> 44227 | K28: =EOMONTH(J28,1) -> 44255 | L28: =EOMONTH(K28,1) -> 44286 | M28: =EOMONTH(L28,1) -> 44316 | N28: =EOMONTH(M28,1) -> 44347 | O28: =EOMONTH(N28,1) -> 44377 | P28: =EOMONTH(O28,1) -> 44408 | Q28: =EOMONTH(P28,1) -> 44439 | ... CO28: =EOMONTH(CN28,1) -> 46752 | CP28: x
B29: Sum | C29: Comments | D29: Sign | H29: Days | I29: 31 | J29: =J28-I28 -> 31 | K29: =K28-J28 -> 28 | L29: =L28-K28 -> 31 | M29: =M28-L28 -> 30 | N29: =N28-M28 -> 31 | O29: =O28-N28 -> 30 | P29: =P28-O28 -> 31 | Q29: =Q28-P28 -> 31 | ... CO29: =CO28-CN28 -> 31 | CP29: x
F31: Cash Flows to Equity
C32: HINT: Index, Match, AND IFERROR functions will be helpful here.
C33: Make sure to divide by 12 for monthly! | D33: + | F33: Net Operating Income Hotel | I33: =IFERROR(INDEX(NOI!$C$76:$H$76,MATCH(I27,NOI!$C$8:$H$8,0))/12,0) -> 0 | J33: =IFERROR(INDEX(NOI!$C$76:$H$76,MATCH(J27,NOI!$C$8:$H$8,0))/12,0) -> 246463.73 | K33: =IFERROR(INDEX(NOI!$C$76:$H$76,MATCH(K27,NOI!$C$8:$H$8,0))/12,0) -> 246463.73 | L33: =IFERROR(INDEX(NOI!$C$76:$H$76,MATCH(L27,NOI!$C$8:$H$8,0))/12,0) -> 246463.73 | M33: =IFERROR(INDEX(NOI!$C$76:$H$76,MATCH(M27,NOI!$C$8:$H$8,0))/12,0) -> 246463.73 | N33: =IFERROR(INDEX(NOI!$C$76:$H$76,MATCH(N27,NOI!$C$8:$H$8,0))/12,0) -> 246463.73 | O33: =IFERROR(INDEX(NOI!$C$76:$H$76,MATCH(O27,NOI!$C$8:$H$8,0))/12,0) -> 246463.73 | P33: =IFERROR(INDEX(NOI!$C$76:$H$76,MATCH(P27,NOI!$C$8:$H$8,0))/12,0) -> 246463.73 | ... CO33: =IFERROR(INDEX(NOI!$C$76:$H$76,MATCH(CO27,NOI!$C$8:$H$8,0))/12,0) -> 0 | CP33: x
D35: + | F35: Selected Net Operating Income | I35: =(Today>=OpeningDate)*(Today<=ExitDate)*I33 -> 0 | J35: =(Today>=OpeningDate)*(Today<=ExitDate)*J33 -> 0 | K35: =(Today>=OpeningDate)*(Today<=ExitDate)*K33 -> 0 | L35: =(Today>=OpeningDate)*(Today<=ExitDate)*L33 -> 0 | M35: =(Today>=OpeningDate)*(Today<=ExitDate)*M33 -> 0 | N35: =(Today>=OpeningDate)*(Today<=ExitDate)*N33 -> 0 | O35: =(Today>=OpeningDate)*(Today<=ExitDate)*O33 -> 0 | P35: =(Today>=OpeningDate)*(Today<=ExitDate)*P33 -> 0 | ... CO35: =(Today>=OpeningDate)*(Today<=ExitDate)*CO33 -> 0 | CP35: x
C36: HINT: TTM = Trailing 12 month (OFFSET Function will be helpful here) | D36: + | F36: TTM NOI | I36: =IF(Today<OpeningDate,0,SUM(OFFSET(I35,,0,1,-12))) -> 0 | J36: =IF(Today<OpeningDate,0,SUM(OFFSET(J35,,0,1,-12))) -> 0 | K36: =IF(Today<OpeningDate,0,SUM(OFFSET(K35,,0,1,-12))) -> 0 | L36: =IF(Today<OpeningDate,0,SUM(OFFSET(L35,,0,1,-12))) -> 0 | M36: =IF(Today<OpeningDate,0,SUM(OFFSET(M35,,0,1,-12))) -> 0 | N36: =IF(Today<OpeningDate,0,SUM(OFFSET(N35,,0,1,-12))) -> 0 | O36: =IF(Today<OpeningDate,0,SUM(OFFSET(O35,,0,1,-12))) -> 0 | P36: =IF(Today<OpeningDate,0,SUM(OFFSET(P35,,0,1,-12))) -> 0 | ... CO36: =IF(Today<OpeningDate,0,SUM(OFFSET(CO35,,0,1,-12))) -> 0 | CP36: x
B38: =SUM(I38:CO38) -> 15868156 | C38: HINT: There should be no NOI after sale date (cell G20) | D38: + | F38: Net Operating Income | I38: =I35 -> 0 | J38: =J35 -> 0 | K38: =K35 -> 0 | L38: =L35 -> 0 | M38: =M35 -> 0 | N38: =N35 -> 0 | O38: =O35 -> 0 | P38: =P35 -> 0 | ... CO38: =CO35 -> 0 | CP38: x
B39: =SUM(I39:CO39) -> -28520153 | C39: HINT: Link to "Construction Budget" tab | D39: – | F39: Unlevered Development Costs | I39: =-Construction!E32 -> -8050223.9 | J39: =-Construction!F32 -> -311434.77 | K39: =-Construction!G32 -> -311434.77 | L39: =-Construction!H32 -> -334774.57 | M39: =-Construction!I32 -> -317269.72 | N39: =-Construction!J32 -> -268256.14 | O39: =-Construction!K32 -> -455644.58 | P39: =-Construction!L32 -> -697211.51 | ... CO39: =-Construction!CK32 -> 0 | CP39: x
B40: =SUM(I40:CO40) -> -125000 | C40: HINT: These should be paid at closing (cell G18) | D40: – | F40: Loan Fees | I40: =-ConstLoanOFees*(Today=ClosingDate) -> -125000 | J40: =-ConstLoanOFees*(Today=ClosingDate) -> 0 | K40: =-ConstLoanOFees*(Today=ClosingDate) -> 0 | L40: =-ConstLoanOFees*(Today=ClosingDate) -> 0 | M40: =-ConstLoanOFees*(Today=ClosingDate) -> 0 | N40: =-ConstLoanOFees*(Today=ClosingDate) -> 0 | O40: =-ConstLoanOFees*(Today=ClosingDate) -> 0 | P40: =-ConstLoanOFees*(Today=ClosingDate) -> 0 | ... CO40: =-ConstLoanOFees*(Today=ClosingDate) -> 0 | CP40: x
B41: =SUM(I41:CO41) -> -197955.79 | D41: – | F41: Construction Period Interest Draws | I41: =-I97 -> 0 | J41: =-J97 -> 0 | K41: =-K97 -> 0 | L41: =-L97 -> 0 | M41: =-M97 -> 0 | N41: =-N97 -> 0 | O41: =-O97 -> 0 | P41: =-P97 -> 0 | ... CO41: =-CO97 -> 0 | CP41: x
B42: =SUM(I42:CO42) -> 5000000 | D42: + | F42: Preferred Equity Funding | I42: =I82 -> 0 | J42: =J82 -> 0 | K42: =K82 -> 0 | L42: =L82 -> 0 | M42: =M82 -> 0 | N42: =N82 -> 0 | O42: =O82 -> 0 | P42: =P82 -> 0 | ... CO42: =CO82 -> 0 | CP42: x
B43: =SUM(I43:CO43) -> 11697956 | D43: + | F43: Construction Loan Funding | I43: =I88 -> 0 | J43: =J88 -> 0 | K43: =K88 -> 0 | L43: =L88 -> 0 | M43: =M88 -> 0 | N43: =N88 -> 0 | O43: =O88 -> 0 | P43: =P88 -> 0 | ... CO43: =CO88 -> 0 | CP43: x
B44: =SUM(I44:CO44) -> -564113.48 | C44: HINT: Interest expense less $ funded by construction interest draws | D44: – | F44: Construction Loan Interest | I44: =-I96+I97 -> 0 | J44: =-J96+J97 -> 0 | K44: =-K96+K97 -> 0 | L44: =-L96+L97 -> 0 | M44: =-M96+M97 -> 0 | N44: =-N96+N97 -> 0 | O44: =-O96+O97 -> 0 | P44: =-P96+P97 -> 0 | ... CO44: =-CO96+CO97 -> 0 | CP44: x
B45: =SUM(I45:CO45) -> 0 | C45: HINT: Only payable if you refinance in Year 4 | D45: – | F45: Construction Loan Extension Payment | I45: =-ConstLoanExtensionDummy*(ConstLoanExtensionFee*I87)*(Today=ConstLoanExtensionDate) -> 0 | J45: =-ConstLoanExtensionDummy*(ConstLoanExtensionFee*J87)*(Today=ConstLoanExtensionDate) -> 0 | K45: =-ConstLoanExtensionDummy*(ConstLoanExtensionFee*K87)*(Today=ConstLoanExtensionDate) -> 0 | L45: =-ConstLoanExtensionDummy*(ConstLoanExtensionFee*L87)*(Today=ConstLoanExtensionDate) -> 0 | M45: =-ConstLoanExtensionDummy*(ConstLoanExtensionFee*M87)*(Today=ConstLoanExtensionDate) -> 0 | N45: =-ConstLoanExtensionDummy*(ConstLoanExtensionFee*N87)*(Today=ConstLoanExtensionDate) -> 0 | O45: =-ConstLoanExtensionDummy*(ConstLoanExtensionFee*O87)*(Today=ConstLoanExtensionDate) -> 0 | P45: =-ConstLoanExtensionDummy*(ConstLoanExtensionFee*P87)*(Today=ConstLoanExtensionDate) -> 0 | ... CO45: =-ConstLoanExtensionDummy*(ConstLoanExtensionFee*CO87)*(Today=ConstLoanExtensionDate) -> 0 | CP45: x
B46: =SUM(I46:CO46) -> -11697956 | D46: – | F46: Construction Loan Repayment | I46: =I89 -> 0 | J46: =J89 -> 0 | K46: =K89 -> 0 | L46: =L89 -> 0 | M46: =M89 -> 0 | N46: =N89 -> 0 | O46: =O89 -> 0 | P46: =P89 -> 0 | ... CO46: =CO89 -> 0 | CP46: x
B47: =SUM(I47:CO47) -> 35005242 | D47: + | F47: Permanent Loan Proceeds | I47: =I101 -> 0 | J47: =J101 -> 0 | K47: =K101 -> 0 | L47: =L101 -> 0 | M47: =M101 -> 0 | N47: =N101 -> 0 | O47: =O101 -> 0 | P47: =P101 -> 0 | ... CO47: =CO101 -> 0 | CP47: x
B48: =SUM(I48:CO48) -> -350052.42 | C48: HINT: Payable on origination of new loan | D48: – | F48: Permanent Loan Fees | I48: =-I47*PermanentLoanPoints -> 0 | J48: =-J47*PermanentLoanPoints -> 0 | K48: =-K47*PermanentLoanPoints -> 0 | L48: =-L47*PermanentLoanPoints -> 0 | M48: =-M47*PermanentLoanPoints -> 0 | N48: =-N47*PermanentLoanPoints -> 0 | O48: =-O47*PermanentLoanPoints -> 0 | P48: =-P47*PermanentLoanPoints -> 0 | ... CO48: =-CO47*PermanentLoanPoints -> 0 | CP48: x
F49: Permanent Loan Debt Service | I49: =-I109 -> 0 | J49: =-J109 -> 0 | K49: =-K109 -> 0 | L49: =-L109 -> 0 | M49: =-M109 -> 0 | N49: =-N109 -> 0 | O49: =-O109 -> 0 | P49: =-P109 -> 0 | ... CO49: =-CO109 -> 0 | CP49: x
B50: =SUM(I50:CO50) -> -33859508 | D50: – | F50: Permanent Loan Repayment | I50: =I103 -> 0 | J50: =J103 -> 0 | K50: =K103 -> 0 | L50: =L103 -> 0 | M50: =M103 -> 0 | N50: =N103 -> 0 | O50: =O103 -> 0 | P50: =P103 -> 0 | ... CO50: =CO103 -> 0 | CP50: x
B51: =SUM(I51:CO51) -> 0 | C51: HINT: Only payable if you refinance in Year 4 | D51: – | F51: Permanent Loan Prepayment Penalty | I51: =I50*PermanentLoanPPMTFee*PermanentLoanPPMTDummy -> 0 | J51: =J50*PermanentLoanPPMTFee*PermanentLoanPPMTDummy -> 0 | K51: =K50*PermanentLoanPPMTFee*PermanentLoanPPMTDummy -> 0 | L51: =L50*PermanentLoanPPMTFee*PermanentLoanPPMTDummy -> 0 | M51: =M50*PermanentLoanPPMTFee*PermanentLoanPPMTDummy -> 0 | N51: =N50*PermanentLoanPPMTFee*PermanentLoanPPMTDummy -> 0 | O51: =O50*PermanentLoanPPMTFee*PermanentLoanPPMTDummy -> 0 | P51: =P50*PermanentLoanPPMTFee*PermanentLoanPPMTDummy -> 0 | ... CO51: =CO50*PermanentLoanPPMTFee*PermanentLoanPPMTDummy -> 0 | CP51: x
B52: =SUM(I52:CO52) -> 47973474 | D52: + | F52: Gross Sales Proceeds | I52: =I36/TerminalCapRateHotel*(Today=ExitDate) -> 0 | J52: =J36/TerminalCapRateHotel*(Today=ExitDate) -> 0 | K52: =K36/TerminalCapRateHotel*(Today=ExitDate) -> 0 | L52: =L36/TerminalCapRateHotel*(Today=ExitDate) -> 0 | M52: =M36/TerminalCapRateHotel*(Today=ExitDate) -> 0 | N52: =N36/TerminalCapRateHotel*(Today=ExitDate) -> 0 | O52: =O36/TerminalCapRateHotel*(Today=ExitDate) -> 0 | P52: =P36/TerminalCapRateHotel*(Today=ExitDate) -> 0 | ... CO52: =CO36/TerminalCapRateHotel*(Today=ExitDate) -> 0 | CP52: x
B53: =SUM(I53:CO53) -> -1439204.2 | D53: – | F53: Sales Costs | I53: =-SellingCost*I52 -> 0 | J53: =-SellingCost*J52 -> 0 | K53: =-SellingCost*K52 -> 0 | L53: =-SellingCost*L52 -> 0 | M53: =-SellingCost*M52 -> 0 | N53: =-SellingCost*N52 -> 0 | O53: =-SellingCost*O52 -> 0 | P53: =-SellingCost*P52 -> 0 | ... CO53: =-SellingCost*CO52 -> 0 | CP53: x
B54: =SUM(I54:CO54) -> -5788496.4 | D54: – | F54: Preferred Equity Repayment | I54: =I83 -> 0 | J54: =J83 -> 0 | K54: =K83 -> 0 | L54: =L83 -> 0 | M54: =M83 -> 0 | N54: =N83 -> 0 | O54: =O83 -> 0 | P54: =P83 -> 0 | ... CO54: =CO83 -> 0 | CP54: x
B55: =SUM(I55:CO55) -> 24618323 | D55: + | F55: Total Cash Flows to Equity | I55: =SUM(I38:I54) -> -8175223.9 | J55: =SUM(J38:J54) -> -311434.77 | K55: =SUM(K38:K54) -> -311434.77 | L55: =SUM(L38:L54) -> -334774.57 | M55: =SUM(M38:M54) -> -317269.72 | N55: =SUM(N38:N54) -> -268256.14 | O55: =SUM(O38:O54) -> -455644.58 | P55: =SUM(P38:P54) -> -697211.51 | ... CO55: =SUM(CO38:CO54) -> 0 | CP55: x
C56: HINT: You'll need a MAX function here | D56: + | F56: Cumulative Equity Invested | I56: =MAX(H56-I55,0) -> 8175223.9 | J56: =MAX(I56-J55,0) -> 8486658.7 | K56: =MAX(J56-K55,0) -> 8798093.4 | L56: =MAX(K56-L55,0) -> 9132868 | M56: =MAX(L56-M55,0) -> 9450137.7 | N56: =MAX(M56-N55,0) -> 9718393.9 | O56: =MAX(N56-O55,0) -> 10174038 | P56: =MAX(O56-P55,0) -> 10871250 | ... CO56: =MAX(CN56-CO55,0) -> 0 | CP56: x
F58: Development Sources and Uses - CHECK
B59: =SUM(I59:CO59) -> -28520153 | D59: – | F59: Unlevered Development Costs | I59: =I39 -> -8050223.9 | J59: =J39 -> -311434.77 | K59: =K39 -> -311434.77 | L59: =L39 -> -334774.57 | M59: =M39 -> -317269.72 | N59: =N39 -> -268256.14 | O59: =O39 -> -455644.58 | P59: =P39 -> -697211.51 | ... CO59: =CO39 -> 0 | CP59: x
B60: =SUM(I60:CO60) -> -125000 | D60: – | F60: Loan Fees | I60: =I40 -> -125000 | J60: =J40 -> 0 | K60: =K40 -> 0 | L60: =L40 -> 0 | M60: =M40 -> 0 | N60: =N40 -> 0 | O60: =O40 -> 0 | P60: =P40 -> 0 | ... CO60: =CO40 -> 0 | CP60: x
B61: =SUM(I61:CO61) -> -197955.79 | D61: – | F61: Construction Period Interest Draws | I61: =I41 -> 0 | J61: =J41 -> 0 | K61: =K41 -> 0 | L61: =L41 -> 0 | M61: =M41 -> 0 | N61: =N41 -> 0 | O61: =O41 -> 0 | P61: =P41 -> 0 | ... CO61: =CO41 -> 0 | CP61: x
B62: =SUM(I62:CO62) -> 12145153 | D62: + | F62: Equity Funding | I62: =I76 -> 8175223.9 | J62: =J76 -> 311434.77 | K62: =K76 -> 311434.77 | L62: =L76 -> 334774.57 | M62: =M76 -> 317269.72 | N62: =N76 -> 268256.14 | O62: =O76 -> 455644.58 | P62: =P76 -> 697211.51 | ... CO62: =CO76 -> 0 | CP62: x
B63: =SUM(I63:CO63) -> 5000000 | D63: + | F63: Preferred Equity Funding | I63: =I42 -> 0 | J63: =J42 -> 0 | K63: =K42 -> 0 | L63: =L42 -> 0 | M63: =M42 -> 0 | N63: =N42 -> 0 | O63: =O42 -> 0 | P63: =P42 -> 0 | ... CO63: =CO42 -> 0 | CP63: x
B64: =SUM(I64:CO64) -> 11697956 | D64: + | F64: Construction Loan Funding | I64: =I43 -> 0 | J64: =J43 -> 0 | K64: =K43 -> 0 | L64: =L43 -> 0 | M64: =M43 -> 0 | N64: =N43 -> 0 | O64: =O43 -> 0 | P64: =P43 -> 0 | ... CO64: =CO43 -> 0 | CP64: x
B66: =SUM(I66:CO66) -> 0 | C66: HINT: If something doesn’t balance you will see the ERROR message come up | F66: CHECK | I66: =IF(SUM(I59:I64)=0, "-", "ERROR") -> - | J66: =IF(SUM(J59:J64)=0, "-", "ERROR") -> - | K66: =IF(SUM(K59:K64)=0, "-", "ERROR") -> - | L66: =IF(SUM(L59:L64)=0, "-", "ERROR") -> - | M66: =IF(SUM(M59:M64)=0, "-", "ERROR") -> - | N66: =IF(SUM(N59:N64)=0, "-", "ERROR") -> - | O66: =IF(SUM(O59:O64)=0, "-", "ERROR") -> - | P66: =IF(SUM(P59:P64)=0, "-", "ERROR") -> - | ... CO66: =IF(SUM(CO59:CO64)=0, "-", "ERROR") -> - | CP66: x
F68: IRR | I68: =XIRR($I55:$CO55,HoldingDates) -> 0.34137853
C69: HINT: Ratio of all positive equity cash flows over all equity injections | F69: CFx | I69: =SUMIF($I55:$CO55,">0")/-SUMIF($I55:$CO55,"<0") -> 3.0270081
C70: HINT: Sum of all equity cash flows (no discounting) | F70: Net Profit | I70: =SUM(I55:CO55) -> 24618323
F72: Capital Accounts
F74: Common Equity
F75: Beginning | I75: 0 | J75: =I77 -> 8175223.9 | K75: =J77 -> 8486658.7 | L75: =K77 -> 8798093.4 | M75: =L77 -> 9132868 | N75: =M77 -> 9450137.7 | O75: =N77 -> 9718393.9 | P75: =O77 -> 10174038 | Q75: =P77 -> 10871250 | ... CO75: =CN77 -> 12145153 | CP75: x
B76: =SUM(I76:CO76) -> 12145153 | D76: + | F76: Funding | I76: =MIN(-SUM(I39:I40),CommonEquityOBalance-SUM($H76:H76)) -> 8175223.9 | J76: =MIN(-SUM(J39:J40),CommonEquityOBalance-SUM($H76:I76)) -> 311434.77 | K76: =MIN(-SUM(K39:K40),CommonEquityOBalance-SUM($H76:J76)) -> 311434.77 | L76: =MIN(-SUM(L39:L40),CommonEquityOBalance-SUM($H76:K76)) -> 334774.57 | M76: =MIN(-SUM(M39:M40),CommonEquityOBalance-SUM($H76:L76)) -> 317269.72 | N76: =MIN(-SUM(N39:N40),CommonEquityOBalance-SUM($H76:M76)) -> 268256.14 | O76: =MIN(-SUM(O39:O40),CommonEquityOBalance-SUM($H76:N76)) -> 455644.58 | P76: =MIN(-SUM(P39:P40),CommonEquityOBalance-SUM($H76:O76)) -> 697211.51 | ... CO76: =MIN(-SUM(CO39:CO40),CommonEquityOBalance-SUM($H76:CN76)) -> 0 | CP76: x
B77: =SUM(B75:B76) -> 12145153 | F77: Ending | I77: =SUM(I75:I76) -> 8175223.9 | J77: =SUM(J75:J76) -> 8486658.7 | K77: =SUM(K75:K76) -> 8798093.4 | L77: =SUM(L75:L76) -> 9132868 | M77: =SUM(M75:M76) -> 9450137.7 | N77: =SUM(N75:N76) -> 9718393.9 | O77: =SUM(O75:O76) -> 10174038 | P77: =SUM(P75:P76) -> 10871250 | ... CO77: =SUM(CO75:CO76) -> 12145153 | CP77: x
F79: Preferred Equity
F80: Beginning | I80: =H84 -> 0 | J80: =I84 -> 0 | K80: =J84 -> 0 | L80: =K84 -> 0 | M80: =L84 -> 0 | N80: =M84 -> 0 | O80: =N84 -> 0 | P80: =O84 -> 0 | ... CO80: =CN84 -> 0 | CP80: x
B81: =SUM(I81:CO81) -> 788496.42 | C81: HINT: Need to adjust rate for a monthly model | D81: + | F81: Pref Accrual | G81: =(1+PreferredEquityReturn_Case1)^(1/12)-1 -> 0.0072073233 | I81: =I80*$G$81 -> 0 | J81: =J80*$G$81 -> 0 | K81: =K80*$G$81 -> 0 | L81: =L80*$G$81 -> 0 | M81: =M80*$G$81 -> 0 | N81: =N80*$G$81 -> 0 | O81: =O80*$G$81 -> 0 | P81: =P80*$G$81 -> 0 | ... CO81: =CO80*$G$81 -> 0 | CP81: x
B82: =SUM(I82:CO82) -> 5000000 | D82: + | F82: Funding | I82: =MIN(-(SUM(I39:I40)+I76),PreferredEquityOBalance-SUM($H82:H82)) -> 0 | J82: =MIN(-(SUM(J39:J40)+J76),PreferredEquityOBalance-SUM($H82:I82)) -> 0 | K82: =MIN(-(SUM(K39:K40)+K76),PreferredEquityOBalance-SUM($H82:J82)) -> 0 | L82: =MIN(-(SUM(L39:L40)+L76),PreferredEquityOBalance-SUM($H82:K82)) -> 0 | M82: =MIN(-(SUM(M39:M40)+M76),PreferredEquityOBalance-SUM($H82:L82)) -> 0 | N82: =MIN(-(SUM(N39:N40)+N76),PreferredEquityOBalance-SUM($H82:M82)) -> 0 | O82: =MIN(-(SUM(O39:O40)+O76),PreferredEquityOBalance-SUM($H82:N82)) -> 0 | P82: =MIN(-(SUM(P39:P40)+P76),PreferredEquityOBalance-SUM($H82:O82)) -> 0 | ... CO82: =MIN(-(SUM(CO39:CO40)+CO76),PreferredEquityOBalance-SUM($H82:CN82)) -> 0 | CP82: x
B83: =SUM(I83:CO83) -> -5788496.4 | C83: =-MIN(SUM(H78:H80),MAX(SUM(H36:H51),0)) | D83: – | F83: Repayment | I83: =-MIN(SUM(I80:I82),MAX(SUM(I38:I53),0)) -> 0 | J83: =-MIN(SUM(J80:J82),MAX(SUM(J38:J53),0)) -> 0 | K83: =-MIN(SUM(K80:K82),MAX(SUM(K38:K53),0)) -> 0 | L83: =-MIN(SUM(L80:L82),MAX(SUM(L38:L53),0)) -> 0 | M83: =-MIN(SUM(M80:M82),MAX(SUM(M38:M53),0)) -> 0 | N83: =-MIN(SUM(N80:N82),MAX(SUM(N38:N53),0)) -> 0 | O83: =-MIN(SUM(O80:O82),MAX(SUM(O38:O53),0)) -> 0 | P83: =-MIN(SUM(P80:P82),MAX(SUM(P38:P53),0)) -> 0 | ... CO83: =-MIN(SUM(CO80:CO82),MAX(SUM(CO38:CO53),0)) -> 0 | CP83: x
B84: =SUM(B81:B83) -> 0 | F84: Ending | I84: =SUM(I80:I83) -> 0 | J84: =SUM(J80:J83) -> 0 | K84: =SUM(K80:K83) -> 0 | L84: =SUM(L80:L83) -> 0 | M84: =SUM(M80:M83) -> 0 | N84: =SUM(N80:N83) -> 0 | O84: =SUM(O80:O83) -> 0 | P84: =SUM(P80:P83) -> 0 | ... CO84: =SUM(CO80:CO83) -> 0 | CP84: x
F86: Construction Loan
F87: Beginning | I87: =H90 -> 0 | J87: =I90 -> 0 | K87: =J90 -> 0 | L87: =K90 -> 0 | M87: =L90 -> 0 | N87: =M90 -> 0 | O87: =N90 -> 0 | P87: =O90 -> 0 | ... CO87: =CN90 -> 0 | CP87: x
B88: =SUM(I88:CO88) -> 11697956 | D88: + | F88: Funding | I88: =MIN(-(SUM(I39:I41)+I76+I82),ConstLoanOBalance-SUM($H88:H88)) -> 0 | J88: =MIN(-(SUM(J39:J41)+J76+J82),ConstLoanOBalance-SUM($H88:I88)) -> 0 | K88: =MIN(-(SUM(K39:K41)+K76+K82),ConstLoanOBalance-SUM($H88:J88)) -> 0 | L88: =MIN(-(SUM(L39:L41)+L76+L82),ConstLoanOBalance-SUM($H88:K88)) -> 0 | M88: =MIN(-(SUM(M39:M41)+M76+M82),ConstLoanOBalance-SUM($H88:L88)) -> 0 | N88: =MIN(-(SUM(N39:N41)+N76+N82),ConstLoanOBalance-SUM($H88:M88)) -> 0 | O88: =MIN(-(SUM(O39:O41)+O76+O82),ConstLoanOBalance-SUM($H88:N88)) -> 0 | P88: =MIN(-(SUM(P39:P41)+P76+P82),ConstLoanOBalance-SUM($H88:O88)) -> 0 | ... CO88: =MIN(-(SUM(CO39:CO41)+CO76+CO82),ConstLoanOBalance-SUM($H88:CN88)) -> 0 | CP88: x
B89: =SUM(I89:CO89) -> -11697956 | D89: – | F89: Repayment | I89: =-SUM(I87:I88)*(Today=ConstLoanMaturityDate) -> 0 | J89: =-SUM(J87:J88)*(Today=ConstLoanMaturityDate) -> 0 | K89: =-SUM(K87:K88)*(Today=ConstLoanMaturityDate) -> 0 | L89: =-SUM(L87:L88)*(Today=ConstLoanMaturityDate) -> 0 | M89: =-SUM(M87:M88)*(Today=ConstLoanMaturityDate) -> 0 | N89: =-SUM(N87:N88)*(Today=ConstLoanMaturityDate) -> 0 | O89: =-SUM(O87:O88)*(Today=ConstLoanMaturityDate) -> 0 | P89: =-SUM(P87:P88)*(Today=ConstLoanMaturityDate) -> 0 | ... CO89: =-SUM(CO87:CO88)*(Today=ConstLoanMaturityDate) -> 0 | CP89: x
F90: Ending | I90: =SUM(I87:I89) -> 0 | J90: =SUM(J87:J89) -> 0 | K90: =SUM(K87:K89) -> 0 | L90: =SUM(L87:L89) -> 0 | M90: =SUM(M87:M89) -> 0 | N90: =SUM(N87:N89) -> 0 | O90: =SUM(O87:O89) -> 0 | P90: =SUM(P87:P89) -> 0 | ... CO90: =SUM(CO87:CO89) -> 0 | CP90: x
D92: + | F92: 1 Month LIBOR | I92: =INDEX(Libor!$C$11:$DS$11, MATCH(I28,Libor!$C$9:$DS$9,0)) -> 0.0014925 | J92: =INDEX(Libor!$C$11:$DS$11, MATCH(J28,Libor!$C$9:$DS$9,0)) -> 0.0015746 | K92: =INDEX(Libor!$C$11:$DS$11, MATCH(K28,Libor!$C$9:$DS$9,0)) -> 0.0016548 | L92: =INDEX(Libor!$C$11:$DS$11, MATCH(L28,Libor!$C$9:$DS$9,0)) -> 0.0017305 | M92: =INDEX(Libor!$C$11:$DS$11, MATCH(M28,Libor!$C$9:$DS$9,0)) -> 0.001734 | N92: =INDEX(Libor!$C$11:$DS$11, MATCH(N28,Libor!$C$9:$DS$9,0)) -> 0.0016393 | O92: =INDEX(Libor!$C$11:$DS$11, MATCH(O28,Libor!$C$9:$DS$9,0)) -> 0.0014936 | P92: =INDEX(Libor!$C$11:$DS$11, MATCH(P28,Libor!$C$9:$DS$9,0)) -> 0.0013758 | ... CO92: =INDEX(Libor!$C$11:$DS$11, MATCH(CO28,Libor!$C$9:$DS$9,0)) -> 0.0115155 | CP92: x
D93: + | F93: Spread | G93: =ConstLoanSpread -> 0.045 | I93: =$G$93 -> 0.045 | J93: =$G$93 -> 0.045 | K93: =$G$93 -> 0.045 | L93: =$G$93 -> 0.045 | M93: =$G$93 -> 0.045 | N93: =$G$93 -> 0.045 | O93: =$G$93 -> 0.045 | P93: =$G$93 -> 0.045 | ... CO93: =$G$93 -> 0.045 | CP93: x
F94: All-In Rate | I94: =SUM(I92:I93) -> 0.0464925 | J94: =SUM(J92:J93) -> 0.0465746 | K94: =SUM(K92:K93) -> 0.0466548 | L94: =SUM(L92:L93) -> 0.0467305 | M94: =SUM(M92:M93) -> 0.046734 | N94: =SUM(N92:N93) -> 0.0466393 | O94: =SUM(O92:O93) -> 0.0464936 | P94: =SUM(P92:P93) -> 0.0463758 | ... CO94: =SUM(CO92:CO93) -> 0.0565155 | CP94: x
B96: =SUM(I96:CO96) -> 762069.28 | C96: HINT: Use beginning bal to avoid circular reference. Adjust for Act / 360. "Days" in Row 22 can be helpful. | D96: + | F96: Interest Expense | I96: =I94*I87*DaysInMonth/ConstLoanType -> 0 | J96: =J94*J87*DaysInMonth/ConstLoanType -> 0 | K96: =K94*K87*DaysInMonth/ConstLoanType -> 0 | L96: =L94*L87*DaysInMonth/ConstLoanType -> 0 | M96: =M94*M87*DaysInMonth/ConstLoanType -> 0 | N96: =N94*N87*DaysInMonth/ConstLoanType -> 0 | O96: =O94*O87*DaysInMonth/ConstLoanType -> 0 | P96: =P94*P87*DaysInMonth/ConstLoanType -> 0 | ... CO96: =CO94*CO87*DaysInMonth/ConstLoanType -> 0 | CP96: x
B97: =SUM(I97:CO97) -> 197955.79 | C97: HINT: Difference between NOI and interest expense | D97: + | F97: Construction Period Interest | I97: =MAX(I96-NOI_Today,0) -> 0 | J97: =MAX(J96-NOI_Today,0) -> 0 | K97: =MAX(K96-NOI_Today,0) -> 0 | L97: =MAX(L96-NOI_Today,0) -> 0 | M97: =MAX(M96-NOI_Today,0) -> 0 | N97: =MAX(N96-NOI_Today,0) -> 0 | O97: =MAX(O96-NOI_Today,0) -> 0 | P97: =MAX(P96-NOI_Today,0) -> 0 | ... CO97: =MAX(CO96-NOI_Today,0) -> 0 | CP97: x
F99: Permanent Loan
F100: Beginning | I100: =H104 -> 0 | J100: =I104 -> 0 | K100: =J104 -> 0 | L100: =K104 -> 0 | M100: =L104 -> 0 | N100: =M104 -> 0 | O100: =N104 -> 0 | P100: =O104 -> 0 | ... CO100: =CN104 -> 0 | CP100: x
B101: =SUM(I101:CO101) -> 35005242 | D101: + | F101: Funding | I101: =PermanentLoanOBalance*(Today=PermanentLoanOriginationDate) -> 0 | J101: =PermanentLoanOBalance*(Today=PermanentLoanOriginationDate) -> 0 | K101: =PermanentLoanOBalance*(Today=PermanentLoanOriginationDate) -> 0 | L101: =PermanentLoanOBalance*(Today=PermanentLoanOriginationDate) -> 0 | M101: =PermanentLoanOBalance*(Today=PermanentLoanOriginationDate) -> 0 | N101: =PermanentLoanOBalance*(Today=PermanentLoanOriginationDate) -> 0 | O101: =PermanentLoanOBalance*(Today=PermanentLoanOriginationDate) -> 0 | P101: =PermanentLoanOBalance*(Today=PermanentLoanOriginationDate) -> 0 | ... CO101: =PermanentLoanOBalance*(Today=PermanentLoanOriginationDate) -> 0 | CP101: x
B102: =SUM(I102:CO102) -> -1145734.5 | D102: – | F102: Amortization | I102: =-I107 -> 0 | J102: =-J107 -> 0 | K102: =-K107 -> 0 | L102: =-L107 -> 0 | M102: =-M107 -> 0 | N102: =-N107 -> 0 | O102: =-O107 -> 0 | P102: =-P107 -> 0 | ... CO102: =-CO107 -> 0 | CP102: x
B103: =SUM(I103:CO103) -> -33859508 | D103: – | F103: Repayment | I103: =-SUM(I100:I102)*(Today=PermanentLoanMaturityDate) -> 0 | J103: =-SUM(J100:J102)*(Today=PermanentLoanMaturityDate) -> 0 | K103: =-SUM(K100:K102)*(Today=PermanentLoanMaturityDate) -> 0 | L103: =-SUM(L100:L102)*(Today=PermanentLoanMaturityDate) -> 0 | M103: =-SUM(M100:M102)*(Today=PermanentLoanMaturityDate) -> 0 | N103: =-SUM(N100:N102)*(Today=PermanentLoanMaturityDate) -> 0 | O103: =-SUM(O100:O102)*(Today=PermanentLoanMaturityDate) -> 0 | P103: =-SUM(P100:P102)*(Today=PermanentLoanMaturityDate) -> 0 | ... CO103: =-SUM(CO100:CO102)*(Today=PermanentLoanMaturityDate) -> 0 | CP103: x
F104: Ending | I104: =SUM(I100:I103) -> 0 | J104: =SUM(J100:J103) -> 0 | K104: =SUM(K100:K103) -> 0 | L104: =SUM(L100:L103) -> 0 | M104: =SUM(M100:M103) -> 0 | N104: =SUM(N100:N103) -> 0 | O104: =SUM(O100:O103) -> 0 | P104: =SUM(P100:P103) -> 0 | ... CO104: =SUM(CO100:CO103) -> 0 | CP104: x
B106: =SUM(I106:CO106) -> 7238332.5 | C106: HINT: Divide by 12 for monthly | D106: + | F106: Interest Expense | I106: =I100*PermanentLoanRate/12 -> 0 | J106: =J100*PermanentLoanRate/12 -> 0 | K106: =K100*PermanentLoanRate/12 -> 0 | L106: =L100*PermanentLoanRate/12 -> 0 | M106: =M100*PermanentLoanRate/12 -> 0 | N106: =N100*PermanentLoanRate/12 -> 0 | O106: =O100*PermanentLoanRate/12 -> 0 | P106: =P100*PermanentLoanRate/12 -> 0 | ... CO106: =CO100*PermanentLoanRate/12 -> 0 | CP106: x
B107: =SUM(I107:CO107) -> 1145734.5 | C107: HINT: Difference between payment and interest expense | D107: + | F107: Amortization | I107: =I109-I106 -> 0 | J107: =J109-J106 -> 0 | K107: =K109-K106 -> 0 | L107: =L109-L106 -> 0 | M107: =M109-M106 -> 0 | N107: =N109-N106 -> 0 | O107: =O109-O106 -> 0 | P107: =P109-P106 -> 0 | ... CO107: =CO109-CO106 -> 0 | CP107: x
F108: Payment Dummy | I108: =(Today>PermanentLoanOriginationDate)*(Today<=PermanentLoanMaturityDate) -> 0 | J108: =(Today>PermanentLoanOriginationDate)*(Today<=PermanentLoanMaturityDate) -> 0 | K108: =(Today>PermanentLoanOriginationDate)*(Today<=PermanentLoanMaturityDate) -> 0 | L108: =(Today>PermanentLoanOriginationDate)*(Today<=PermanentLoanMaturityDate) -> 0 | M108: =(Today>PermanentLoanOriginationDate)*(Today<=PermanentLoanMaturityDate) -> 0 | N108: =(Today>PermanentLoanOriginationDate)*(Today<=PermanentLoanMaturityDate) -> 0 | O108: =(Today>PermanentLoanOriginationDate)*(Today<=PermanentLoanMaturityDate) -> 0 | P108: =(Today>PermanentLoanOriginationDate)*(Today<=PermanentLoanMaturityDate) -> 0 | ... CO108: =(Today>PermanentLoanOriginationDate)*(Today<=PermanentLoanMaturityDate) -> 0 | CP108: x
B109: =SUM(I109:CO109) -> 8384067 | D109: + | F109: Payment | I109: =(PermanentLoanOBalance*PermanentLoanMortgageConstant/12)*PermanentLoanDebtServiceDummy -> 0 | J109: =(PermanentLoanOBalance*PermanentLoanMortgageConstant/12)*PermanentLoanDebtServiceDummy -> 0 | K109: =(PermanentLoanOBalance*PermanentLoanMortgageConstant/12)*PermanentLoanDebtServiceDummy -> 0 | L109: =(PermanentLoanOBalance*PermanentLoanMortgageConstant/12)*PermanentLoanDebtServiceDummy -> 0 | M109: =(PermanentLoanOBalance*PermanentLoanMortgageConstant/12)*PermanentLoanDebtServiceDummy -> 0 | N109: =(PermanentLoanOBalance*PermanentLoanMortgageConstant/12)*PermanentLoanDebtServiceDummy -> 0 | O109: =(PermanentLoanOBalance*PermanentLoanMortgageConstant/12)*PermanentLoanDebtServiceDummy -> 0 | P109: =(PermanentLoanOBalance*PermanentLoanMortgageConstant/12)*PermanentLoanDebtServiceDummy -> 0 | ... CO109: =(PermanentLoanOBalance*PermanentLoanMortgageConstant/12)*PermanentLoanDebtServiceDummy -> 0 | CP109: x
F111: Fees
B113: =SUM(I113:CO113) -> 24618323 | F113: Cash Flows to Equity | I113: =I55 -> -8175223.9 | J113: =J55 -> -311434.77 | K113: =K55 -> -311434.77 | L113: =L55 -> -334774.57 | M113: =M55 -> -317269.72 | N113: =N55 -> -268256.14 | O113: =O55 -> -455644.58 | P113: =P55 -> -697211.51 | ... CO113: =CO55 -> 0 | CP113: x
B114: =SUM(I114:CO114) -> -50000 | D114: – | F114: Acquisition Fee | H114: 0.01 | I114: =-(Today=ClosingDate)*LandCost*AcquisitionFee -> -50000 | J114: =-(Today=ClosingDate)*LandCost*AcquisitionFee -> 0 | K114: =-(Today=ClosingDate)*LandCost*AcquisitionFee -> 0 | L114: =-(Today=ClosingDate)*LandCost*AcquisitionFee -> 0 | M114: =-(Today=ClosingDate)*LandCost*AcquisitionFee -> 0 | N114: =-(Today=ClosingDate)*LandCost*AcquisitionFee -> 0 | O114: =-(Today=ClosingDate)*LandCost*AcquisitionFee -> 0 | P114: =-(Today=ClosingDate)*LandCost*AcquisitionFee -> 0 | ... CO114: =-(Today=ClosingDate)*LandCost*AcquisitionFee -> 0 | CP114: x
B115: =SUM(I115:CO115) -> -276196.17 | C115: HINT: See "Cumulative Equity Invested" metric above. Adjust for monthly | D115: – | F115: Asset Management Fee | H115: 0.008 | I115: =-CumulEquityInvested*AssetManagementFee/12*(Today<=ExitDate) -> -5450.1493 | J115: =-CumulEquityInvested*AssetManagementFee/12*(Today<=ExitDate) -> -5657.7724 | K115: =-CumulEquityInvested*AssetManagementFee/12*(Today<=ExitDate) -> -5865.3956 | L115: =-CumulEquityInvested*AssetManagementFee/12*(Today<=ExitDate) -> -6088.5787 | M115: =-CumulEquityInvested*AssetManagementFee/12*(Today<=ExitDate) -> -6300.0918 | N115: =-CumulEquityInvested*AssetManagementFee/12*(Today<=ExitDate) -> -6478.9293 | O115: =-CumulEquityInvested*AssetManagementFee/12*(Today<=ExitDate) -> -6782.6923 | P115: =-CumulEquityInvested*AssetManagementFee/12*(Today<=ExitDate) -> -7247.5 | ... CO115: =-CumulEquityInvested*AssetManagementFee/12*(Today<=ExitDate) -> 0 | CP115: x
B116: =SUM(I116:CO116) -> -62209.358 | D116: – | F116: Disposition Fee | H116: 0.005 | I116: =-SUM(I47:I53)*DispositionFee*(Today=ExitDate) -> 0 | J116: =-SUM(J47:J53)*DispositionFee*(Today=ExitDate) -> 0 | K116: =-SUM(K47:K53)*DispositionFee*(Today=ExitDate) -> 0 | L116: =-SUM(L47:L53)*DispositionFee*(Today=ExitDate) -> 0 | M116: =-SUM(M47:M53)*DispositionFee*(Today=ExitDate) -> 0 | N116: =-SUM(N47:N53)*DispositionFee*(Today=ExitDate) -> 0 | O116: =-SUM(O47:O53)*DispositionFee*(Today=ExitDate) -> 0 | P116: =-SUM(P47:P53)*DispositionFee*(Today=ExitDate) -> 0 | ... CO116: =-SUM(CO47:CO53)*DispositionFee*(Today=ExitDate) -> 0 | CP116: x
F117: Cash Flows to Equity Net of Fees | I117: =SUM(I113:I116) -> -8230674.1 | J117: =SUM(J113:J116) -> -317092.55 | K117: =SUM(K113:K116) -> -317300.17 | L117: =SUM(L113:L116) -> -340863.15 | M117: =SUM(M113:M116) -> -323569.81 | N117: =SUM(N113:N116) -> -274735.07 | O117: =SUM(O113:O116) -> -462427.28 | P117: =SUM(P113:P116) -> -704459.01 | ... CO117: =SUM(CO113:CO116) -> 0 | CP117: x
H119: Sum of Fees | I119: =SUM(I114:CO116) -> -388405.53
F121: Net IRR (Pre-Promote) | I121: =XIRR($I117:$CO117,HoldingDates) -> 0.3335279
F122: CFx | I122: =SUMIF($I117:$CO117,">0")/-SUMIF($I117:$CO117,"<0") -> 2.9428465
F123: Net Profit | I123: =SUM(I117:CO117) -> 24229917
C126: Real Estate Financial Modeling
...

Sheet Q1 - CAP Acct. 2
F2: =Inputs!B2 -> Comparing Complex Deal Structures
F4: Model: Capital Accounts | I4: Scenario in Model: | K4: =Scenario!E4 -> Best Case | M4: Deal in Model: | O4: Case 2 - SCP
F6: SOURCES AND USES | O6: FINANCING ASSUMPTIONS
F8: USES | H8: $ | I8: Per Key | J8: SOURCES | L8: $ | M8: % | O8: CONSTRUCTION LOAN | S8: PERMANENT LOAN
F9: Land | H9: 5000000 | I9: =H9/NumberRooms -> 20000 | J9: Construction Loan | L9: =ConstLoanOBalance -> 12500000 | M9: =L9/H15 -> 0.42165409 | O9: Construction Loan Commitment | R9: 12500000 | S9: Permanent Loan Proceeds | V9: =V10/V11/V15 -> 35005242
F10: Soft Costs | H10: =SUM(Construction!D10:D13)+Construction!D26 -> 4600000 | I10: =H10/NumberRooms -> 18400 | J10: Preferred Equity | L10: =PreferredEquityOBalance -> 5000000 | M10: =L10/$H$15 -> 0.16866164 | O10: Loan Fees | R10: 0.01 | S10: NOI at Refi | V10: =INDEX($I$36:$CO$36,MATCH(V16,$I$28:$CO$28,FALSE)) -> 3772830.2
F11: Hard Costs | H11: =SUM(Construction!D14:D15,Construction!D25) -> 17570000 | I11: =H11/NumberRooms -> 70280 | J11: Common Equity | L11: =TotalUses-SUM(L9:L10) -> 12145153 | M11: =L11/$H$15 -> 0.40968427 | O11: Spread | R11: 0.045 | S11: DSCR | V11: 1.35
F12: Contingency and Escalation | H12: =SUM(Construction!D29:D30) -> 1350153 | I12: =H12/NumberRooms -> 5400.612 | J12: Sponsor | L12: =M12*$L$11 -> 1214515.3 | M12: 0.1 | O12: Origination | R12: =H18 -> 44196 | S12: Loan Fees | V12: 0.01
F13: Interest Reserve | H13: 1000000 | I13: =H13/NumberRooms -> 4000 | J13: Co-Investor | L13: =M13*$L$11 -> 10930638 | M13: =1-M12 -> 0.9 | O13: Maturity | Q13: 3 | R13: =EOMONTH(R12,Q13*12) -> 45291 | S13: Rate | V13: 0.07
F14: Loan Fees | H14: =R10*L9 -> 125000 | I14: =H14/NumberRooms -> 500 | O14: Type | R14: 360 | S14: Amortization (Years) | V14: 30
F15: Total Uses | H15: =SUM(H9:H14) -> 29645153 | I15: =H15/NumberRooms -> 118580.61 | J15: Total Sources | L15: =SUM(L9:L11) -> 29645153 | M15: =SUM(M9:M11) -> 1 | O15: Extension Fee | R15: 0.005 | S15: Mortgage Constant (%) | V15: =PMT(V13/12,V14*12,-1)*12 -> 0.079836299
O16: Exercise Extension? | Q16: DON’T EDIT | R16: =($Q$13=4)*1 -> 0 | S16: Origination | V16: =R13 -> 45291
F17: SCENARIO | J17: Exit Cap Rate | L17: =TerminalCapRateHotel -> 0.085 | O17: Extension Date | R17: =EOMONTH(R13,-12)*R16 -> 0 | S17: Maturity | T17: DON’T EDIT | U17: =DATEDIF(R13,V17,"y") -> 3 | V17: =ExitDate -> 46387
F18: Closing | H18: =Inputs!C11-1 -> 44196 | J18: Sales Costs | L18: =SellingCost -> 0.03 | O18: PREFERRED EQUITY | S18: Prepayment Fee | V18: 0.01
F19: Opening | H19: =EOMONTH(Construction!AC7,1) -> 44957 | J19: Gross Sales Proceeds | L19: =SUM(I52:CO52) -> 47973474 | O19: Preferred Equity | R19: 5000000 | S19: Prepay Loan? | U19: DON’T EDIT | V19: =IF(U17<=2, 1, 0) -> 0
F20: Sale Date | H20: =DATE(YEAR(H18) + HoldingPeriod + 1, MONTH(H18), DAY(H18)) -> 46387 | J20: Price per Key | L20: =L19/NumberRooms -> 191893.9 | O20: Preferred Equity Return | R20: 0.12
F22: Funding | H22: Position | I22: Weight
F23: =J11 -> Common Equity | H23: 1 | I23: 0.45
F24: =J10 -> Preferred Equity | H24: 1 | I24: =1-I23 -> 0.55
F25: =J9 -> Construction Loan | H25: 2 | I25: 1
H27: Year | I27: =YEAR(I28) -> 2020 | J27: =YEAR(J28) -> 2021 | K27: =YEAR(K28) -> 2021 | L27: =YEAR(L28) -> 2021 | M27: =YEAR(M28) -> 2021 | N27: =YEAR(N28) -> 2021 | O27: =YEAR(O28) -> 2021 | P27: =YEAR(P28) -> 2021 | ... CO27: =YEAR(CO28) -> 2027 | CP27: x
H28: Date | I28: =H18 -> 44196 | J28: =EOMONTH(I28,1) -> 44227 | K28: =EOMONTH(J28,1) -> 44255 | L28: =EOMONTH(K28,1) -> 44286 | M28: =EOMONTH(L28,1) -> 44316 | N28: =EOMONTH(M28,1) -> 44347 | O28: =EOMONTH(N28,1) -> 44377 | P28: =EOMONTH(O28,1) -> 44408 | Q28: =EOMONTH(P28,1) -> 44439 | ... CO28: =EOMONTH(CN28,1) -> 46752 | CP28: x
B29: Sum | C29: Comments | D29: Sign | H29: Days | I29: 31 | J29: =J28-I28 -> 31 | K29: =K28-J28 -> 28 | L29: =L28-K28 -> 31 | M29: =M28-L28 -> 30 | N29: =N28-M28 -> 31 | O29: =O28-N28 -> 30 | P29: =P28-O28 -> 31 | Q29: =Q28-P28 -> 31 | ... CO29: =CO28-CN28 -> 31 | CP29: x
F31: Cash Flows to Equity
C32: HINT: Index, Match, AND IFERROR functions will be helpful here.
C33: Make sure to divide by 12 for monthly! | D33: + | F33: Net Operating Income Hotel | I33: =IFERROR(INDEX(NOI!$C$76:$H$76,MATCH(I27,NOI!$C$8:$H$8,0))/12,0) -> 0 | J33: =IFERROR(INDEX(NOI!$C$76:$H$76,MATCH(J27,NOI!$C$8:$H$8,0))/12,0) -> 246463.73 | K33: =IFERROR(INDEX(NOI!$C$76:$H$76,MATCH(K27,NOI!$C$8:$H$8,0))/12,0) -> 246463.73 | L33: =IFERROR(INDEX(NOI!$C$76:$H$76,MATCH(L27,NOI!$C$8:$H$8,0))/12,0) -> 246463.73 | M33: =IFERROR(INDEX(NOI!$C$76:$H$76,MATCH(M27,NOI!$C$8:$H$8,0))/12,0) -> 246463.73 | N33: =IFERROR(INDEX(NOI!$C$76:$H$76,MATCH(N27,NOI!$C$8:$H$8,0))/12,0) -> 246463.73 | O33: =IFERROR(INDEX(NOI!$C$76:$H$76,MATCH(O27,NOI!$C$8:$H$8,0))/12,0) -> 246463.73 | P33: =IFERROR(INDEX(NOI!$C$76:$H$76,MATCH(P27,NOI!$C$8:$H$8,0))/12,0) -> 246463.73 | ... CO33: =IFERROR(INDEX(NOI!$C$76:$H$76,MATCH(CO27,NOI!$C$8:$H$8,0))/12,0) -> 0 | CP33: x
D35: + | F35: Selected Net Operating Income | I35: =(Today>=OpeningDate)*(Today<=ExitDate)*I33 -> 0 | J35: =(Today>=OpeningDate)*(Today<=ExitDate)*J33 -> 0 | K35: =(Today>=OpeningDate)*(Today<=ExitDate)*K33 -> 0 | L35: =(Today>=OpeningDate)*(Today<=ExitDate)*L33 -> 0 | M35: =(Today>=OpeningDate)*(Today<=ExitDate)*M33 -> 0 | N35: =(Today>=OpeningDate)*(Today<=ExitDate)*N33 -> 0 | O35: =(Today>=OpeningDate)*(Today<=ExitDate)*O33 -> 0 | P35: =(Today>=OpeningDate)*(Today<=ExitDate)*P33 -> 0 | ... CO35: =(Today>=OpeningDate)*(Today<=ExitDate)*CO33 -> 0 | CP35: x
C36: HINT: TTM = Trailing 12 month (OFFSET Function will be helpful here) | D36: + | F36: TTM NOI | I36: =IF(Today<OpeningDate,0,SUM(OFFSET(I35,,0,1,-12))) -> 0 | J36: =IF(Today<OpeningDate,0,SUM(OFFSET(J35,,0,1,-12))) -> 0 | K36: =IF(Today<OpeningDate,0,SUM(OFFSET(K35,,0,1,-12))) -> 0 | L36: =IF(Today<OpeningDate,0,SUM(OFFSET(L35,,0,1,-12))) -> 0 | M36: =IF(Today<OpeningDate,0,SUM(OFFSET(M35,,0,1,-12))) -> 0 | N36: =IF(Today<OpeningDate,0,SUM(OFFSET(N35,,0,1,-12))) -> 0 | O36: =IF(Today<OpeningDate,0,SUM(OFFSET(O35,,0,1,-12))) -> 0 | P36: =IF(Today<OpeningDate,0,SUM(OFFSET(P35,,0,1,-12))) -> 0 | ... CO36: =IF(Today<OpeningDate,0,SUM(OFFSET(CO35,,0,1,-12))) -> 0 | CP36: x
B38: =SUM(I38:CO38) -> 15868156 | C38: HINT: There should be no NOI after sale date (cell G20) | D38: + | F38: Net Operating Income | I38: =I35 -> 0 | J38: =J35 -> 0 | K38: =K35 -> 0 | L38: =L35 -> 0 | M38: =M35 -> 0 | N38: =N35 -> 0 | O38: =O35 -> 0 | P38: =P35 -> 0 | ... CO38: =CO35 -> 0 | CP38: x
B39: =SUM(I39:CO39) -> -28520153 | C39: HINT: Link to "Construction Budget" tab | D39: – | F39: Unlevered Development Costs | I39: =-Construction!E32 -> -8050223.9 | J39: =-Construction!F32 -> -311434.77 | K39: =-Construction!G32 -> -311434.77 | L39: =-Construction!H32 -> -334774.57 | M39: =-Construction!I32 -> -317269.72 | N39: =-Construction!J32 -> -268256.14 | O39: =-Construction!K32 -> -455644.58 | P39: =-Construction!L32 -> -697211.51 | ... CO39: =-Construction!CK32 -> 0 | CP39: x
B40: =SUM(I40:CO40) -> -125000 | C40: HINT: These should be paid at closing (cell G18) | D40: – | F40: Loan Fees | I40: =-ConstLoanOFees*(Today=ClosingDate) -> -125000 | J40: =-ConstLoanOFees*(Today=ClosingDate) -> 0 | K40: =-ConstLoanOFees*(Today=ClosingDate) -> 0 | L40: =-ConstLoanOFees*(Today=ClosingDate) -> 0 | M40: =-ConstLoanOFees*(Today=ClosingDate) -> 0 | N40: =-ConstLoanOFees*(Today=ClosingDate) -> 0 | O40: =-ConstLoanOFees*(Today=ClosingDate) -> 0 | P40: =-ConstLoanOFees*(Today=ClosingDate) -> 0 | ... CO40: =-ConstLoanOFees*(Today=ClosingDate) -> 0 | CP40: x
B41: =SUM(I41:CO41) -> -197955.79 | D41: – | F41: Construction Period Interest Draws | I41: =-I98 -> 0 | J41: =-J98 -> 0 | K41: =-K98 -> 0 | L41: =-L98 -> 0 | M41: =-M98 -> 0 | N41: =-N98 -> 0 | O41: =-O98 -> 0 | P41: =-P98 -> 0 | ... CO41: =-CO98 -> 0 | CP41: x
B42: =SUM(I42:CO42) -> 5000000 | D42: + | F42: Preferred Equity Funding | I42: =I83 -> 4496373.1 | J42: =J83 -> 171289.13 | K42: =K83 -> 171289.13 | L42: =L83 -> 161048.6 | M42: =M83 -> 0 | N42: =N83 -> 0 | O42: =O83 -> 0 | P42: =P83 -> 0 | ... CO42: =CO83 -> 0 | CP42: x
B43: =SUM(I43:CO43) -> 11697956 | D43: + | F43: Construction Loan Funding | I43: =I89 -> 0 | J43: =J89 -> 0 | K43: =K89 -> 0 | L43: =L89 -> 0 | M43: =M89 -> 0 | N43: =N89 -> 0 | O43: =O89 -> 0 | P43: =P89 -> 0 | ... CO43: =CO89 -> 0 | CP43: x
B44: =SUM(I44:CO44) -> -564113.48 | C44: HINT: Interest expense less $ funded by construction interest draws | D44: – | F44: Construction Loan Interest | I44: =-I97+I98 -> 0 | J44: =-J97+J98 -> 0 | K44: =-K97+K98 -> 0 | L44: =-L97+L98 -> 0 | M44: =-M97+M98 -> 0 | N44: =-N97+N98 -> 0 | O44: =-O97+O98 -> 0 | P44: =-P97+P98 -> 0 | ... CO44: =-CO97+CO98 -> 0 | CP44: x
B45: =SUM(I45:CO45) -> 0 | C45: HINT: Only payable if you refinance in Year 4 | D45: – | F45: Construction Loan Extension Payment | I45: =-ConstLoanExtensionDummy*(ConstLoanExtensionFee*I88)*(Today=ConstLoanExtensionDate) -> 0 | J45: =-ConstLoanExtensionDummy*(ConstLoanExtensionFee*J88)*(Today=ConstLoanExtensionDate) -> 0 | K45: =-ConstLoanExtensionDummy*(ConstLoanExtensionFee*K88)*(Today=ConstLoanExtensionDate) -> 0 | L45: =-ConstLoanExtensionDummy*(ConstLoanExtensionFee*L88)*(Today=ConstLoanExtensionDate) -> 0 | M45: =-ConstLoanExtensionDummy*(ConstLoanExtensionFee*M88)*(Today=ConstLoanExtensionDate) -> 0 | N45: =-ConstLoanExtensionDummy*(ConstLoanExtensionFee*N88)*(Today=ConstLoanExtensionDate) -> 0 | O45: =-ConstLoanExtensionDummy*(ConstLoanExtensionFee*O88)*(Today=ConstLoanExtensionDate) -> 0 | P45: =-ConstLoanExtensionDummy*(ConstLoanExtensionFee*P88)*(Today=ConstLoanExtensionDate) -> 0 | ... CO45: =-ConstLoanExtensionDummy*(ConstLoanExtensionFee*CO88)*(Today=ConstLoanExtensionDate) -> 0 | CP45: x
B46: =SUM(I46:CO46) -> -11697956 | D46: – | F46: Construction Loan Repayment | I46: =I90 -> 0 | J46: =J90 -> 0 | K46: =K90 -> 0 | L46: =L90 -> 0 | M46: =M90 -> 0 | N46: =N90 -> 0 | O46: =O90 -> 0 | P46: =P90 -> 0 | ... CO46: =CO90 -> 0 | CP46: x
B47: =SUM(I47:CO47) -> 35005242 | D47: + | F47: Permanent Loan Proceeds | I47: =I102 -> 0 | J47: =J102 -> 0 | K47: =K102 -> 0 | L47: =L102 -> 0 | M47: =M102 -> 0 | N47: =N102 -> 0 | O47: =O102 -> 0 | P47: =P102 -> 0 | ... CO47: =CO102 -> 0 | CP47: x
B48: =SUM(I48:CO48) -> -350052.42 | C48: HINT: Payable on origination of new loan | D48: – | F48: Permanent Loan Fees | I48: =-I47*PermanentLoanPoints -> 0 | J48: =-J47*PermanentLoanPoints -> 0 | K48: =-K47*PermanentLoanPoints -> 0 | L48: =-L47*PermanentLoanPoints -> 0 | M48: =-M47*PermanentLoanPoints -> 0 | N48: =-N47*PermanentLoanPoints -> 0 | O48: =-O47*PermanentLoanPoints -> 0 | P48: =-P47*PermanentLoanPoints -> 0 | ... CO48: =-CO47*PermanentLoanPoints -> 0 | CP48: x
F49: Permanent Loan Debt Service | I49: =-I110 -> 0 | J49: =-J110 -> 0 | K49: =-K110 -> 0 | L49: =-L110 -> 0 | M49: =-M110 -> 0 | N49: =-N110 -> 0 | O49: =-O110 -> 0 | P49: =-P110 -> 0 | ... CO49: =-CO110 -> 0 | CP49: x
B50: =SUM(I50:CO50) -> -33859508 | D50: – | F50: Permanent Loan Repayment | I50: =I104 -> 0 | J50: =J104 -> 0 | K50: =K104 -> 0 | L50: =L104 -> 0 | M50: =M104 -> 0 | N50: =N104 -> 0 | O50: =O104 -> 0 | P50: =P104 -> 0 | ... CO50: =CO104 -> 0 | CP50: x
B51: =SUM(I51:CO51) -> 0 | C51: HINT: Only payable if you refinance in Year 4 | D51: – | F51: Permanent Loan Prepayment Penalty | I51: =I50*PermanentLoanPPMTFee*PermanentLoanPPMTDummy -> 0 | J51: =J50*PermanentLoanPPMTFee*PermanentLoanPPMTDummy -> 0 | K51: =K50*PermanentLoanPPMTFee*PermanentLoanPPMTDummy -> 0 | L51: =L50*PermanentLoanPPMTFee*PermanentLoanPPMTDummy -> 0 | M51: =M50*PermanentLoanPPMTFee*PermanentLoanPPMTDummy -> 0 | N51: =N50*PermanentLoanPPMTFee*PermanentLoanPPMTDummy -> 0 | O51: =O50*PermanentLoanPPMTFee*PermanentLoanPPMTDummy -> 0 | P51: =P50*PermanentLoanPPMTFee*PermanentLoanPPMTDummy -> 0 | ... CO51: =CO50*PermanentLoanPPMTFee*PermanentLoanPPMTDummy -> 0 | CP51: x
B52: =SUM(I52:CO52) -> 47973474 | D52: + | F52: Gross Sales Proceeds | I52: =I36/TerminalCapRateHotel*(Today=ExitDate) -> 0 | J52: =J36/TerminalCapRateHotel*(Today=ExitDate) -> 0 | K52: =K36/TerminalCapRateHotel*(Today=ExitDate) -> 0 | L52: =L36/TerminalCapRateHotel*(Today=ExitDate) -> 0 | M52: =M36/TerminalCapRateHotel*(Today=ExitDate) -> 0 | N52: =N36/TerminalCapRateHotel*(Today=ExitDate) -> 0 | O52: =O36/TerminalCapRateHotel*(Today=ExitDate) -> 0 | P52: =P36/TerminalCapRateHotel*(Today=ExitDate) -> 0 | ... CO52: =CO36/TerminalCapRateHotel*(Today=ExitDate) -> 0 | CP52: x
B53: =SUM(I53:CO53) -> -1439204.2 | D53: – | F53: Sales Costs | I53: =-SellingCost*I52 -> 0 | J53: =-SellingCost*J52 -> 0 | K53: =-SellingCost*K52 -> 0 | L53: =-SellingCost*L52 -> 0 | M53: =-SellingCost*M52 -> 0 | N53: =-SellingCost*N52 -> 0 | O53: =-SellingCost*O52 -> 0 | P53: =-SellingCost*P52 -> 0 | ... CO53: =-SellingCost*CO52 -> 0 | CP53: x
B54: =SUM(I54:CO54) -> -6838344.1 | D54: – | F54: Preferred Equity Repayment | I54: =I84 -> 0 | J54: =J84 -> 0 | K54: =K84 -> 0 | L54: =L84 -> 0 | M54: =M84 -> 0 | N54: =N84 -> 0 | O54: =O84 -> 0 | P54: =P84 -> 0 | ... CO54: =CO84 -> 0 | CP54: x
B55: =SUM(I55:CO55) -> 23568475 | D55: + | F55: Total Cash Flows to Equity | I55: =SUM(I38:I54) -> -3678850.8 | J55: =SUM(J38:J54) -> -140145.65 | K55: =SUM(K38:K54) -> -140145.65 | L55: =SUM(L38:L54) -> -173725.97 | M55: =SUM(M38:M54) -> -317269.72 | N55: =SUM(N38:N54) -> -268256.14 | O55: =SUM(O38:O54) -> -455644.58 | P55: =SUM(P38:P54) -> -697211.51 | ... CO55: =SUM(CO38:CO54) -> 0 | CP55: x
C56: HINT: You'll need a MAX function here | D56: + | F56: Cumulative Equity Invested | I56: =MAX(H56-I55,0) -> 3678850.8 | J56: =MAX(I56-J55,0) -> 3818996.4 | K56: =MAX(J56-K55,0) -> 3959142.1 | L56: =MAX(K56-L55,0) -> 4132868 | M56: =MAX(L56-M55,0) -> 4450137.7 | N56: =MAX(M56-N55,0) -> 4718393.9 | O56: =MAX(N56-O55,0) -> 5174038.5 | P56: =MAX(O56-P55,0) -> 5871250 | ... CO56: =MAX(CN56-CO55,0) -> 0 | CP56: x
F58: Development Sources and Uses - CHECK
B59: =SUM(I59:CO59) -> -28520153 | D59: – | F59: Unlevered Development Costs | I59: =I39 -> -8050223.9 | J59: =J39 -> -311434.77 | K59: =K39 -> -311434.77 | L59: =L39 -> -334774.57 | M59: =M39 -> -317269.72 | N59: =N39 -> -268256.14 | O59: =O39 -> -455644.58 | P59: =P39 -> -697211.51 | ... CO59: =CO39 -> 0 | CP59: x
B60: =SUM(I60:CO60) -> -125000 | D60: – | F60: Loan Fees | I60: =I40 -> -125000 | J60: =J40 -> 0 | K60: =K40 -> 0 | L60: =L40 -> 0 | M60: =M40 -> 0 | N60: =N40 -> 0 | O60: =O40 -> 0 | P60: =P40 -> 0 | ... CO60: =CO40 -> 0 | CP60: x
B61: =SUM(I61:CO61) -> -197955.79 | D61: – | F61: Construction Period Interest Draws | I61: =I41 -> 0 | J61: =J41 -> 0 | K61: =K41 -> 0 | L61: =L41 -> 0 | M61: =M41 -> 0 | N61: =N41 -> 0 | O61: =O41 -> 0 | P61: =P41 -> 0 | ... CO61: =CO41 -> 0 | CP61: x
B62: =SUM(I62:CO62) -> 12145153 | D62: + | F62: Equity Funding | I62: =SUM(I76:I77) -> 3678850.8 | J62: =SUM(J76:J77) -> 140145.65 | K62: =SUM(K76:K77) -> 140145.65 | L62: =SUM(L76:L77) -> 173725.97 | M62: =SUM(M76:M77) -> 317269.72 | N62: =SUM(N76:N77) -> 268256.14 | O62: =SUM(O76:O77) -> 455644.58 | P62: =SUM(P76:P77) -> 697211.51 | ... CO62: =SUM(CO76:CO77) -> 0 | CP62: x
B63: =SUM(I63:CO63) -> 5000000 | D63: + | F63: Preferred Equity Funding | I63: =I42 -> 4496373.1 | J63: =J42 -> 171289.13 | K63: =K42 -> 171289.13 | L63: =L42 -> 161048.6 | M63: =M42 -> 0 | N63: =N42 -> 0 | O63: =O42 -> 0 | P63: =P42 -> 0 | ... CO63: =CO42 -> 0 | CP63: x
B64: =SUM(I64:CO64) -> 11697956 | D64: + | F64: Construction Loan Funding | I64: =I43 -> 0 | J64: =J43 -> 0 | K64: =K43 -> 0 | L64: =L43 -> 0 | M64: =M43 -> 0 | N64: =N43 -> 0 | O64: =O43 -> 0 | P64: =P43 -> 0 | ... CO64: =CO43 -> 0 | CP64: x
B66: =SUM(I66:CO66) -> 0 | C66: HINT: If something doesn’t balance you will see the ERROR message come up | F66: CHECK | I66: =IF(SUM(I59:I64)=0, "-", "ERROR") -> - | J66: =IF(SUM(J59:J64)=0, "-", "ERROR") -> - | K66: =IF(SUM(K59:K64)=0, "-", "ERROR") -> - | L66: =IF(SUM(L59:L64)=0, "-", "ERROR") -> - | M66: =IF(SUM(M59:M64)=0, "-", "ERROR") -> - | N66: =IF(SUM(N59:N64)=0, "-", "ERROR") -> - | O66: =IF(SUM(O59:O64)=0, "-", "ERROR") -> - | P66: =IF(SUM(P59:P64)=0, "-", "ERROR") -> - | ... CO66: =IF(SUM(CO59:CO64)=0, "-", "ERROR") -> - | CP66: x
F68: IRR | I68: =XIRR($I55:$CO55,HoldingDates) -> 0.37547664
C69: HINT: Ratio of all positive equity cash flows over all equity injections | F69: CFx | I69: =SUMIF($I55:$CO55,">0")/-SUMIF($I55:$CO55,"<0") -> 2.9405664
C70: HINT: Sum of all equity cash flows (no discounting) | F70: Net Profit | I70: =SUM(I55:CO55) -> 23568475
F72: Capital Accounts
F74: Common Equity
F75: Beginning | I75: 0 | J75: =I78 -> 3678850.8 | K75: =J78 -> 3818996.4 | L75: =K78 -> 3959142.1 | M75: =L78 -> 4132868 | N75: =M78 -> 4450137.7 | O75: =N78 -> 4718393.9 | P75: =O78 -> 5174038.5 | Q75: =P78 -> 5871250 | ... CO75: =CN78 -> 12145153 | CP75: x
B76: =SUM(I76:CO76) -> 7917716.8 | D76: + | F76: ="Funding at "&TEXT(CommonEquityWeight,"0%") -> Funding at 45% | I76: =MIN(-SUM(I39:I40)*CommonEquityWeight,CommonEquityOBalance-I75) -> 3678850.8 | J76: =MIN(-SUM(J39:J40)*CommonEquityWeight,CommonEquityOBalance-J75) -> 140145.65 | K76: =MIN(-SUM(K39:K40)*CommonEquityWeight,CommonEquityOBalance-K75) -> 140145.65 | L76: =MIN(-SUM(L39:L40)*CommonEquityWeight,CommonEquityOBalance-L75) -> 150648.56 | M76: =MIN(-SUM(M39:M40)*CommonEquityWeight,CommonEquityOBalance-M75) -> 142771.38 | N76: =MIN(-SUM(N39:N40)*CommonEquityWeight,CommonEquityOBalance-N75) -> 120715.26 | O76: =MIN(-SUM(O39:O40)*CommonEquityWeight,CommonEquityOBalance-O75) -> 205040.06 | P76: =MIN(-SUM(P39:P40)*CommonEquityWeight,CommonEquityOBalance-P75) -> 313745.18 | ... CO76: =MIN(-SUM(CO39:CO40)*CommonEquityWeight,CommonEquityOBalance-CO75) -> 0 | CP76: x
F77: Funding at 100% | I77: =MIN(-SUM(I39:I40)-I76-I83,CommonEquityOBalance-SUM(I75:I76)) -> 0 | J77: =MIN(-SUM(J39:J40)-J76-J83,CommonEquityOBalance-SUM(J75:J76)) -> 0 | K77: =MIN(-SUM(K39:K40)-K76-K83,CommonEquityOBalance-SUM(K75:K76)) -> 0 | L77: =MIN(-SUM(L39:L40)-L76-L83,CommonEquityOBalance-SUM(L75:L76)) -> 23077.411 | M77: =MIN(-SUM(M39:M40)-M76-M83,CommonEquityOBalance-SUM(M75:M76)) -> 174498.35 | N77: =MIN(-SUM(N39:N40)-N76-N83,CommonEquityOBalance-SUM(N75:N76)) -> 147540.88 | O77: =MIN(-SUM(O39:O40)-O76-O83,CommonEquityOBalance-SUM(O75:O76)) -> 250604.52 | P77: =MIN(-SUM(P39:P40)-P76-P83,CommonEquityOBalance-SUM(P75:P76)) -> 383466.33 | ... CO77: =MIN(-SUM(CO39:CO40)-CO76-CO83,CommonEquityOBalance-SUM(CO75:CO76)) -> 0 | CP77: x
B78: =SUM(B75:B76) -> 7917716.8 | F78: Ending | I78: =SUM(I75:I77) -> 3678850.8 | J78: =SUM(J75:J77) -> 3818996.4 | K78: =SUM(K75:K77) -> 3959142.1 | L78: =SUM(L75:L77) -> 4132868 | M78: =SUM(M75:M77) -> 4450137.7 | N78: =SUM(N75:N77) -> 4718393.9 | O78: =SUM(O75:O77) -> 5174038.5 | P78: =SUM(P75:P77) -> 5871250 | ... CO78: =SUM(CO75:CO77) -> 12145153 | CP78: x
F80: Preferred Equity
F81: Beginning | I81: =H85 -> 0 | J81: =I85 -> 4496373.1 | K81: =J85 -> 4710327.4 | L81: =K85 -> 4926311.9 | M81: =L85 -> 5134105.2 | N81: =M85 -> 5182821.7 | O81: =N85 -> 5232000.4 | P81: =O85 -> 5281645.8 | ... CO81: =CN85 -> 0 | CP81: x
B82: =SUM(I82:CO82) -> 1838344.1 | C82: HINT: Need to adjust rate for a monthly model | D82: + | F82: Pref Accrual | G82: =(1+PreferredEquityReturn_Case2)^(1/12)-1 -> 0.0094887929 | I82: =I81*$G$82 -> 0 | J82: =J81*$G$82 -> 42665.154 | K82: =K81*$G$82 -> 44695.322 | L82: =L81*$G$82 -> 46744.753 | M82: =M81*$G$82 -> 48716.461 | N82: =N81*$G$82 -> 49178.722 | O82: =O81*$G$82 -> 49645.369 | P82: =P81*$G$82 -> 50116.443 | ... CO82: =CO81*$G$82 -> 0 | CP82: x
B83: =SUM(I83:CO83) -> 5000000 | D83: + | F83: Funding | I83: =MIN(-(SUM(I39:I40)+I76),PreferredEquityOBalance-SUM($H83:H83)) -> 4496373.1 | J83: =MIN(-(SUM(J39:J40)+J76),PreferredEquityOBalance-SUM($H83:I83)) -> 171289.13 | K83: =MIN(-(SUM(K39:K40)+K76),PreferredEquityOBalance-SUM($H83:J83)) -> 171289.13 | L83: =MIN(-(SUM(L39:L40)+L76),PreferredEquityOBalance-SUM($H83:K83)) -> 161048.6 | M83: =MIN(-(SUM(M39:M40)+M76),PreferredEquityOBalance-SUM($H83:L83)) -> 0 | N83: =MIN(-(SUM(N39:N40)+N76),PreferredEquityOBalance-SUM($H83:M83)) -> 0 | O83: =MIN(-(SUM(O39:O40)+O76),PreferredEquityOBalance-SUM($H83:N83)) -> 0 | P83: =MIN(-(SUM(P39:P40)+P76),PreferredEquityOBalance-SUM($H83:O83)) -> 0 | ... CO83: =MIN(-(SUM(CO39:CO40)+CO76),PreferredEquityOBalance-SUM($H83:CN83)) -> 0 | CP83: x
B84: =SUM(I84:CO84) -> -6838344.1 | C84: =-MIN(SUM(H78:H80),MAX(SUM(H36:H51),0)) | D84: – | F84: Repayment | I84: =-MIN(SUM(I81:I83),MAX(SUM(I38:I53),0)) -> 0 | J84: =-MIN(SUM(J81:J83),MAX(SUM(J38:J53),0)) -> 0 | K84: =-MIN(SUM(K81:K83),MAX(SUM(K38:K53),0)) -> 0 | L84: =-MIN(SUM(L81:L83),MAX(SUM(L38:L53),0)) -> 0 | M84: =-MIN(SUM(M81:M83),MAX(SUM(M38:M53),0)) -> 0 | N84: =-MIN(SUM(N81:N83),MAX(SUM(N38:N53),0)) -> 0 | O84: =-MIN(SUM(O81:O83),MAX(SUM(O38:O53),0)) -> 0 | P84: =-MIN(SUM(P81:P83),MAX(SUM(P38:P53),0)) -> 0 | ... CO84: =-MIN(SUM(CO81:CO83),MAX(SUM(CO38:CO53),0)) -> 0 | CP84: x
B85: =SUM(B82:B84) -> 0 | F85: Ending | I85: =SUM(I81:I84) -> 4496373.1 | J85: =SUM(J81:J84) -> 4710327.4 | K85: =SUM(K81:K84) -> 4926311.9 | L85: =SUM(L81:L84) -> 5134105.2 | M85: =SUM(M81:M84) -> 5182821.7 | N85: =SUM(N81:N84) -> 5232000.4 | O85: =SUM(O81:O84) -> 5281645.8 | P85: =SUM(P81:P84) -> 5331762.2 | ... CO85: =SUM(CO81:CO84) -> 0 | CP85: x
F87: Construction Loan
F88: Beginning | I88: =H91 -> 0 | J88: =I91 -> 0 | K88: =J91 -> 0 | L88: =K91 -> 0 | M88: =L91 -> 0 | N88: =M91 -> 0 | O88: =N91 -> 0 | P88: =O91 -> 0 | ... CO88: =CN91 -> 0 | CP88: x
B89: =SUM(I89:CO89) -> 11697956 | D89: + | F89: Funding | I89: =MIN(-(SUM(I39:I41)+SUM(I76:I77)+I83),ConstLoanOBalance-SUM($H89:H89)) -> 0 | J89: =MIN(-(SUM(J39:J41)+SUM(J76:J77)+J83),ConstLoanOBalance-SUM($H89:I89)) -> 0 | K89: =MIN(-(SUM(K39:K41)+SUM(K76:K77)+K83),ConstLoanOBalance-SUM($H89:J89)) -> 0 | L89: =MIN(-(SUM(L39:L41)+SUM(L76:L77)+L83),ConstLoanOBalance-SUM($H89:K89)) -> 0 | M89: =MIN(-(SUM(M39:M41)+SUM(M76:M77)+M83),ConstLoanOBalance-SUM($H89:L89)) -> 0 | N89: =MIN(-(SUM(N39:N41)+SUM(N76:N77)+N83),ConstLoanOBalance-SUM($H89:M89)) -> 0 | O89: =MIN(-(SUM(O39:O41)+SUM(O76:O77)+O83),ConstLoanOBalance-SUM($H89:N89)) -> 0 | P89: =MIN(-(SUM(P39:P41)+SUM(P76:P77)+P83),ConstLoanOBalance-SUM($H89:O89)) -> 0 | ... CO89: =MIN(-(SUM(CO39:CO41)+SUM(CO76:CO77)+CO83),ConstLoanOBalance-SUM($H89:CN89)) -> 0 | CP89: x
B90: =SUM(I90:CO90) -> -11697956 | D90: – | F90: Repayment | I90: =-SUM(I88:I89)*(Today=ConstLoanMaturityDate) -> 0 | J90: =-SUM(J88:J89)*(Today=ConstLoanMaturityDate) -> 0 | K90: =-SUM(K88:K89)*(Today=ConstLoanMaturityDate) -> 0 | L90: =-SUM(L88:L89)*(Today=ConstLoanMaturityDate) -> 0 | M90: =-SUM(M88:M89)*(Today=ConstLoanMaturityDate) -> 0 | N90: =-SUM(N88:N89)*(Today=ConstLoanMaturityDate) -> 0 | O90: =-SUM(O88:O89)*(Today=ConstLoanMaturityDate) -> 0 | P90: =-SUM(P88:P89)*(Today=ConstLoanMaturityDate) -> 0 | ... CO90: =-SUM(CO88:CO89)*(Today=ConstLoanMaturityDate) -> 0 | CP90: x
F91: Ending | I91: =SUM(I88:I90) -> 0 | J91: =SUM(J88:J90) -> 0 | K91: =SUM(K88:K90) -> 0 | L91: =SUM(L88:L90) -> 0 | M91: =SUM(M88:M90) -> 0 | N91: =SUM(N88:N90) -> 0 | O91: =SUM(O88:O90) -> 0 | P91: =SUM(P88:P90) -> 0 | ... CO91: =SUM(CO88:CO90) -> 0 | CP91: x
D93: + | F93: 1 Month LIBOR | I93: =INDEX(Libor!$C$11:$DS$11, MATCH(I28,Libor!$C$9:$DS$9,0)) -> 0.0014925 | J93: =INDEX(Libor!$C$11:$DS$11, MATCH(J28,Libor!$C$9:$DS$9,0)) -> 0.0015746 | K93: =INDEX(Libor!$C$11:$DS$11, MATCH(K28,Libor!$C$9:$DS$9,0)) -> 0.0016548 | L93: =INDEX(Libor!$C$11:$DS$11, MATCH(L28,Libor!$C$9:$DS$9,0)) -> 0.0017305 | M93: =INDEX(Libor!$C$11:$DS$11, MATCH(M28,Libor!$C$9:$DS$9,0)) -> 0.001734 | N93: =INDEX(Libor!$C$11:$DS$11, MATCH(N28,Libor!$C$9:$DS$9,0)) -> 0.0016393 | O93: =INDEX(Libor!$C$11:$DS$11, MATCH(O28,Libor!$C$9:$DS$9,0)) -> 0.0014936 | P93: =INDEX(Libor!$C$11:$DS$11, MATCH(P28,Libor!$C$9:$DS$9,0)) -> 0.0013758 | ... CO93: =INDEX(Libor!$C$11:$DS$11, MATCH(CO28,Libor!$C$9:$DS$9,0)) -> 0.0115155 | CP93: x
D94: + | F94: Spread | G94: =ConstLoanSpread -> 0.045 | I94: =$G$94 -> 0.045 | J94: =$G$94 -> 0.045 | K94: =$G$94 -> 0.045 | L94: =$G$94 -> 0.045 | M94: =$G$94 -> 0.045 | N94: =$G$94 -> 0.045 | O94: =$G$94 -> 0.045 | P94: =$G$94 -> 0.045 | ... CO94: =$G$94 -> 0.045 | CP94: x
F95: All-In Rate | I95: =SUM(I93:I94) -> 0.0464925 | J95: =SUM(J93:J94) -> 0.0465746 | K95: =SUM(K93:K94) -> 0.0466548 | L95: =SUM(L93:L94) -> 0.0467305 | M95: =SUM(M93:M94) -> 0.046734 | N95: =SUM(N93:N94) -> 0.0466393 | O95: =SUM(O93:O94) -> 0.0464936 | P95: =SUM(P93:P94) -> 0.0463758 | ... CO95: =SUM(CO93:CO94) -> 0.0565155 | CP95: x
B97: =SUM(I97:CO97) -> 762069.28 | C97: HINT: Use beginning bal to avoid circular reference. Adjust for Act / 360. "Days" in Row 22 can be helpful. | D97: + | F97: Interest Expense | I97: =I95*I88*DaysInMonth/ConstLoanType -> 0 | J97: =J95*J88*DaysInMonth/ConstLoanType -> 0 | K97: =K95*K88*DaysInMonth/ConstLoanType -> 0 | L97: =L95*L88*DaysInMonth/ConstLoanType -> 0 | M97: =M95*M88*DaysInMonth/ConstLoanType -> 0 | N97: =N95*N88*DaysInMonth/ConstLoanType -> 0 | O97: =O95*O88*DaysInMonth/ConstLoanType -> 0 | P97: =P95*P88*DaysInMonth/ConstLoanType -> 0 | ... CO97: =CO95*CO88*DaysInMonth/ConstLoanType -> 0 | CP97: x
B98: =SUM(I98:CO98) -> 197955.79 | C98: HINT: Difference between NOI and interest expense | D98: + | F98: Construction Period Interest | I98: =MAX(I97-NOI_Today,0) -> 0 | J98: =MAX(J97-NOI_Today,0) -> 0 | K98: =MAX(K97-NOI_Today,0) -> 0 | L98: =MAX(L97-NOI_Today,0) -> 0 | M98: =MAX(M97-NOI_Today,0) -> 0 | N98: =MAX(N97-NOI_Today,0) -> 0 | O98: =MAX(O97-NOI_Today,0) -> 0 | P98: =MAX(P97-NOI_Today,0) -> 0 | ... CO98: =MAX(CO97-NOI_Today,0) -> 0 | CP98: x
F100: Permanent Loan
F101: Beginning | I101: =H105 -> 0 | J101: =I105 -> 0 | K101: =J105 -> 0 | L101: =K105 -> 0 | M101: =L105 -> 0 | N101: =M105 -> 0 | O101: =N105 -> 0 | P101: =O105 -> 0 | ... CO101: =CN105 -> 0 | CP101: x
B102: =SUM(I102:CO102) -> 35005242 | D102: + | F102: Funding | I102: =PermanentLoanOBalance*(Today=PermanentLoanOriginationDate) -> 0 | J102: =PermanentLoanOBalance*(Today=PermanentLoanOriginationDate) -> 0 | K102: =PermanentLoanOBalance*(Today=PermanentLoanOriginationDate) -> 0 | L102: =PermanentLoanOBalance*(Today=PermanentLoanOriginationDate) -> 0 | M102: =PermanentLoanOBalance*(Today=PermanentLoanOriginationDate) -> 0 | N102: =PermanentLoanOBalance*(Today=PermanentLoanOriginationDate) -> 0 | O102: =PermanentLoanOBalance*(Today=PermanentLoanOriginationDate) -> 0 | P102: =PermanentLoanOBalance*(Today=PermanentLoanOriginationDate) -> 0 | ... CO102: =PermanentLoanOBalance*(Today=PermanentLoanOriginationDate) -> 0 | CP102: x
B103: =SUM(I103:CO103) -> -1145734.5 | D103: – | F103: Amortization | I103: =-I108 -> 0 | J103: =-J108 -> 0 | K103: =-K108 -> 0 | L103: =-L108 -> 0 | M103: =-M108 -> 0 | N103: =-N108 -> 0 | O103: =-O108 -> 0 | P103: =-P108 -> 0 | ... CO103: =-CO108 -> 0 | CP103: x
B104: =SUM(I104:CO104) -> -33859508 | D104: – | F104: Repayment | I104: =-SUM(I101:I103)*(Today=PermanentLoanMaturityDate) -> 0 | J104: =-SUM(J101:J103)*(Today=PermanentLoanMaturityDate) -> 0 | K104: =-SUM(K101:K103)*(Today=PermanentLoanMaturityDate) -> 0 | L104: =-SUM(L101:L103)*(Today=PermanentLoanMaturityDate) -> 0 | M104: =-SUM(M101:M103)*(Today=PermanentLoanMaturityDate) -> 0 | N104: =-SUM(N101:N103)*(Today=PermanentLoanMaturityDate) -> 0 | O104: =-SUM(O101:O103)*(Today=PermanentLoanMaturityDate) -> 0 | P104: =-SUM(P101:P103)*(Today=PermanentLoanMaturityDate) -> 0 | ... CO104: =-SUM(CO101:CO103)*(Today=PermanentLoanMaturityDate) -> 0 | CP104: x
F105: Ending | I105: =SUM(I101:I104) -> 0 | J105: =SUM(J101:J104) -> 0 | K105: =SUM(K101:K104) -> 0 | L105: =SUM(L101:L104) -> 0 | M105: =SUM(M101:M104) -> 0 | N105: =SUM(N101:N104) -> 0 | O105: =SUM(O101:O104) -> 0 | P105: =SUM(P101:P104) -> 0 | ... CO105: =SUM(CO101:CO104) -> 0 | CP105: x
B107: =SUM(I107:CO107) -> 7238332.5 | C107: HINT: Divide by 12 for monthly | D107: + | F107: Interest Expense | I107: =I101*PermanentLoanRate/12 -> 0 | J107: =J101*PermanentLoanRate/12 -> 0 | K107: =K101*PermanentLoanRate/12 -> 0 | L107: =L101*PermanentLoanRate/12 -> 0 | M107: =M101*PermanentLoanRate/12 -> 0 | N107: =N101*PermanentLoanRate/12 -> 0 | O107: =O101*PermanentLoanRate/12 -> 0 | P107: =P101*PermanentLoanRate/12 -> 0 | ... CO107: =CO101*PermanentLoanRate/12 -> 0 | CP107: x
B108: =SUM(I108:CO108) -> 1145734.5 | C108: HINT: Difference between payment and interest expense | D108: + | F108: Amortization | I108: =I110-I107 -> 0 | J108: =J110-J107 -> 0 | K108: =K110-K107 -> 0 | L108: =L110-L107 -> 0 | M108: =M110-M107 -> 0 | N108: =N110-N107 -> 0 | O108: =O110-O107 -> 0 | P108: =P110-P107 -> 0 | ... CO108: =CO110-CO107 -> 0 | CP108: x
F109: Payment Dummy | I109: =(Today>PermanentLoanOriginationDate)*(Today<=PermanentLoanMaturityDate) -> 0 | J109: =(Today>PermanentLoanOriginationDate)*(Today<=PermanentLoanMaturityDate) -> 0 | K109: =(Today>PermanentLoanOriginationDate)*(Today<=PermanentLoanMaturityDate) -> 0 | L109: =(Today>PermanentLoanOriginationDate)*(Today<=PermanentLoanMaturityDate) -> 0 | M109: =(Today>PermanentLoanOriginationDate)*(Today<=PermanentLoanMaturityDate) -> 0 | N109: =(Today>PermanentLoanOriginationDate)*(Today<=PermanentLoanMaturityDate) -> 0 | O109: =(Today>PermanentLoanOriginationDate)*(Today<=PermanentLoanMaturityDate) -> 0 | P109: =(Today>PermanentLoanOriginationDate)*(Today<=PermanentLoanMaturityDate) -> 0 | ... CO109: =(Today>PermanentLoanOriginationDate)*(Today<=PermanentLoanMaturityDate) -> 0 | CP109: x
B110: =SUM(I110:CO110) -> 8384067 | D110: + | F110: Payment | I110: =(PermanentLoanOBalance*PermanentLoanMortgageConstant/12)*PermanentLoanDebtServiceDummy -> 0 | J110: =(PermanentLoanOBalance*PermanentLoanMortgageConstant/12)*PermanentLoanDebtServiceDummy -> 0 | K110: =(PermanentLoanOBalance*PermanentLoanMortgageConstant/12)*PermanentLoanDebtServiceDummy -> 0 | L110: =(PermanentLoanOBalance*PermanentLoanMortgageConstant/12)*PermanentLoanDebtServiceDummy -> 0 | M110: =(PermanentLoanOBalance*PermanentLoanMortgageConstant/12)*PermanentLoanDebtServiceDummy -> 0 | N110: =(PermanentLoanOBalance*PermanentLoanMortgageConstant/12)*PermanentLoanDebtServiceDummy -> 0 | O110: =(PermanentLoanOBalance*PermanentLoanMortgageConstant/12)*PermanentLoanDebtServiceDummy -> 0 | P110: =(PermanentLoanOBalance*PermanentLoanMortgageConstant/12)*PermanentLoanDebtServiceDummy -> 0 | ... CO110: =(PermanentLoanOBalance*PermanentLoanMortgageConstant/12)*PermanentLoanDebtServiceDummy -> 0 | CP110: x
F112: Fees
B114: =SUM(I114:CO114) -> 23568475 | F114: Cash Flows to Equity | I114: =I55 -> -3678850.8 | J114: =J55 -> -140145.65 | K114: =K55 -> -140145.65 | L114: =L55 -> -173725.97 | M114: =M55 -> -317269.72 | N114: =N55 -> -268256.14 | O114: =O55 -> -455644.58 | P114: =P55 -> -697211.51 | ... CO114: =CO55 -> 0 | CP114: x
B115: =SUM(I115:CO115) -> -50000 | D115: – | F115: Acquisition Fee | H115: 0.01 | I115: =-(Today=ClosingDate)*LandCost*AcquisitionFee -> -50000 | J115: =-(Today=ClosingDate)*LandCost*AcquisitionFee -> 0 | K115: =-(Today=ClosingDate)*LandCost*AcquisitionFee -> 0 | L115: =-(Today=ClosingDate)*LandCost*AcquisitionFee -> 0 | M115: =-(Today=ClosingDate)*LandCost*AcquisitionFee -> 0 | N115: =-(Today=ClosingDate)*LandCost*AcquisitionFee -> 0 | O115: =-(Today=ClosingDate)*LandCost*AcquisitionFee -> 0 | P115: =-(Today=ClosingDate)*LandCost*AcquisitionFee -> 0 | ... CO115: =-(Today=ClosingDate)*LandCost*AcquisitionFee -> 0 | CP115: x
B116: =SUM(I116:CO116) -> -235149.05 | C116: HINT: See "Cumulative Equity Invested" metric above. Adjust for monthly | D116: – | F116: Asset Management Fee | H116: 0.008 | I116: =-I56*AssetManagementFee/12*(Today<=ExitDate) -> -2452.5672 | J116: =-J56*AssetManagementFee/12*(Today<=ExitDate) -> -2545.9976 | K116: =-K56*AssetManagementFee/12*(Today<=ExitDate) -> -2639.428 | L116: =-L56*AssetManagementFee/12*(Today<=ExitDate) -> -2755.2453 | M116: =-M56*AssetManagementFee/12*(Today<=ExitDate) -> -2966.7585 | N116: =-N56*AssetManagementFee/12*(Today<=ExitDate) -> -3145.5959 | O116: =-O56*AssetManagementFee/12*(Today<=ExitDate) -> -3449.359 | P116: =-P56*AssetManagementFee/12*(Today<=ExitDate) -> -3914.1667 | ... CO116: =-CO56*AssetManagementFee/12*(Today<=ExitDate) -> 0 | CP116: x
B117: =SUM(I117:CO117) -> -62209.358 | D117: – | F117: Disposition Fee | H117: 0.005 | I117: =-SUM(I47:I53)*DispositionFee*(Today=ExitDate) -> 0 | J117: =-SUM(J47:J53)*DispositionFee*(Today=ExitDate) -> 0 | K117: =-SUM(K47:K53)*DispositionFee*(Today=ExitDate) -> 0 | L117: =-SUM(L47:L53)*DispositionFee*(Today=ExitDate) -> 0 | M117: =-SUM(M47:M53)*DispositionFee*(Today=ExitDate) -> 0 | N117: =-SUM(N47:N53)*DispositionFee*(Today=ExitDate) -> 0 | O117: =-SUM(O47:O53)*DispositionFee*(Today=ExitDate) -> 0 | P117: =-SUM(P47:P53)*DispositionFee*(Today=ExitDate) -> 0 | ... CO117: =-SUM(CO47:CO53)*DispositionFee*(Today=ExitDate) -> 0 | CP117: x
F118: Cash Flows to Equity Net of Fees | I118: =SUM(I114:I117) -> -3731303.3 | J118: =SUM(J114:J117) -> -142691.65 | K118: =SUM(K114:K117) -> -142785.08 | L118: =SUM(L114:L117) -> -176481.21 | M118: =SUM(M114:M117) -> -320236.48 | N118: =SUM(N114:N117) -> -271401.74 | O118: =SUM(O114:O117) -> -459093.94 | P118: =SUM(P114:P117) -> -701125.68 | ... CO118: =SUM(CO114:CO117) -> 0 | CP118: x
H120: Sum of Fees | I120: =SUM(I115:CO117) -> -347358.41
F122: Net IRR (Pre-Promote) | I122: =IFERROR(XIRR($I118:$CO118,HoldingDates),XIRR($I118:$CO118,HoldingDates,-0.1)) -> 0.36700209
F123: CFx | I123: =SUMIF($I118:$CO118,">0")/-SUMIF($I118:$CO118,"<0") -> 2.8681056
F124: Net Profit | I124: =SUM(I118:CO118) -> 23221117
...

Sheet Q2 - Equity Waterfall 1
B2: =Inputs!B2 -> Comparing Complex Deal Structures
B4: Model: Equity Waterfall | E4: Scenario in Model: | G4: =Scenario!E4 -> Best Case | J4: Deal in Model: | L4: Case 1 - Eagle Investment & Fulcrum Capital
B6: PROMOTE
B8: Promote Structure | D8: Hurdle | H8: % of Cash Flows
D9: EMx | F9: Net Promote | G9: Sponsor % | H9: Co-Investor | I9: Sponsor
B10: Tier 1 | D10: 1.25 | F10: 0 | G10: 0 | H10: =1-I10 -> 1 | I10: 0
B11: Tier 2 - Catch up | D11: 1.25 | F11: =(I11-$I$10)/$H$10 -> 1 | G11: 1 | H11: =1-I11 -> 0 | I11: =$I$10+Tier2_Promote_Case1 -> 1
B12: Tier 3 | D12: 1.4 | F12: =(I12-$I$10)/$H$10 -> 0.5 | G12: 0.5 | H12: =1-I12 -> 0.5 | I12: =$I$10+Tier3_Promote_Case1 -> 0.5
B13: Thereafter | F13: =(I13-$I$10)/$H$10 -> 0.6 | G13: 0.6 | H13: =1-I13 -> 0.4 | I13: =$I$10+G13 -> 0.6
D17: Year | E17: =YEAR(E18) -> 2020 | F17: =YEAR(F18) -> 2021 | G17: =YEAR(G18) -> 2021 | H17: =YEAR(H18) -> 2021 | I17: =YEAR(I18) -> 2021 | J17: =YEAR(J18) -> 2021 | K17: =YEAR(K18) -> 2021 | L17: =YEAR(L18) -> 2021 | ... CK17: =YEAR(CK18) -> 2027 | CL17: x
D18: Date | E18: ='Provided - CAP Acct. 1'!I28 -> 44196 | F18: =EOMONTH(E18,1) -> 44227 | G18: =EOMONTH(F18,1) -> 44255 | H18: =EOMONTH(G18,1) -> 44286 | I18: =EOMONTH(H18,1) -> 44316 | J18: =EOMONTH(I18,1) -> 44347 | K18: =EOMONTH(J18,1) -> 44377 | L18: =EOMONTH(K18,1) -> 44408 | M18: =EOMONTH(L18,1) -> 44439 | ... CK18: =EOMONTH(CJ18,1) -> 46752 | CL18: x
D19: Days | E19: 31 | F19: =F18-E18 -> 31 | G19: =G18-F18 -> 28 | H19: =H18-G18 -> 31 | I19: =I18-H18 -> 30 | J19: =J18-I18 -> 31 | K19: =K18-J18 -> 30 | L19: =L18-K18 -> 31 | M19: =M18-L18 -> 31 | ... CK19: =CK18-CJ18 -> 31 | CL19: x
B21: Cash Flows to Equity
B23: Case 1 - Cash Flows to Equity Net of Fees | E23: ='Provided - CAP Acct. 1'!I117 -> -8230674.1 | F23: ='Provided - CAP Acct. 1'!J117 -> -317092.55 | G23: ='Provided - CAP Acct. 1'!K117 -> -317300.17 | H23: ='Provided - CAP Acct. 1'!L117 -> -340863.15 | I23: ='Provided - CAP Acct. 1'!M117 -> -323569.81 | J23: ='Provided - CAP Acct. 1'!N117 -> -274735.07 | K23: ='Provided - CAP Acct. 1'!O117 -> -462427.28 | L23: ='Provided - CAP Acct. 1'!P117 -> -704459.01 | ... CK23: ='Provided - CAP Acct. 1'!CO117 -> 0 | CL23: x
B25: Net IRR (Pre-Promote) | E25: =XIRR($E$23:$CK$23,HoldingDates) -> 0.3335279
B26: CFx | E26: =SUMIF($E23:$CK23,">0")/-SUMIF($E23:$CK23,"<0") -> 2.9428465
B27: Net Profit | E27: =SUM(E23:CK23) -> 24229917
B29: Tier 1
B31: Cash Flows to Distribute to Tier 1 | E31: =MAX(E23,0) -> 0 | F31: =MAX(F23,0) -> 0 | G31: =MAX(G23,0) -> 0 | H31: =MAX(H23,0) -> 0 | I31: =MAX(I23,0) -> 0 | J31: =MAX(J23,0) -> 0 | K31: =MAX(K23,0) -> 0 | L31: =MAX(L23,0) -> 0 | ... CK31: =MAX(CK23,0) -> 0 | CL31: x
B33: Beginning Balance - Co-investor | E33: =D37 -> 0 | F33: =E37 -> 9259508.3 | G33: =F37 -> 9616237.4 | H33: =G37 -> 9973200.1 | I33: =H37 -> 10356671 | J33: =I37 -> 10720687 | K33: =J37 -> 11029764 | L33: =K37 -> 11549995 | ... CK33: =CJ37 -> 0 | CL33: x
B34: Contributions | E34: =-MIN(E23,0)*CoInvestorEquityContributionPct -> 7407606.6 | F34: =-MIN(F23,0)*CoInvestorEquityContributionPct -> 285383.29 | G34: =-MIN(G23,0)*CoInvestorEquityContributionPct -> 285570.15 | H34: =-MIN(H23,0)*CoInvestorEquityContributionPct -> 306776.84 | I34: =-MIN(I23,0)*CoInvestorEquityContributionPct -> 291212.83 | J34: =-MIN(J23,0)*CoInvestorEquityContributionPct -> 247261.56 | K34: =-MIN(K23,0)*CoInvestorEquityContributionPct -> 416184.55 | L34: =-MIN(L23,0)*CoInvestorEquityContributionPct -> 634013.11 | ... CK34: =-MIN(CK23,0)*CoInvestorEquityContributionPct -> 0 | CL34: x
B35: Accrual for EMx Hurdle | E35: =E34*Tier1_Hurdle_Case1-E34 -> 1851901.7 | F35: =F34*Tier1_Hurdle_Case1-F34 -> 71345.823 | G35: =G34*Tier1_Hurdle_Case1-G34 -> 71392.538 | H35: =H34*Tier1_Hurdle_Case1-H34 -> 76694.209 | I35: =I34*Tier1_Hurdle_Case1-I34 -> 72803.208 | J35: =J34*Tier1_Hurdle_Case1-J34 -> 61815.391 | K35: =K34*Tier1_Hurdle_Case1-K34 -> 104046.14 | L35: =L34*Tier1_Hurdle_Case1-L34 -> 158503.28 | ... CK35: =CK34*Tier1_Hurdle_Case1-CK34 -> 0 | CL35: x
B36: Tier 1 Paydown | E36: =-MIN(SUM(E33:E35),E31*Tier1_CoInvestorPctCF_Case1) -> 0 | F36: =-MIN(SUM(F33:F35),F31*Tier1_CoInvestorPctCF_Case1) -> 0 | G36: =-MIN(SUM(G33:G35),G31*Tier1_CoInvestorPctCF_Case1) -> 0 | H36: =-MIN(SUM(H33:H35),H31*Tier1_CoInvestorPctCF_Case1) -> 0 | I36: =-MIN(SUM(I33:I35),I31*Tier1_CoInvestorPctCF_Case1) -> 0 | J36: =-MIN(SUM(J33:J35),J31*Tier1_CoInvestorPctCF_Case1) -> 0 | K36: =-MIN(SUM(K33:K35),K31*Tier1_CoInvestorPctCF_Case1) -> 0 | L36: =-MIN(SUM(L33:L35),L31*Tier1_CoInvestorPctCF_Case1) -> 0 | ... CK36: =-MIN(SUM(CK33:CK35),CK31*Tier1_CoInvestorPctCF_Case1) -> 0 | CL36: x
B37: Ending Balance | E37: =SUM(E33:E36) -> 9259508.3 | F37: =SUM(F33:F36) -> 9616237.4 | G37: =SUM(G33:G36) -> 9973200.1 | H37: =SUM(H33:H36) -> 10356671 | I37: =SUM(I33:I36) -> 10720687 | J37: =SUM(J33:J36) -> 11029764 | K37: =SUM(K33:K36) -> 11549995 | L37: =SUM(L33:L36) -> 12342511 | ... CK37: =SUM(CK33:CK36) -> 0 | CL37: x
B39: Cash Flows Distributed to Co-Investor at Tier 1 | E39: =-E36 -> 0 | F39: =-F36 -> 0 | G39: =-G36 -> 0 | H39: =-H36 -> 0 | I39: =-I36 -> 0 | J39: =-J36 -> 0 | K39: =-K36 -> 0 | L39: =-L36 -> 0 | ... CK39: =-CK36 -> 0 | CL39: x
B40: Cash Flows Distributed to Sponsor at Tier 1 | E40: =E39*Tier1_SponsorPctCF_Case1/Tier1_CoInvestorPctCF_Case1 -> 0 | F40: =F39*Tier1_SponsorPctCF_Case1/Tier1_CoInvestorPctCF_Case1 -> 0 | G40: =G39*Tier1_SponsorPctCF_Case1/Tier1_CoInvestorPctCF_Case1 -> 0 | H40: =H39*Tier1_SponsorPctCF_Case1/Tier1_CoInvestorPctCF_Case1 -> 0 | I40: =I39*Tier1_SponsorPctCF_Case1/Tier1_CoInvestorPctCF_Case1 -> 0 | J40: =J39*Tier1_SponsorPctCF_Case1/Tier1_CoInvestorPctCF_Case1 -> 0 | K40: =K39*Tier1_SponsorPctCF_Case1/Tier1_CoInvestorPctCF_Case1 -> 0 | L40: =L39*Tier1_SponsorPctCF_Case1/Tier1_CoInvestorPctCF_Case1 -> 0 | ... CK40: =CK39*Tier1_SponsorPctCF_Case1/Tier1_CoInvestorPctCF_Case1 -> 0 | CL40: x
B41: Total | E41: =SUM(E39:E40) -> 0 | F41: =SUM(F39:F40) -> 0 | G41: =SUM(G39:G40) -> 0 | H41: =SUM(H39:H40) -> 0 | I41: =SUM(I39:I40) -> 0 | J41: =SUM(J39:J40) -> 0 | K41: =SUM(K39:K40) -> 0 | L41: =SUM(L39:L40) -> 0 | ... CK41: =SUM(CK39:CK40) -> 0 | CL41: x
B43: Cash Flows to Co-Investor | E43: =-E34+E39 -> -7407606.6 | F43: =-F34+F39 -> -285383.29 | G43: =-G34+G39 -> -285570.15 | H43: =-H34+H39 -> -306776.84 | I43: =-I34+I39 -> -291212.83 | J43: =-J34+J39 -> -247261.56 | K43: =-K34+K39 -> -416184.55 | L43: =-L34+L39 -> -634013.11 | ... CK43: =-CK34+CK39 -> 0 | CL43: x
B44: Cash Flows to Sponsor | E44: =MIN(E23,0)*SponsorEquityContributionPct -> -823067.41 | F44: =MIN(F23,0)*SponsorEquityContributionPct -> -31709.255 | G44: =MIN(G23,0)*SponsorEquityContributionPct -> -31730.017 | H44: =MIN(H23,0)*SponsorEquityContributionPct -> -34086.315 | I44: =MIN(I23,0)*SponsorEquityContributionPct -> -32356.981 | J44: =MIN(J23,0)*SponsorEquityContributionPct -> -27473.507 | K44: =MIN(K23,0)*SponsorEquityContributionPct -> -46242.728 | L44: =MIN(L23,0)*SponsorEquityContributionPct -> -70445.901 | ... CK44: =MIN(CK23,0)*SponsorEquityContributionPct -> 0 | CL44: x
B45: Total | E45: =SUM(E43:E44) -> -8230674.1 | F45: =SUM(F43:F44) -> -317092.55 | G45: =SUM(G43:G44) -> -317300.17 | H45: =SUM(H43:H44) -> -340863.15 | I45: =SUM(I43:I44) -> -323569.81 | J45: =SUM(J43:J44) -> -274735.07 | K45: =SUM(K43:K44) -> -462427.28 | L45: =SUM(L43:L44) -> -704459.01 | ... CK45: =SUM(CK43:CK44) -> 0 | CL45: x
B47: Tier 1 IRR | E47: Co-Investor | F47: Sponsor | G47: Total
B48: IRR | E48: =XIRR(E43:CK43,HoldingDates) -> 0.082391265 | F48: =XIRR(E44:CK44,HoldingDates) -> #NUM! | G48: =XIRR(E45:CK45,HoldingDates) -> 0.042708787
B49: CFx | E49: =-SUMIF(E43:CK43,">"&0)/SUMIF(E43:CK43,"<"&0) -> 1.25 | F49: =-SUMIF(E44:CK44,">"&0)/SUMIF(E44:CK44,"<"&0) -> 0 | G49: =-SUMIF(E45:CK45,">"&0)/SUMIF(E45:CK45,"<"&0) -> 1.125
B50: Net Profit | E50: =SUM(E43:CK43) -> 2806053.6 | F50: =SUM(E44:CK44) -> -1247134.9 | G50: =SUM(E45:CK45) -> 1558918.6
B52: Tier 2
B54: Cash Flows to Distribute to Tier 2 | E54: =E31-E41 -> 0 | F54: =F31-F41 -> 0 | G54: =G31-G41 -> 0 | H54: =H31-H41 -> 0 | I54: =I31-I41 -> 0 | J54: =J31-J41 -> 0 | K54: =K31-K41 -> 0 | L54: =L31-L41 -> 0 | ... CK54: =CK31-CK41 -> 0 | CL54: x
B56: Beginning Balance - Sponsor | E56: =D61 -> 0 | F56: =E61 -> 1028834.3 | G56: =F61 -> 1068470.8 | H56: =G61 -> 1108133.3 | I56: =H61 -> 1150741.2 | J56: =I61 -> 1191187.5 | K56: =J61 -> 1225529.4 | L56: =K61 -> 1283332.8 | ... CK56: =CJ61 -> 0 | CL56: x
B57: Contributions | E57: =-MIN(E23,0)*SponsorEquityContributionPct -> 823067.41 | F57: =-MIN(F23,0)*SponsorEquityContributionPct -> 31709.255 | G57: =-MIN(G23,0)*SponsorEquityContributionPct -> 31730.017 | H57: =-MIN(H23,0)*SponsorEquityContributionPct -> 34086.315 | I57: =-MIN(I23,0)*SponsorEquityContributionPct -> 32356.981 | J57: =-MIN(J23,0)*SponsorEquityContributionPct -> 27473.507 | K57: =-MIN(K23,0)*SponsorEquityContributionPct -> 46242.728 | L57: =-MIN(L23,0)*SponsorEquityContributionPct -> 70445.901 | ... CK57: =-MIN(CK23,0)*SponsorEquityContributionPct -> 0 | CL57: x
B58: Accrual for EMx Hurdle | E58: =E57*(Tier2_Hurdle_Case1-1) -> 205766.85 | F58: =F57*(Tier2_Hurdle_Case1-1) -> 7927.3136 | G58: =G57*(Tier2_Hurdle_Case1-1) -> 7932.5042 | H58: =H57*(Tier2_Hurdle_Case1-1) -> 8521.5788 | I58: =I57*(Tier2_Hurdle_Case1-1) -> 8089.2454 | J58: =J57*(Tier2_Hurdle_Case1-1) -> 6868.3768 | K58: =K57*(Tier2_Hurdle_Case1-1) -> 11560.682 | L58: =L57*(Tier2_Hurdle_Case1-1) -> 17611.475 | ... CK58: =CK57*(Tier2_Hurdle_Case1-1) -> 0 | CL58: x
B59: Tier 1 Paydown | E59: =-E40 -> 0 | F59: =-F40 -> 0 | G59: =-G40 -> 0 | H59: =-H40 -> 0 | I59: =-I40 -> 0 | J59: =-J40 -> 0 | K59: =-K40 -> 0 | L59: =-L40 -> 0 | ... CK59: =-CK40 -> 0 | CL59: x
B60: Tier 2 Paydown | E60: =-MIN(SUM(E56:E59),E54*Tier2_SponsorPctCF_Case1) -> 0 | F60: =-MIN(SUM(F56:F59),F54*Tier2_SponsorPctCF_Case1) -> 0 | G60: =-MIN(SUM(G56:G59),G54*Tier2_SponsorPctCF_Case1) -> 0 | H60: =-MIN(SUM(H56:H59),H54*Tier2_SponsorPctCF_Case1) -> 0 | I60: =-MIN(SUM(I56:I59),I54*Tier2_SponsorPctCF_Case1) -> 0 | J60: =-MIN(SUM(J56:J59),J54*Tier2_SponsorPctCF_Case1) -> 0 | K60: =-MIN(SUM(K56:K59),K54*Tier2_SponsorPctCF_Case1) -> 0 | L60: =-MIN(SUM(L56:L59),L54*Tier2_SponsorPctCF_Case1) -> 0 | ... CK60: =-MIN(SUM(CK56:CK59),CK54*Tier2_SponsorPctCF_Case1) -> 0 | CL60: x
B61: Ending Balance | E61: =SUM(E56:E60) -> 1028834.3 | F61: =SUM(F56:F60) -> 1068470.8 | G61: =SUM(G56:G60) -> 1108133.3 | H61: =SUM(H56:H60) -> 1150741.2 | I61: =SUM(I56:I60) -> 1191187.5 | J61: =SUM(J56:J60) -> 1225529.4 | K61: =SUM(K56:K60) -> 1283332.8 | L61: =SUM(L56:L60) -> 1371390.1 | ... CK61: =SUM(CK56:CK60) -> 0 | CL61: x
B63: Cash Flows Distributed to Co-Investor at Tier 2 | E63: =E64*Tier2_CoInvestorPctCF_Case1/Tier2_SponsorPctCF_Case1 -> 0 | F63: =F64*Tier2_CoInvestorPctCF_Case1/Tier2_SponsorPctCF_Case1 -> 0 | G63: =G64*Tier2_CoInvestorPctCF_Case1/Tier2_SponsorPctCF_Case1 -> 0 | H63: =H64*Tier2_CoInvestorPctCF_Case1/Tier2_SponsorPctCF_Case1 -> 0 | I63: =I64*Tier2_CoInvestorPctCF_Case1/Tier2_SponsorPctCF_Case1 -> 0 | J63: =J64*Tier2_CoInvestorPctCF_Case1/Tier2_SponsorPctCF_Case1 -> 0 | K63: =K64*Tier2_CoInvestorPctCF_Case1/Tier2_SponsorPctCF_Case1 -> 0 | L63: =L64*Tier2_CoInvestorPctCF_Case1/Tier2_SponsorPctCF_Case1 -> 0 | ... CK63: =CK64*Tier2_CoInvestorPctCF_Case1/Tier2_SponsorPctCF_Case1 -> 0 | CL63: x
B64: Cash Flows Distributed to Sponsor at Tier 2 | E64: =-E60 -> 0 | F64: =-F60 -> 0 | G64: =-G60 -> 0 | H64: =-H60 -> 0 | I64: =-I60 -> 0 | J64: =-J60 -> 0 | K64: =-K60 -> 0 | L64: =-L60 -> 0 | ... CK64: =-CK60 -> 0 | CL64: x
B65: Total | E65: =SUM(E63:E64) -> 0 | F65: =SUM(F63:F64) -> 0 | G65: =SUM(G63:G64) -> 0 | H65: =SUM(H63:H64) -> 0 | I65: =SUM(I63:I64) -> 0 | J65: =SUM(J63:J64) -> 0 | K65: =SUM(K63:K64) -> 0 | L65: =SUM(L63:L64) -> 0 | ... CK65: =SUM(CK63:CK64) -> 0 | CL65: x
B67: Cash Flows to Co-Investor | E67: =SUM(E63,E43) -> -7407606.6 | F67: =SUM(F63,F43) -> -285383.29 | G67: =SUM(G63,G43) -> -285570.15 | H67: =SUM(H63,H43) -> -306776.84 | I67: =SUM(I63,I43) -> -291212.83 | J67: =SUM(J63,J43) -> -247261.56 | K67: =SUM(K63,K43) -> -416184.55 | L67: =SUM(L63,L43) -> -634013.11 | ... CK67: =SUM(CK63,CK43) -> 0 | CL67: x
B68: Cash Flows to Sponsor | E68: =SUM(E64,E44) -> -823067.41 | F68: =SUM(F64,F44) -> -31709.255 | G68: =SUM(G64,G44) -> -31730.017 | H68: =SUM(H64,H44) -> -34086.315 | I68: =SUM(I64,I44) -> -32356.981 | J68: =SUM(J64,J44) -> -27473.507 | K68: =SUM(K64,K44) -> -46242.728 | L68: =SUM(L64,L44) -> -70445.901 | ... CK68: =SUM(CK64,CK44) -> 0 | CL68: x
B69: Total | E69: =SUM(E65,E45) -> -8230674.1 | F69: =SUM(F65,F45) -> -317092.55 | G69: =SUM(G65,G45) -> -317300.17 | H69: =SUM(H65,H45) -> -340863.15 | I69: =SUM(I65,I45) -> -323569.81 | J69: =SUM(J65,J45) -> -274735.07 | K69: =SUM(K65,K45) -> -462427.28 | L69: =SUM(L65,L45) -> -704459.01 | ... CK69: =SUM(CK65,CK45) -> 0 | CL69: x
B71: Tier 2 IRR | E71: Co-Investor | F71: Sponsor | G71: Total
B72: IRR | E72: =XIRR(E67:CK67,HoldingDates) -> 0.082391265 | F72: =XIRR(E68:CK68,HoldingDates) -> 0.082391265 | G72: =XIRR(E69:CK69,HoldingDates) -> 0.082391265
B73: CFx | E73: =-SUMIF(E67:CK67,">"&0)/SUMIF(E67:CK67,"<"&0) -> 1.25 | F73: =-SUMIF(E68:CK68,">"&0)/SUMIF(E68:CK68,"<"&0) -> 1.25 | G73: =-SUMIF(E69:CK69,">"&0)/SUMIF(E69:CK69,"<"&0) -> 1.25
B74: Net Profit | E74: =SUM(E67:CK67) -> 2806053.6 | F74: =SUM(E68:CK68) -> 311783.73 | G74: =SUM(E69:CK69) -> 3117837.3
B76: Tier 3
B78: Cash Flows to Distribute to Tier 3 | E78: =E54-E65 -> 0 | F78: =F54-F65 -> 0 | G78: =G54-G65 -> 0 | H78: =H54-H65 -> 0 | I78: =I54-I65 -> 0 | J78: =J54-J65 -> 0 | K78: =K54-K65 -> 0 | L78: =L54-L65 -> 0 | ... CK78: =CK54-CK65 -> 0 | CL78: x
B80: Beginning Balance - Co-investor | E80: =D86 -> 0 | F80: =E86 -> 10370649 | G80: =F86 -> 10770186 | H80: =G86 -> 11169984 | I80: =H86 -> 11599472 | J80: =I86 -> 12007170 | K80: =J86 -> 12353336 | L80: =K86 -> 12935994 | ... CK80: =CJ86 -> 0 | CL80: x
B81: Contributions | E81: =E34 -> 7407606.6 | F81: =F34 -> 285383.29 | G81: =G34 -> 285570.15 | H81: =H34 -> 306776.84 | I81: =I34 -> 291212.83 | J81: =J34 -> 247261.56 | K81: =K34 -> 416184.55 | L81: =L34 -> 634013.11 | ... CK81: =CK34 -> 0 | CL81: x
B82: Accrual for EMx Hurdle | E82: =E81*(Tier3_Hurdle_Case1-1) -> 2963042.7 | F82: =F81*(Tier3_Hurdle_Case1-1) -> 114153.32 | G82: =G81*(Tier3_Hurdle_Case1-1) -> 114228.06 | H82: =H81*(Tier3_Hurdle_Case1-1) -> 122710.73 | I82: =I81*(Tier3_Hurdle_Case1-1) -> 116485.13 | J82: =J81*(Tier3_Hurdle_Case1-1) -> 98904.626 | K82: =K81*(Tier3_Hurdle_Case1-1) -> 166473.82 | L82: =L81*(Tier3_Hurdle_Case1-1) -> 253605.25 | ... CK82: =CK81*(Tier3_Hurdle_Case1-1) -> 0 | CL82: x
B83: Tier 1 Paydown | E83: =-E39 -> 0 | F83: =-F39 -> 0 | G83: =-G39 -> 0 | H83: =-H39 -> 0 | I83: =-I39 -> 0 | J83: =-J39 -> 0 | K83: =-K39 -> 0 | L83: =-L39 -> 0 | ... CK83: =-CK39 -> 0 | CL83: x
B84: Tier 2 Paydown | E84: =-E63 -> 0 | F84: =-F63 -> 0 | G84: =-G63 -> 0 | H84: =-H63 -> 0 | I84: =-I63 -> 0 | J84: =-J63 -> 0 | K84: =-K63 -> 0 | L84: =-L63 -> 0 | ... CK84: =-CK63 -> 0 | CL84: x
B85: Tier 3 Paydown | E85: =-MIN(SUM(E80:E84),E78*Tier3_CoInvestorPctCF_Case1) -> 0 | F85: =-MIN(SUM(F80:F84),F78*Tier3_CoInvestorPctCF_Case1) -> 0 | G85: =-MIN(SUM(G80:G84),G78*Tier3_CoInvestorPctCF_Case1) -> 0 | H85: =-MIN(SUM(H80:H84),H78*Tier3_CoInvestorPctCF_Case1) -> 0 | I85: =-MIN(SUM(I80:I84),I78*Tier3_CoInvestorPctCF_Case1) -> 0 | J85: =-MIN(SUM(J80:J84),J78*Tier3_CoInvestorPctCF_Case1) -> 0 | K85: =-MIN(SUM(K80:K84),K78*Tier3_CoInvestorPctCF_Case1) -> 0 | L85: =-MIN(SUM(L80:L84),L78*Tier3_CoInvestorPctCF_Case1) -> 0 | ... CK85: =-MIN(SUM(CK80:CK84),CK78*Tier3_CoInvestorPctCF_Case1) -> 0 | CL85: x
B86: Ending Balance | E86: =SUM(E80:E85) -> 10370649 | F86: =SUM(F80:F85) -> 10770186 | G86: =SUM(G80:G85) -> 11169984 | H86: =SUM(H80:H85) -> 11599472 | I86: =SUM(I80:I85) -> 12007170 | J86: =SUM(J80:J85) -> 12353336 | K86: =SUM(K80:K85) -> 12935994 | L86: =SUM(L80:L85) -> 13823613 | ... CK86: =SUM(CK80:CK85) -> 0 | CL86: x
B88: Cash Flows Distributed to Co-Investor at Tier 3 | E88: =-E85 -> 0 | F88: =-F85 -> 0 | G88: =-G85 -> 0 | H88: =-H85 -> 0 | I88: =-I85 -> 0 | J88: =-J85 -> 0 | K88: =-K85 -> 0 | L88: =-L85 -> 0 | ... CK88: =-CK85 -> 0 | CL88: x
B89: Cash Flows Distributed to Sponsor at Tier 3 | E89: =E88*Tier3_SponsorPctCF_Case1/Tier3_CoInvestorPctCF_Case1 -> 0 | F89: =F88*Tier3_SponsorPctCF_Case1/Tier3_CoInvestorPctCF_Case1 -> 0 | G89: =G88*Tier3_SponsorPctCF_Case1/Tier3_CoInvestorPctCF_Case1 -> 0 | H89: =H88*Tier3_SponsorPctCF_Case1/Tier3_CoInvestorPctCF_Case1 -> 0 | I89: =I88*Tier3_SponsorPctCF_Case1/Tier3_CoInvestorPctCF_Case1 -> 0 | J89: =J88*Tier3_SponsorPctCF_Case1/Tier3_CoInvestorPctCF_Case1 -> 0 | K89: =K88*Tier3_SponsorPctCF_Case1/Tier3_CoInvestorPctCF_Case1 -> 0 | L89: =L88*Tier3_SponsorPctCF_Case1/Tier3_CoInvestorPctCF_Case1 -> 0 | ... CK89: =CK88*Tier3_SponsorPctCF_Case1/Tier3_CoInvestorPctCF_Case1 -> 0 | CL89: x
B90: Total | E90: =SUM(E88:E89) -> 0 | F90: =SUM(F88:F89) -> 0 | G90: =SUM(G88:G89) -> 0 | H90: =SUM(H88:H89) -> 0 | I90: =SUM(I88:I89) -> 0 | J90: =SUM(J88:J89) -> 0 | K90: =SUM(K88:K89) -> 0 | L90: =SUM(L88:L89) -> 0 | ... CK90: =SUM(CK88:CK89) -> 0 | CL90: x
B92: Cash Flows to Co-Investor | E92: =SUM(E88,E67) -> -7407606.6 | F92: =SUM(F88,F67) -> -285383.29 | G92: =SUM(G88,G67) -> -285570.15 | H92: =SUM(H88,H67) -> -306776.84 | I92: =SUM(I88,I67) -> -291212.83 | J92: =SUM(J88,J67) -> -247261.56 | K92: =SUM(K88,K67) -> -416184.55 | L92: =SUM(L88,L67) -> -634013.11 | ... CK92: =SUM(CK88,CK67) -> 0 | CL92: x
B93: Cash Flows to Sponsor | E93: =SUM(E89,E68) -> -823067.41 | F93: =SUM(F89,F68) -> -31709.255 | G93: =SUM(G89,G68) -> -31730.017 | H93: =SUM(H89,H68) -> -34086.315 | I93: =SUM(I89,I68) -> -32356.981 | J93: =SUM(J89,J68) -> -27473.507 | K93: =SUM(K89,K68) -> -46242.728 | L93: =SUM(L89,L68) -> -70445.901 | ... CK93: =SUM(CK89,CK68) -> 0 | CL93: x
B94: Total | E94: =SUM(E90,E69) -> -8230674.1 | F94: =SUM(F90,F69) -> -317092.55 | G94: =SUM(G90,G69) -> -317300.17 | H94: =SUM(H90,H69) -> -340863.15 | I94: =SUM(I90,I69) -> -323569.81 | J94: =SUM(J90,J69) -> -274735.07 | K94: =SUM(K90,K69) -> -462427.28 | L94: =SUM(L90,L69) -> -704459.01 | ... CK94: =SUM(CK90,CK69) -> 0 | CL94: x
B96: Tier 3 IRR | E96: Co-Investor | F96: Sponsor | G96: Total
B97: IRR | E97: =XIRR(E92:CK92,HoldingDates) -> 0.12669399 | F97: =XIRR(E93:CK93,HoldingDates) -> 0.4013172 | G97: =XIRR(E94:CK94,HoldingDates) -> 0.15993008
B98: CFx | E98: =-SUMIF(E92:CK92,">"&0)/SUMIF(E92:CK92,"<"&0) -> 1.4 | F98: =-SUMIF(E93:CK93,">"&0)/SUMIF(E93:CK93,"<"&0) -> 2.6 | G98: =-SUMIF(E94:CK94,">"&0)/SUMIF(E94:CK94,"<"&0) -> 1.52
B99: Net Profit | E99: =SUM(E92:CK92) -> 4489685.7 | F99: =SUM(E93:CK93) -> 1995415.9 | G99: =SUM(E94:CK94) -> 6485101.6
B101: Tier 4
B103: Cash Flows Remaining to Distribute to Tier 4 | E103: =E78-E90 -> 0 | F103: =F78-F90 -> 0 | G103: =G78-G90 -> 0 | H103: =H78-H90 -> 0 | I103: =I78-I90 -> 0 | J103: =J78-J90 -> 0 | K103: =K78-K90 -> 0 | L103: =L78-L90 -> 0 | ... CK103: =CK78-CK90 -> 0 | CL103: x
B104: =TEXT(H13,"0.0%")&" to Co-Investor" -> 40.0% to Co-Investor | E104: =E103*Tier4_CoInvestorPctCF_Case1 -> 0 | F104: =F103*Tier4_CoInvestorPctCF_Case1 -> 0 | G104: =G103*Tier4_CoInvestorPctCF_Case1 -> 0 | H104: =H103*Tier4_CoInvestorPctCF_Case1 -> 0 | I104: =I103*Tier4_CoInvestorPctCF_Case1 -> 0 | J104: =J103*Tier4_CoInvestorPctCF_Case1 -> 0 | K104: =K103*Tier4_CoInvestorPctCF_Case1 -> 0 | L104: =L103*Tier4_CoInvestorPctCF_Case1 -> 0 | ... CK104: =CK103*Tier4_CoInvestorPctCF_Case1 -> 0 | CL104: x
B105: =TEXT(I13,"0.0%")&" to Sponsor" -> 60.0% to Sponsor | E105: =E103*Tier4_SponsorPctCF_Case1 -> 0 | F105: =F103*Tier4_SponsorPctCF_Case1 -> 0 | G105: =G103*Tier4_SponsorPctCF_Case1 -> 0 | H105: =H103*Tier4_SponsorPctCF_Case1 -> 0 | I105: =I103*Tier4_SponsorPctCF_Case1 -> 0 | J105: =J103*Tier4_SponsorPctCF_Case1 -> 0 | K105: =K103*Tier4_SponsorPctCF_Case1 -> 0 | L105: =L103*Tier4_SponsorPctCF_Case1 -> 0 | ... CK105: =CK103*Tier4_SponsorPctCF_Case1 -> 0 | CL105: x
B107: Cash Flows Distributed to Co-Investor at Tier 4 | E107: =E104 -> 0 | F107: =F104 -> 0 | G107: =G104 -> 0 | H107: =H104 -> 0 | I107: =I104 -> 0 | J107: =J104 -> 0 | K107: =K104 -> 0 | L107: =L104 -> 0 | ... CK107: =CK104 -> 0 | CL107: x
B108: Cash Flows Distributed to Sponsor at Tier 4 | E108: =E105 -> 0 | F108: =F105 -> 0 | G108: =G105 -> 0 | H108: =H105 -> 0 | I108: =I105 -> 0 | J108: =J105 -> 0 | K108: =K105 -> 0 | L108: =L105 -> 0 | ... CK108: =CK105 -> 0 | CL108: x
B109: Total | E109: =SUM(E107:E108) -> 0 | F109: =SUM(F107:F108) -> 0 | G109: =SUM(G107:G108) -> 0 | H109: =SUM(H107:H108) -> 0 | I109: =SUM(I107:I108) -> 0 | J109: =SUM(J107:J108) -> 0 | K109: =SUM(K107:K108) -> 0 | L109: =SUM(L107:L108) -> 0 | ... CK109: =SUM(CK107:CK108) -> 0 | CL109: x
B111: Cash Flows to Co-Investor | E111: =E92+E107 -> -7407606.6 | F111: =F92+F107 -> -285383.29 | G111: =G92+G107 -> -285570.15 | H111: =H92+H107 -> -306776.84 | I111: =I92+I107 -> -291212.83 | J111: =J92+J107 -> -247261.56 | K111: =K92+K107 -> -416184.55 | L111: =L92+L107 -> -634013.11 | ... CK111: =CK92+CK107 -> 0 | CL111: x
B112: Cash Flows to Sponsor | E112: =E93+E108 -> -823067.41 | F112: =F93+F108 -> -31709.255 | G112: =G93+G108 -> -31730.017 | H112: =H93+H108 -> -34086.315 | I112: =I93+I108 -> -32356.981 | J112: =J93+J108 -> -27473.507 | K112: =K93+K108 -> -46242.728 | L112: =L93+L108 -> -70445.901 | ... CK112: =CK93+CK108 -> 0 | CL112: x
B113: Total | E113: =E94+E109 -> -8230674.1 | F113: =F94+F109 -> -317092.55 | G113: =G94+G109 -> -317300.17 | H113: =H94+H109 -> -340863.15 | I113: =I94+I109 -> -323569.81 | J113: =J94+J109 -> -274735.07 | K113: =K94+K109 -> -462427.28 | L113: =L94+L109 -> -704459.01 | ... CK113: =CK94+CK109 -> 0 | CL113: x
B115: Tier 4 IRR | E115: Co-Investor | F115: Sponsor | G115: Total
B116: IRR | E116: =XIRR(E111:CK111,HoldingDates) -> 0.22900502 | F116: =XIRR(E112:CK112,HoldingDates) -> 0.78426007 | G116: =XIRR(E113:CK113,HoldingDates) -> 0.3335279
B117: CFx | E117: =-SUMIF(E111:CK111,">"&0)/SUMIF(E111:CK111,"<"&0) -> 2.0323762 | F117: =-SUMIF(E112:CK112,">"&0)/SUMIF(E112:CK112,"<"&0) -> 11.137079 | G117: =-SUMIF(E113:CK113,">"&0)/SUMIF(E113:CK113,"<"&0) -> 2.9428465
B118: Net Profit | E118: =SUM(E111:CK111) -> 11587612 | F118: =SUM(E112:CK112) -> 12642305 | G118: =SUM(E113:CK113) -> 24229917
B120: Adjustment for Fees to Sponsor
B122: Cash Flows to Sponsor | E122: =E112 -> -823067.41 | F122: =F112 -> -31709.255 | G122: =G112 -> -31730.017 | H122: =H112 -> -34086.315 | I122: =I112 -> -32356.981 | J122: =J112 -> -27473.507 | K122: =K112 -> -46242.728 | L122: =L112 -> -70445.901 | ... CK122: =CK112 -> 0 | CL122: x
B123: Adjustment for Fees | E123: =SUM('Provided - CAP Acct. 1'!I114:I116) -> -55450.149 | F123: =SUM('Provided - CAP Acct. 1'!J114:J116) -> -5657.7724 | G123: =SUM('Provided - CAP Acct. 1'!K114:K116) -> -5865.3956 | H123: =SUM('Provided - CAP Acct. 1'!L114:L116) -> -6088.5787 | I123: =SUM('Provided - CAP Acct. 1'!M114:M116) -> -6300.0918 | J123: =SUM('Provided - CAP Acct. 1'!N114:N116) -> -6478.9293 | K123: =SUM('Provided - CAP Acct. 1'!O114:O116) -> -6782.6923 | L123: =SUM('Provided - CAP Acct. 1'!P114:P116) -> -7247.5 | ... CK123: =SUM('Provided - CAP Acct. 1'!CO114:CO116) -> 0 | CL123: x
B124: Cash Flows to Sponsor + Fees | E124: =E122-E123 -> -767617.26 | F124: =F122-F123 -> -26051.482 | G124: =G122-G123 -> -25864.621 | H124: =H122-H123 -> -27997.736 | I124: =I122-I123 -> -26056.89 | J124: =J122-J123 -> -20994.578 | K124: =K122-K123 -> -39460.035 | L124: =L122-L123 -> -63198.402 | ... CK124: =CK122-CK123 -> 0 | CL124: x
B126: Adjusted Sponsor IRR | E126: =IFERROR(XIRR(E124:CK124,HoldingDates,-0.1),XIRR(E124:CK124,HoldingDates)) -> 0.86798524
B127: CFx | E127: =-SUMIF(E124:CK124,">"&0)/SUMIF(E124:CK124,"<"&0) -> 12.735117
B128: Net Profit | E128: =SUM(E124:CK124) -> 13030711

Sheet Q3 - Equity Waterfall 2
B2: =Inputs!B2 -> Comparing Complex Deal Structures
B4: Model: Equity Waterfall | E4: Scenario in Model: | G4: =Scenario!E4 -> Best Case | J4: Deal in Model: | L4: Case 2 - SCP
B6: PROMOTE
B8: Promote Structure | D8: Hurdle | J8: % of Cash Flows
D9: Monthly | E9: Annual | F9: EMx | H9: Net Promote | I9: Sponsor % | J9: Co-Investor | K9: Sponsor
B10: Tier 1 | D10: =(1+Tier1_HurdleRate_Case2)^(1/12)-1 -> 0.0040741238 | E10: 0.05 | F10: 1.25 | H10: 0 | I10: 0 | J10: =1-K10 -> 1 | K10: 0
B11: Tier 2 - Catch up | D11: =(1+Tier2_HurdleRate_Case2)^(1/12)-1 -> 0.0040741238 | E11: 0.05 | F11: 1.25 | H11: =(K11-$K$10)/$J$10 -> 1 | I11: 1 | J11: =1-K11 -> 0 | K11: =$K$10+Tier2_Promote_Case1 -> 1
B12: Tier 3 | D12: =(1+Tier3_HurdleRate_Case2)^(1/12)-1 -> 0.0079741404 | E12: 0.1 | F12: 1.4 | H12: =(K12-$K$10)/$J$10 -> 0.5 | I12: 0.5 | J12: =1-K12 -> 0.5 | K12: =$K$10+Tier3_Promote_Case1 -> 0.5
B13: Thereafter | H13: =(K13-$K$10)/$J$10 -> 0.6 | I13: 0.6 | J13: =1-K13 -> 0.4 | K13: =$K$10+I13 -> 0.6
D17: Year | E17: =YEAR(E18) -> 2020 | F17: =YEAR(F18) -> 2021 | G17: =YEAR(G18) -> 2021 | H17: =YEAR(H18) -> 2021 | I17: =YEAR(I18) -> 2021 | J17: =YEAR(J18) -> 2021 | K17: =YEAR(K18) -> 2021 | L17: =YEAR(L18) -> 2021 | ... CK17: =YEAR(CK18) -> 2027 | CL17: x
D18: Date | E18: ='Provided - CAP Acct. 1'!I28 -> 44196 | F18: =EOMONTH(E18,1) -> 44227 | G18: =EOMONTH(F18,1) -> 44255 | H18: =EOMONTH(G18,1) -> 44286 | I18: =EOMONTH(H18,1) -> 44316 | J18: =EOMONTH(I18,1) -> 44347 | K18: =EOMONTH(J18,1) -> 44377 | L18: =EOMONTH(K18,1) -> 44408 | M18: =EOMONTH(L18,1) -> 44439 | ... CK18: =EOMONTH(CJ18,1) -> 46752 | CL18: x
D19: Days | E19: 31 | F19: =F18-E18 -> 31 | G19: =G18-F18 -> 28 | H19: =H18-G18 -> 31 | I19: =I18-H18 -> 30 | J19: =J18-I18 -> 31 | K19: =K18-J18 -> 30 | L19: =L18-K18 -> 31 | M19: =M18-L18 -> 31 | ... CK19: =CK18-CJ18 -> 31 | CL19: x
B21: Cash Flows to Equity
B23: Case 2 - Cash Flows to Equity Net of Fees | E23: ='Q1 - CAP Acct. 2'!I118 -> -3731303.3 | F23: ='Q1 - CAP Acct. 2'!J118 -> -142691.65 | G23: ='Q1 - CAP Acct. 2'!K118 -> -142785.08 | H23: ='Q1 - CAP Acct. 2'!L118 -> -176481.21 | I23: ='Q1 - CAP Acct. 2'!M118 -> -320236.48 | J23: ='Q1 - CAP Acct. 2'!N118 -> -271401.74 | K23: ='Q1 - CAP Acct. 2'!O118 -> -459093.94 | L23: ='Q1 - CAP Acct. 2'!P118 -> -701125.68 | ... CK23: ='Q1 - CAP Acct. 2'!CO118 -> 0 | CL23: x
B25: Net IRR (Pre-Promote) | E25: =XIRR($E$23:$CK$23,HoldingDates) -> 0.36700209
B26: CFx | E26: =SUMIF($E23:$CK23,">0")/-SUMIF($E23:$CK23,"<0") -> 2.8681056
B27: Net Profit | E27: =SUM(E23:CK23) -> 23221117
B29: Tier 1
B31: Cash Flows to Distribute to Tier 1 | E31: =MAX(E23,0) -> 0 | F31: =MAX(F23,0) -> 0 | G31: =MAX(G23,0) -> 0 | H31: =MAX(H23,0) -> 0 | I31: =MAX(I23,0) -> 0 | J31: =MAX(J23,0) -> 0 | K31: =MAX(K23,0) -> 0 | L31: =MAX(L23,0) -> 0 | ... CK31: =MAX(CK23,0) -> 0 | CL31: x
B33: Beginning Balance - Co-investor | E33: =D40 -> 0 | F33: =E40 -> 4197716.2 | G33: =F40 -> 4358244.3 | H33: =G40 -> 4518877.5 | I33: =H40 -> 4717418.9 | J33: =I40 -> 5077685 | K33: =J40 -> 5383011.9 | L33: =K40 -> 5899492.6 | ... CK33: =CJ40 -> 0 | CL33: x
B34: Contributions | E34: =-MIN(E23,0)*CoInvestorEquityContributionPct -> 3358173 | F34: =-MIN(F23,0)*CoInvestorEquityContributionPct -> 128422.48 | G34: =-MIN(G23,0)*CoInvestorEquityContributionPct -> 128506.57 | H34: =-MIN(H23,0)*CoInvestorEquityContributionPct -> 158833.09 | I34: =-MIN(I23,0)*CoInvestorEquityContributionPct -> 288212.83 | J34: =-MIN(J23,0)*CoInvestorEquityContributionPct -> 244261.56 | K34: =-MIN(K23,0)*CoInvestorEquityContributionPct -> 413184.55 | L34: =-MIN(L23,0)*CoInvestorEquityContributionPct -> 631013.11 | ... CK34: =-MIN(CK23,0)*CoInvestorEquityContributionPct -> 0 | CL34: x
B35: Accrual for IRR Hurdle | E35: =MAX((D37+D39)*Tier1_HurdleMonthly_Case2,0) -> 0 | F35: =MAX((E37+E39)*Tier1_HurdleMonthly_Case2,0) -> 13681.612 | G35: =MAX((F37+F39)*Tier1_HurdleMonthly_Case2,0) -> 14260.562 | H35: =MAX((G37+G39)*Tier1_HurdleMonthly_Case2,0) -> 14842.213 | I35: =MAX((H37+H39)*Tier1_HurdleMonthly_Case2,0) -> 15549.788 | J35: =MAX((I37+I39)*Tier1_HurdleMonthly_Case2,0) -> 16787.354 | K35: =MAX((J37+J39)*Tier1_HurdleMonthly_Case2,0) -> 17850.9 | L35: =MAX((K37+K39)*Tier1_HurdleMonthly_Case2,0) -> 19606.992 | ... CK35: =MAX((CJ37+CJ39)*Tier1_HurdleMonthly_Case2,0) -> 0 | CL35: x
B36: Accrual for EMx Hurdle | E36: =MAX(E34*(Tier1_Hurdle_EM_Case2-1),0) -> 839543.25 | F36: =MAX(F34*(Tier1_Hurdle_EM_Case2-1),0) -> 32105.62 | G36: =MAX(G34*(Tier1_Hurdle_EM_Case2-1),0) -> 32126.642 | H36: =MAX(H34*(Tier1_Hurdle_EM_Case2-1),0) -> 39708.273 | I36: =MAX(I34*(Tier1_Hurdle_EM_Case2-1),0) -> 72053.208 | J36: =MAX(J34*(Tier1_Hurdle_EM_Case2-1),0) -> 61065.391 | K36: =MAX(K34*(Tier1_Hurdle_EM_Case2-1),0) -> 103296.14 | L36: =MAX(L34*(Tier1_Hurdle_EM_Case2-1),0) -> 157753.28 | ... CK36: =MAX(CK34*(Tier1_Hurdle_EM_Case2-1),0) -> 0 | CL36: x
B37: Balance to Pay for IRR Hurdle | E37: =MAX(D37+D39+E34+E35,0) -> 3358173 | F37: =MAX(E37+E39+F34+F35,0) -> 3500277.1 | G37: =MAX(F37+F39+G34+G35,0) -> 3643044.2 | H37: =MAX(G37+G39+H34+H35,0) -> 3816719.5 | I37: =MAX(H37+H39+I34+I35,0) -> 4120482.1 | J37: =MAX(I37+I39+J34+J35,0) -> 4381531.1 | K37: =MAX(J37+J39+K34+K35,0) -> 4812566.5 | L37: =MAX(K37+K39+L34+L35,0) -> 5463186.6 | ... CK37: =MAX(CJ37+CJ39+CK34+CK35,0) -> 0 | CL37: x
B38: Balance to Pay for EMx Hurdle | E38: =MAX(D38+D39+E34+E36,0) -> 4197716.2 | F38: =MAX(E38+E39+F34+F36,0) -> 4358244.3 | G38: =MAX(F38+F39+G34+G36,0) -> 4518877.5 | H38: =MAX(G38+G39+H34+H36,0) -> 4717418.9 | I38: =MAX(H38+H39+I34+I36,0) -> 5077685 | J38: =MAX(I38+I39+J34+J36,0) -> 5383011.9 | K38: =MAX(J38+J39+K34+K36,0) -> 5899492.6 | L38: =MAX(K38+K39+L34+L36,0) -> 6688259 | ... CK38: =MAX(CJ38+CJ39+CK34+CK36,0) -> 0 | CL38: x
B39: Tier 1 Paydown | E39: =-MIN(MAX(E37:E38),E31*Tier1_CoInvestorPctCF_Case2) -> 0 | F39: =-MIN(MAX(F37:F38),F31*Tier1_CoInvestorPctCF_Case2) -> 0 | G39: =-MIN(MAX(G37:G38),G31*Tier1_CoInvestorPctCF_Case2) -> 0 | H39: =-MIN(MAX(H37:H38),H31*Tier1_CoInvestorPctCF_Case2) -> 0 | I39: =-MIN(MAX(I37:I38),I31*Tier1_CoInvestorPctCF_Case2) -> 0 | J39: =-MIN(MAX(J37:J38),J31*Tier1_CoInvestorPctCF_Case2) -> 0 | K39: =-MIN(MAX(K37:K38),K31*Tier1_CoInvestorPctCF_Case2) -> 0 | L39: =-MIN(MAX(L37:L38),L31*Tier1_CoInvestorPctCF_Case2) -> 0 | ... CK39: =-MIN(MAX(CK37:CK38),CK31*Tier1_CoInvestorPctCF_Case2) -> 0 | CL39: x
B40: Ending Balance | E40: =MAX(E37:E38)+E39 -> 4197716.2 | F40: =MAX(F37:F38)+F39 -> 4358244.3 | G40: =MAX(G37:G38)+G39 -> 4518877.5 | H40: =MAX(H37:H38)+H39 -> 4717418.9 | I40: =MAX(I37:I38)+I39 -> 5077685 | J40: =MAX(J37:J38)+J39 -> 5383011.9 | K40: =MAX(K37:K38)+K39 -> 5899492.6 | L40: =MAX(L37:L38)+L39 -> 6688259 | ... CK40: =MAX(CK37:CK38)+CK39 -> 0 | CL40: x
B42: Cash Flows Distributed to Co-Investor at Tier 1 | E42: =-E39 -> 0 | F42: =-F39 -> 0 | G42: =-G39 -> 0 | H42: =-H39 -> 0 | I42: =-I39 -> 0 | J42: =-J39 -> 0 | K42: =-K39 -> 0 | L42: =-L39 -> 0 | ... CK42: =-CK39 -> 0 | CL42: x
B43: Cash Flows Distributed to Sponsor at Tier 1 | E43: =E42*Tier1_SponsorPctCF_Case2/Tier1_CoInvestorPctCF_Case2 -> 0 | F43: =F42*Tier1_SponsorPctCF_Case2/Tier1_CoInvestorPctCF_Case2 -> 0 | G43: =G42*Tier1_SponsorPctCF_Case2/Tier1_CoInvestorPctCF_Case2 -> 0 | H43: =H42*Tier1_SponsorPctCF_Case2/Tier1_CoInvestorPctCF_Case2 -> 0 | I43: =I42*Tier1_SponsorPctCF_Case2/Tier1_CoInvestorPctCF_Case2 -> 0 | J43: =J42*Tier1_SponsorPctCF_Case2/Tier1_CoInvestorPctCF_Case2 -> 0 | K43: =K42*Tier1_SponsorPctCF_Case2/Tier1_CoInvestorPctCF_Case2 -> 0 | L43: =L42*Tier1_SponsorPctCF_Case2/Tier1_CoInvestorPctCF_Case2 -> 0 | ... CK43: =CK42*Tier1_SponsorPctCF_Case2/Tier1_CoInvestorPctCF_Case2 -> 0 | CL43: x
B44: Total | E44: =SUM(E42:E43) -> 0 | F44: =SUM(F42:F43) -> 0 | G44: =SUM(G42:G43) -> 0 | H44: =SUM(H42:H43) -> 0 | I44: =SUM(I42:I43) -> 0 | J44: =SUM(J42:J43) -> 0 | K44: =SUM(K42:K43) -> 0 | L44: =SUM(L42:L43) -> 0 | ... CK44: =SUM(CK42:CK43) -> 0 | CL44: x
B46: Cash Flows to Co-Investor | E46: =-E34+E42 -> -3358173 | F46: =-F34+F42 -> -128422.48 | G46: =-G34+G42 -> -128506.57 | H46: =-H34+H42 -> -158833.09 | I46: =-I34+I42 -> -288212.83 | J46: =-J34+J42 -> -244261.56 | K46: =-K34+K42 -> -413184.55 | L46: =-L34+L42 -> -631013.11 | ... CK46: =-CK34+CK42 -> 0 | CL46: x
B47: Cash Flows to Sponsor | E47: =MIN(E23,0)*SponsorEquityContributionPct -> -373130.33 | F47: =MIN(F23,0)*SponsorEquityContributionPct -> -14269.165 | G47: =MIN(G23,0)*SponsorEquityContributionPct -> -14278.508 | H47: =MIN(H23,0)*SponsorEquityContributionPct -> -17648.121 | I47: =MIN(I23,0)*SponsorEquityContributionPct -> -32023.648 | J47: =MIN(J23,0)*SponsorEquityContributionPct -> -27140.174 | K47: =MIN(K23,0)*SponsorEquityContributionPct -> -45909.394 | L47: =MIN(L23,0)*SponsorEquityContributionPct -> -70112.568 | ... CK47: =MIN(CK23,0)*SponsorEquityContributionPct -> 0 | CL47: x
B48: Total | E48: =SUM(E46:E47) -> -3731303.3 | F48: =SUM(F46:F47) -> -142691.65 | G48: =SUM(G46:G47) -> -142785.08 | H48: =SUM(H46:H47) -> -176481.21 | I48: =SUM(I46:I47) -> -320236.48 | J48: =SUM(J46:J47) -> -271401.74 | K48: =SUM(K46:K47) -> -459093.94 | L48: =SUM(L46:L47) -> -701125.68 | ... CK48: =SUM(CK46:CK47) -> 0 | CL48: x
B50: Tier 1 IRR | E50: Co-Investor | F50: Sponsor | G50: Total
B51: IRR | E51: =XIRR(E46:CK46,HoldingDates) -> 0.096860534 | F51: =XIRR(E47:CK47,HoldingDates) -> #NUM! | G51: =XIRR(E48:CK48,HoldingDates) -> 0.050119779
B52: CFx | E52: =-SUMIF(E46:CK46,">"&0)/SUMIF(E46:CK46,"<"&0) -> 1.25 | F52: =-SUMIF(E47:CK47,">"&0)/SUMIF(E47:CK47,"<"&0) -> 0 | G52: =-SUMIF(E48:CK48,">"&0)/SUMIF(E48:CK48,"<"&0) -> 1.125
B53: Net Profit | E53: =SUM(E46:CK46) -> 2796818 | F53: =SUM(E47:CK47) -> -1243030.2 | G53: =SUM(E48:CK48) -> 1553787.8
B55: Tier 2
B57: Cash Flows to Distribute to Tier 2 | E57: =E31-E44 -> 0 | F57: =F31-F44 -> 0 | G57: =G31-G44 -> 0 | H57: =H31-H44 -> 0 | I57: =I31-I44 -> 0 | J57: =J31-J44 -> 0 | K57: =K31-K44 -> 0 | L57: =L31-L44 -> 0 | ... CK57: =CK31-CK44 -> 0 | CL57: x
B59: Beginning Balance - Sponsor | E59: =D67 -> 0 | F59: =E67 -> 466412.92 | G59: =F67 -> 484249.37 | H59: =G67 -> 502097.51 | I59: =H67 -> 524157.66 | J59: =I67 -> 564187.22 | K59: =J67 -> 598112.43 | L59: =K67 -> 655499.18 | ... CK59: =CJ67 -> 0 | CL59: x
B60: Contributions | E60: =-MIN(E23,0)*SponsorEquityContributionPct -> 373130.33 | F60: =-MIN(F23,0)*SponsorEquityContributionPct -> 14269.165 | G60: =-MIN(G23,0)*SponsorEquityContributionPct -> 14278.508 | H60: =-MIN(H23,0)*SponsorEquityContributionPct -> 17648.121 | I60: =-MIN(I23,0)*SponsorEquityContributionPct -> 32023.648 | J60: =-MIN(J23,0)*SponsorEquityContributionPct -> 27140.174 | K60: =-MIN(K23,0)*SponsorEquityContributionPct -> 45909.394 | L60: =-MIN(L23,0)*SponsorEquityContributionPct -> 70112.568 | ... CK60: =-MIN(CK23,0)*SponsorEquityContributionPct -> 0 | CL60: x
B61: Accrual for IRR Hurdle | E61: =MAX((D63+D65+D66)*Tier2_HurdleMonthly_Case2,0) -> 0 | F61: =MAX((E63+E65+E66)*Tier2_HurdleMonthly_Case2,0) -> 1520.1792 | G61: =MAX((F63+F65+F66)*Tier2_HurdleMonthly_Case2,0) -> 1584.5069 | H61: =MAX((G63+G65+G66)*Tier2_HurdleMonthly_Case2,0) -> 1649.1348 | I61: =MAX((H63+H65+H66)*Tier2_HurdleMonthly_Case2,0) -> 1727.7542 | J61: =MAX((I63+I65+I66)*Tier2_HurdleMonthly_Case2,0) -> 1865.2616 | K61: =MAX((J63+J65+J66)*Tier2_HurdleMonthly_Case2,0) -> 1983.4333 | L61: =MAX((K63+K65+K66)*Tier2_HurdleMonthly_Case2,0) -> 2178.5546 | ... CK61: =MAX((CJ63+CJ65+CJ66)*Tier2_HurdleMonthly_Case2,0) -> 0 | CL61: x
B62: Accrual for EMx Hurdle | E62: =MAX(E60*(Tier2_Hurdle_EM_Case2-1),0) -> 93282.583 | F62: =MAX(F60*(Tier2_Hurdle_EM_Case2-1),0) -> 3567.2911 | G62: =MAX(G60*(Tier2_Hurdle_EM_Case2-1),0) -> 3569.6269 | H62: =MAX(H60*(Tier2_Hurdle_EM_Case2-1),0) -> 4412.0304 | I62: =MAX(I60*(Tier2_Hurdle_EM_Case2-1),0) -> 8005.912 | J62: =MAX(J60*(Tier2_Hurdle_EM_Case2-1),0) -> 6785.0435 | K62: =MAX(K60*(Tier2_Hurdle_EM_Case2-1),0) -> 11477.349 | L62: =MAX(L60*(Tier2_Hurdle_EM_Case2-1),0) -> 17528.142 | ... CK62: =MAX(CK60*(Tier2_Hurdle_EM_Case2-1),0) -> 0 | CL62: x
B63: Balance to Pay for IRR Hurdle | E63: =MAX(D63+D66+E60+E61,0) -> 373130.33 | F63: =MAX(E63+E66+F60+F61,0) -> 388919.68 | G63: =MAX(F63+F66+G60+G61,0) -> 404782.69 | H63: =MAX(G63+G66+H60+H61,0) -> 424079.95 | I63: =MAX(H63+H66+I60+I61,0) -> 457831.35 | J63: =MAX(I63+I66+J60+J61,0) -> 486836.78 | K63: =MAX(J63+J66+K60+K61,0) -> 534729.61 | L63: =MAX(K63+K66+L60+L61,0) -> 607020.73 | ... CK63: =MAX(CJ63+CJ66+CK60+CK61,0) -> 0 | CL63: x
B64: Balance to Pay for EMx Hurdle | E64: =MAX(D64+D66+E60+E62,0) -> 466412.92 | F64: =MAX(E64+E66+F60+F62,0) -> 484249.37 | G64: =MAX(F64+F66+G60+G62,0) -> 502097.51 | H64: =MAX(G64+G66+H60+H62,0) -> 524157.66 | I64: =MAX(H64+H66+I60+I62,0) -> 564187.22 | J64: =MAX(I64+I66+J60+J62,0) -> 598112.43 | K64: =MAX(J64+J66+K60+K62,0) -> 655499.18 | L64: =MAX(K64+K66+L60+L62,0) -> 743139.89 | ... CK64: =MAX(CJ64+CJ66+CK60+CK62,0) -> 0 | CL64: x
B65: Tier 1 Paydown | E65: =-E43 -> 0 | F65: =-F43 -> 0 | G65: =-G43 -> 0 | H65: =-H43 -> 0 | I65: =-I43 -> 0 | J65: =-J43 -> 0 | K65: =-K43 -> 0 | L65: =-L43 -> 0 | ... CK65: =-CK43 -> 0 | CL65: x
B66: Tier 2 Paydown | E66: =-MIN(MAX(E63:E64)+E65,E57*Tier2_SponsorPctCF_Case2) -> 0 | F66: =-MIN(MAX(F63:F64)+F65,F57*Tier2_SponsorPctCF_Case2) -> 0 | G66: =-MIN(MAX(G63:G64)+G65,G57*Tier2_SponsorPctCF_Case2) -> 0 | H66: =-MIN(MAX(H63:H64)+H65,H57*Tier2_SponsorPctCF_Case2) -> 0 | I66: =-MIN(MAX(I63:I64)+I65,I57*Tier2_SponsorPctCF_Case2) -> 0 | J66: =-MIN(MAX(J63:J64)+J65,J57*Tier2_SponsorPctCF_Case2) -> 0 | K66: =-MIN(MAX(K63:K64)+K65,K57*Tier2_SponsorPctCF_Case2) -> 0 | L66: =-MIN(MAX(L63:L64)+L65,L57*Tier2_SponsorPctCF_Case2) -> 0 | ... CK66: =-MIN(MAX(CK63:CK64)+CK65,CK57*Tier2_SponsorPctCF_Case2) -> 0 | CL66: x
B67: Ending Balance | E67: =MAX(E63:E64)+E65+E66 -> 466412.92 | F67: =MAX(F63:F64)+F65+F66 -> 484249.37 | G67: =MAX(G63:G64)+G65+G66 -> 502097.51 | H67: =MAX(H63:H64)+H65+H66 -> 524157.66 | I67: =MAX(I63:I64)+I65+I66 -> 564187.22 | J67: =MAX(J63:J64)+J65+J66 -> 598112.43 | K67: =MAX(K63:K64)+K65+K66 -> 655499.18 | L67: =MAX(L63:L64)+L65+L66 -> 743139.89 | ... CK67: =MAX(CK63:CK64)+CK65+CK66 -> 0 | CL67: x
B69: Cash Flows Distributed to Co-Investor at Tier 2 | E69: =E70*Tier2_CoInvestorPctCF_Case2/Tier2_SponsorPctCF_Case2 -> 0 | F69: =F70*Tier2_CoInvestorPctCF_Case2/Tier2_SponsorPctCF_Case2 -> 0 | G69: =G70*Tier2_CoInvestorPctCF_Case2/Tier2_SponsorPctCF_Case2 -> 0 | H69: =H70*Tier2_CoInvestorPctCF_Case2/Tier2_SponsorPctCF_Case2 -> 0 | I69: =I70*Tier2_CoInvestorPctCF_Case2/Tier2_SponsorPctCF_Case2 -> 0 | J69: =J70*Tier2_CoInvestorPctCF_Case2/Tier2_SponsorPctCF_Case2 -> 0 | K69: =K70*Tier2_CoInvestorPctCF_Case2/Tier2_SponsorPctCF_Case2 -> 0 | L69: =L70*Tier2_CoInvestorPctCF_Case2/Tier2_SponsorPctCF_Case2 -> 0 | ... CK69: =CK70*Tier2_CoInvestorPctCF_Case2/Tier2_SponsorPctCF_Case2 -> 0 | CL69: x
B70: Cash Flows Distributed to Sponsor at Tier 2 | E70: =-E66 -> 0 | F70: =-F66 -> 0 | G70: =-G66 -> 0 | H70: =-H66 -> 0 | I70: =-I66 -> 0 | J70: =-J66 -> 0 | K70: =-K66 -> 0 | L70: =-L66 -> 0 | ... CK70: =-CK66 -> 0 | CL70: x
B71: Total | E71: =SUM(E69:E70) -> 0 | F71: =SUM(F69:F70) -> 0 | G71: =SUM(G69:G70) -> 0 | H71: =SUM(H69:H70) -> 0 | I71: =SUM(I69:I70) -> 0 | J71: =SUM(J69:J70) -> 0 | K71: =SUM(K69:K70) -> 0 | L71: =SUM(L69:L70) -> 0 | ... CK71: =SUM(CK69:CK70) -> 0 | CL71: x
B73: Cash Flows to Co-Investor | E73: =E46+E69 -> -3358173 | F73: =F46+F69 -> -128422.48 | G73: =G46+G69 -> -128506.57 | H73: =H46+H69 -> -158833.09 | I73: =I46+I69 -> -288212.83 | J73: =J46+J69 -> -244261.56 | K73: =K46+K69 -> -413184.55 | L73: =L46+L69 -> -631013.11 | ... CK73: =CK46+CK69 -> 0 | CL73: x
B74: Cash Flows to Sponsor | E74: =E47+E70 -> -373130.33 | F74: =F47+F70 -> -14269.165 | G74: =G47+G70 -> -14278.508 | H74: =H47+H70 -> -17648.121 | I74: =I47+I70 -> -32023.648 | J74: =J47+J70 -> -27140.174 | K74: =K47+K70 -> -45909.394 | L74: =L47+L70 -> -70112.568 | ... CK74: =CK47+CK70 -> 0 | CL74: x
B75: Total | E75: =E48+E71 -> -3731303.3 | F75: =F48+F71 -> -142691.65 | G75: =G48+G71 -> -142785.08 | H75: =H48+H71 -> -176481.21 | I75: =I48+I71 -> -320236.48 | J75: =J48+J71 -> -271401.74 | K75: =K48+K71 -> -459093.94 | L75: =L48+L71 -> -701125.68 | ... CK75: =CK48+CK71 -> 0 | CL75: x
B77: Tier 2 IRR | E77: Co-Investor | F77: Sponsor | G77: Total
B78: IRR | E78: =XIRR(E73:CK73,HoldingDates) -> 0.096860534 | F78: =XIRR(E74:CK74,HoldingDates) -> 0.096860534 | G78: =XIRR(E75:CK75,HoldingDates) -> 0.096860534
B79: CFx | E79: =-SUMIF(E73:CK73,">"&0)/SUMIF(E73:CK73,"<"&0) -> 1.25 | F79: =-SUMIF(E74:CK74,">"&0)/SUMIF(E74:CK74,"<"&0) -> 1.25 | G79: =-SUMIF(E75:CK75,">"&0)/SUMIF(E75:CK75,"<"&0) -> 1.25
B80: Net Profit | E80: =SUM(E73:CK73) -> 2796818 | F80: =SUM(E74:CK74) -> 310757.55 | G80: =SUM(E75:CK75) -> 3107575.5
B82: Tier 3
B84: Cash Flows to Distribute to Tier 3 | E84: =E57-E71 -> 0 | F84: =F57-F71 -> 0 | G84: =G57-G71 -> 0 | H84: =H57-H71 -> 0 | I84: =I57-I71 -> 0 | J84: =J57-J71 -> 0 | K84: =K57-K71 -> 0 | L84: =L57-L71 -> 0 | ... CK84: =CK57-CK71 -> 0 | CL84: x
B86: Beginning Balance - Co-investor | E86: =D95 -> 0 | F86: =E95 -> 4701442.2 | G86: =F95 -> 4881233.7 | H86: =G95 -> 5061142.9 | I86: =H95 -> 5283509.2 | J86: =I95 -> 5687007.2 | K86: =J95 -> 6028973.3 | L86: =K95 -> 6607431.7 | ... CK86: =CJ95 -> 0 | CL86: x
B87: Contributions | E87: =E34 -> 3358173 | F87: =F34 -> 128422.48 | G87: =G34 -> 128506.57 | H87: =H34 -> 158833.09 | I87: =I34 -> 288212.83 | J87: =J34 -> 244261.56 | K87: =K34 -> 413184.55 | L87: =L34 -> 631013.11 | ... CK87: =CK34 -> 0 | CL87: x
B88: Accrual for IRR Hurdle | E88: =MAX((D90+D92+D93+D94)*Tier3_HurdleMonthly_Case2,0) -> 0 | F88: =MAX((E90+E92+E93+E94)*Tier3_HurdleMonthly_Case2,0) -> 26778.543 | G88: =MAX((F90+F92+F93+F94)*Tier3_HurdleMonthly_Case2,0) -> 28016.138 | H88: =MAX((G90+G92+G93+G94)*Tier3_HurdleMonthly_Case2,0) -> 29264.272 | I88: =MAX((H90+H92+H93+H94)*Tier3_HurdleMonthly_Case2,0) -> 30764.187 | J88: =MAX((I90+I92+I93+I94)*Tier3_HurdleMonthly_Case2,0) -> 33307.754 | K88: =MAX((J90+J92+J93+J94)*Tier3_HurdleMonthly_Case2,0) -> 35521.131 | L88: =MAX((K90+K92+K93+K94)*Tier3_HurdleMonthly_Case2,0) -> 39099.173 | ... CK88: =MAX((CJ90+CJ92+CJ93+CJ94)*Tier3_HurdleMonthly_Case2,0) -> 0 | CL88: x
B89: Accrual for EMx Hurdle | E89: =MAX(E87*(Tier3_Hurdle_EM_Case2-1),0) -> 1343269.2 | F89: =MAX(F87*(Tier3_Hurdle_EM_Case2-1),0) -> 51368.992 | G89: =MAX(G87*(Tier3_Hurdle_EM_Case2-1),0) -> 51402.627 | H89: =MAX(H87*(Tier3_Hurdle_EM_Case2-1),0) -> 63533.237 | I89: =MAX(I87*(Tier3_Hurdle_EM_Case2-1),0) -> 115285.13 | J89: =MAX(J87*(Tier3_Hurdle_EM_Case2-1),0) -> 97704.626 | K89: =MAX(K87*(Tier3_Hurdle_EM_Case2-1),0) -> 165273.82 | L89: =MAX(L87*(Tier3_Hurdle_EM_Case2-1),0) -> 252405.25 | ... CK89: =MAX(CK87*(Tier3_Hurdle_EM_Case2-1),0) -> 0 | CL89: x
B90: Balance to Pay for IRR Hurdle | E90: =MAX(D90+E87+E88+D94+SUM(D92:D93),0) -> 3358173 | F90: =MAX(E90+F87+F88+E94+SUM(E92:E93),0) -> 3513374 | G90: =MAX(F90+G87+G88+F94+SUM(F92:F93),0) -> 3669896.7 | H90: =MAX(G90+H87+H88+G94+SUM(G92:G93),0) -> 3857994.1 | I90: =MAX(H90+I87+I88+H94+SUM(H92:H93),0) -> 4176971.1 | J90: =MAX(I90+J87+J88+I94+SUM(I92:I93),0) -> 4454540.4 | K90: =MAX(J90+K87+K88+J94+SUM(J92:J93),0) -> 4903246.1 | L90: =MAX(K90+L87+L88+K94+SUM(K92:K93),0) -> 5573358.4 | ... CK90: =MAX(CJ90+CK87+CK88+CJ94+SUM(CJ92:CJ93),0) -> 0 | CL90: x
B91: Balance to Pay for EMx Hurdle | E91: =MAX(D91+E87+E89+D94+SUM(D92:D93),0) -> 4701442.2 | F91: =MAX(E91+F87+F89+E94+SUM(E92:E93),0) -> 4881233.7 | G91: =MAX(F91+G87+G89+F94+SUM(F92:F93),0) -> 5061142.9 | H91: =MAX(G91+H87+H89+G94+SUM(G92:G93),0) -> 5283509.2 | I91: =MAX(H91+I87+I89+H94+SUM(H92:H93),0) -> 5687007.2 | J91: =MAX(I91+J87+J89+I94+SUM(I92:I93),0) -> 6028973.3 | K91: =MAX(J91+K87+K89+J94+SUM(J92:J93),0) -> 6607431.7 | L91: =MAX(K91+L87+L89+K94+SUM(K92:K93),0) -> 7490850.1 | ... CK91: =MAX(CJ91+CK87+CK89+CJ94+SUM(CJ92:CJ93),0) -> 0 | CL91: x
B92: Tier 1 Paydown | E92: =-E42 -> 0 | F92: =-F42 -> 0 | G92: =-G42 -> 0 | H92: =-H42 -> 0 | I92: =-I42 -> 0 | J92: =-J42 -> 0 | K92: =-K42 -> 0 | L92: =-L42 -> 0 | ... CK92: =-CK42 -> 0 | CL92: x
B93: Tier 2 Paydown | E93: =-E69 -> 0 | F93: =-F69 -> 0 | G93: =-G69 -> 0 | H93: =-H69 -> 0 | I93: =-I69 -> 0 | J93: =-J69 -> 0 | K93: =-K69 -> 0 | L93: =-L69 -> 0 | ... CK93: =-CK69 -> 0 | CL93: x
B94: Tier 3 Paydown | E94: =-MIN(MAX(E90:E91)+E92+E93,E84*Tier3_CoInvestorPctCF_Case2) -> 0 | F94: =-MIN(MAX(F90:F91)+F92+F93,F84*Tier3_CoInvestorPctCF_Case2) -> 0 | G94: =-MIN(MAX(G90:G91)+G92+G93,G84*Tier3_CoInvestorPctCF_Case2) -> 0 | H94: =-MIN(MAX(H90:H91)+H92+H93,H84*Tier3_CoInvestorPctCF_Case2) -> 0 | I94: =-MIN(MAX(I90:I91)+I92+I93,I84*Tier3_CoInvestorPctCF_Case2) -> 0 | J94: =-MIN(MAX(J90:J91)+J92+J93,J84*Tier3_CoInvestorPctCF_Case2) -> 0 | K94: =-MIN(MAX(K90:K91)+K92+K93,K84*Tier3_CoInvestorPctCF_Case2) -> 0 | L94: =-MIN(MAX(L90:L91)+L92+L93,L84*Tier3_CoInvestorPctCF_Case2) -> 0 | ... CK94: =-MIN(MAX(CK90:CK91)+CK92+CK93,CK84*Tier3_CoInvestorPctCF_Case2) -> 0 | CL94: x
B95: Ending Balance | E95: =MAX(E90:E91)+E92+E93+E94 -> 4701442.2 | F95: =MAX(F90:F91)+F92+F93+F94 -> 4881233.7 | G95: =MAX(G90:G91)+G92+G93+G94 -> 5061142.9 | H95: =MAX(H90:H91)+H92+H93+H94 -> 5283509.2 | I95: =MAX(I90:I91)+I92+I93+I94 -> 5687007.2 | J95: =MAX(J90:J91)+J92+J93+J94 -> 6028973.3 | K95: =MAX(K90:K91)+K92+K93+K94 -> 6607431.7 | L95: =MAX(L90:L91)+L92+L93+L94 -> 7490850.1 | ... CK95: =MAX(CK90:CK91)+CK92+CK93+CK94 -> 0 | CL95: x
B97: Cash Flows Distributed to Co-Investor at Tier 3 | E97: =-E94 -> 0 | F97: =-F94 -> 0 | G97: =-G94 -> 0 | H97: =-H94 -> 0 | I97: =-I94 -> 0 | J97: =-J94 -> 0 | K97: =-K94 -> 0 | L97: =-L94 -> 0 | ... CK97: =-CK94 -> 0 | CL97: x
B98: Cash Flows Distributed to Sponsor at Tier 3 | E98: =E97*Tier3_SponsorPctCF_Case2/Tier3_CoInvestorPctCF_Case2 -> 0 | F98: =F97*Tier3_SponsorPctCF_Case2/Tier3_CoInvestorPctCF_Case2 -> 0 | G98: =G97*Tier3_SponsorPctCF_Case2/Tier3_CoInvestorPctCF_Case2 -> 0 | H98: =H97*Tier3_SponsorPctCF_Case2/Tier3_CoInvestorPctCF_Case2 -> 0 | I98: =I97*Tier3_SponsorPctCF_Case2/Tier3_CoInvestorPctCF_Case2 -> 0 | J98: =J97*Tier3_SponsorPctCF_Case2/Tier3_CoInvestorPctCF_Case2 -> 0 | K98: =K97*Tier3_SponsorPctCF_Case2/Tier3_CoInvestorPctCF_Case2 -> 0 | L98: =L97*Tier3_SponsorPctCF_Case2/Tier3_CoInvestorPctCF_Case2 -> 0 | ... CK98: =CK97*Tier3_SponsorPctCF_Case2/Tier3_CoInvestorPctCF_Case2 -> 0 | CL98: x
B99: Total | E99: =SUM(E97:E98) -> 0 | F99: =SUM(F97:F98) -> 0 | G99: =SUM(G97:G98) -> 0 | H99: =SUM(H97:H98) -> 0 | I99: =SUM(I97:I98) -> 0 | J99: =SUM(J97:J98) -> 0 | K99: =SUM(K97:K98) -> 0 | L99: =SUM(L97:L98) -> 0 | ... CK99: =SUM(CK97:CK98) -> 0 | CL99: x
B101: Cash Flows to Co-Investor | E101: =E73+E97 -> -3358173 | F101: =F73+F97 -> -128422.48 | G101: =G73+G97 -> -128506.57 | H101: =H73+H97 -> -158833.09 | I101: =I73+I97 -> -288212.83 | J101: =J73+J97 -> -244261.56 | K101: =K73+K97 -> -413184.55 | L101: =L73+L97 -> -631013.11 | ... CK101: =CK73+CK97 -> 0 | CL101: x
B102: Cash Flows to Sponsor | E102: =E74+E98 -> -373130.33 | F102: =F74+F98 -> -14269.165 | G102: =G74+G98 -> -14278.508 | H102: =H74+H98 -> -17648.121 | I102: =I74+I98 -> -32023.648 | J102: =J74+J98 -> -27140.174 | K102: =K74+K98 -> -45909.394 | L102: =L74+L98 -> -70112.568 | ... CK102: =CK74+CK98 -> 0 | CL102: x
B103: Total | E103: =E75+E99 -> -3731303.3 | F103: =F75+F99 -> -142691.65 | G103: =G75+G99 -> -142785.08 | H103: =H75+H99 -> -176481.21 | I103: =I75+I99 -> -320236.48 | J103: =J75+J99 -> -271401.74 | K103: =K75+K99 -> -459093.94 | L103: =L75+L99 -> -701125.68 | ... CK103: =CK75+CK99 -> 0 | CL103: x
B105: Tier 3 IRR | E105: Co-Investor | F105: Sponsor | G105: Total
B106: IRR | E106: =XIRR(E101:CK101,HoldingDates) -> 0.14922561 | F106: =XIRR(E102:CK102,HoldingDates) -> 0.47737913 | G106: =XIRR(E103:CK103,HoldingDates) -> 0.18862824
B107: CFx | E107: =-SUMIF(E101:CK101,">"&0)/SUMIF(E101:CK101,"<"&0) -> 1.4 | F107: =-SUMIF(E102:CK102,">"&0)/SUMIF(E102:CK102,"<"&0) -> 2.6 | G107: =-SUMIF(E103:CK103,">"&0)/SUMIF(E103:CK103,"<"&0) -> 1.52
B108: Net Profit | E108: =SUM(E101:CK101) -> 4474908.7 | F108: =SUM(E102:CK102) -> 1988848.3 | G108: =SUM(E103:CK103) -> 6463757.1
B110: Tier 4
B112: Cash Flows Remaining to Distribute to Tier 4 | E112: =E84-E99 -> 0 | F112: =F84-F99 -> 0 | G112: =G84-G99 -> 0 | H112: =H84-H99 -> 0 | I112: =I84-I99 -> 0 | J112: =J84-J99 -> 0 | K112: =K84-K99 -> 0 | L112: =L84-L99 -> 0 | ... CK112: =CK84-CK99 -> 0 | CL112: x
B113: =TEXT(J13,"0.0%")&" to Co-Investor" -> 40.0% to Co-Investor | E113: =E112*Tier4_CoInvestorPctCF_Case2 -> 0 | F113: =F112*Tier4_CoInvestorPctCF_Case2 -> 0 | G113: =G112*Tier4_CoInvestorPctCF_Case2 -> 0 | H113: =H112*Tier4_CoInvestorPctCF_Case2 -> 0 | I113: =I112*Tier4_CoInvestorPctCF_Case2 -> 0 | J113: =J112*Tier4_CoInvestorPctCF_Case2 -> 0 | K113: =K112*Tier4_CoInvestorPctCF_Case2 -> 0 | L113: =L112*Tier4_CoInvestorPctCF_Case2 -> 0 | ... CK113: =CK112*Tier4_CoInvestorPctCF_Case2 -> 0 | CL113: x
B114: =TEXT(K13,"0.0%")&" to Sponsor" -> 60.0% to Sponsor | E114: =E112*Tier4_SponsorPctCF_Case2 -> 0 | F114: =F112*Tier4_SponsorPctCF_Case2 -> 0 | G114: =G112*Tier4_SponsorPctCF_Case2 -> 0 | H114: =H112*Tier4_SponsorPctCF_Case2 -> 0 | I114: =I112*Tier4_SponsorPctCF_Case2 -> 0 | J114: =J112*Tier4_SponsorPctCF_Case2 -> 0 | K114: =K112*Tier4_SponsorPctCF_Case2 -> 0 | L114: =L112*Tier4_SponsorPctCF_Case2 -> 0 | ... CK114: =CK112*Tier4_SponsorPctCF_Case2 -> 0 | CL114: x
B116: Cash Flows Distributed to Co-Investor at Tier 4 | E116: =E113 -> 0 | F116: =F113 -> 0 | G116: =G113 -> 0 | H116: =H113 -> 0 | I116: =I113 -> 0 | J116: =J113 -> 0 | K116: =K113 -> 0 | L116: =L113 -> 0 | ... CK116: =CK113 -> 0 | CL116: x
B117: Cash Flows Distributed to Sponsor at Tier 4 | E117: =E114 -> 0 | F117: =F114 -> 0 | G117: =G114 -> 0 | H117: =H114 -> 0 | I117: =I114 -> 0 | J117: =J114 -> 0 | K117: =K114 -> 0 | L117: =L114 -> 0 | ... CK117: =CK114 -> 0 | CL117: x
B118: Total | E118: =SUM(E116:E117) -> 0 | F118: =SUM(F116:F117) -> 0 | G118: =SUM(G116:G117) -> 0 | H118: =SUM(H116:H117) -> 0 | I118: =SUM(I116:I117) -> 0 | J118: =SUM(J116:J117) -> 0 | K118: =SUM(K116:K117) -> 0 | L118: =SUM(L116:L117) -> 0 | ... CK118: =SUM(CK116:CK117) -> 0 | CL118: x
B120: Cash Flows to Co-Investor | E120: =E101+E116 -> -3358173 | F120: =F101+F116 -> -128422.48 | G120: =G101+G116 -> -128506.57 | H120: =H101+H116 -> -158833.09 | I120: =I101+I116 -> -288212.83 | J120: =J101+J116 -> -244261.56 | K120: =K101+K116 -> -413184.55 | L120: =L101+L116 -> -631013.11 | ... CK120: =CK101+CK116 -> 0 | CL120: x
B121: Cash Flows to Sponsor | E121: =E102+E117 -> -373130.33 | F121: =F102+F117 -> -14269.165 | G121: =G102+G117 -> -14278.508 | H121: =H102+H117 -> -17648.121 | I121: =I102+I117 -> -32023.648 | J121: =J102+J117 -> -27140.174 | K121: =K102+K117 -> -45909.394 | L121: =L102+L117 -> -70112.568 | ... CK121: =CK102+CK117 -> 0 | CL121: x
B122: Total | E122: =E103+E118 -> -3731303.3 | F122: =F103+F118 -> -142691.65 | G122: =G103+G118 -> -142785.08 | H122: =H103+H118 -> -176481.21 | I122: =I103+I118 -> -320236.48 | J122: =J103+J118 -> -271401.74 | K122: =K103+K118 -> -459093.94 | L122: =L103+L118 -> -701125.68 | ... CK122: =CK103+CK118 -> 0 | CL122: x
B124: Tier 4 IRR | E124: Co-Investor | F124: Sponsor | G124: Total
B125: IRR | E125: =XIRR(E120:CK120,HoldingDates) -> 0.25566822 | F125: =XIRR(E121:CK121,HoldingDates) -> 0.84934205 | G125: =XIRR(E122:CK122,HoldingDates) -> 0.36700209
B126: CFx | E126: =-SUMIF(E120:CK120,">"&0)/SUMIF(E120:CK120,"<"&0) -> 1.999158 | F126: =-SUMIF(E121:CK121,">"&0)/SUMIF(E121:CK121,"<"&0) -> 10.688634 | G126: =-SUMIF(E122:CK122,">"&0)/SUMIF(E122:CK122,"<"&0) -> 2.8681056
B127: Net Profit | E127: =SUM(E120:CK120) -> 11177853 | F127: =SUM(E121:CK121) -> 12043264 | G127: =SUM(E122:CK122) -> 23221117
B129: Adjustment for Fees to Sponsor
B131: Cash Flows to Sponsor | E131: =E121 -> -373130.33 | F131: =F121 -> -14269.165 | G131: =G121 -> -14278.508 | H131: =H121 -> -17648.121 | I131: =I121 -> -32023.648 | J131: =J121 -> -27140.174 | K131: =K121 -> -45909.394 | L131: =L121 -> -70112.568 | ... CK131: =CK121 -> 0 | CL131: x
B132: Adjustment for Fees | E132: =SUM('Q1 - CAP Acct. 2'!I115:I117) -> -52452.567 | F132: =SUM('Q1 - CAP Acct. 2'!J115:J117) -> -2545.9976 | G132: =SUM('Q1 - CAP Acct. 2'!K115:K117) -> -2639.428 | H132: =SUM('Q1 - CAP Acct. 2'!L115:L117) -> -2755.2453 | I132: =SUM('Q1 - CAP Acct. 2'!M115:M117) -> -2966.7585 | J132: =SUM('Q1 - CAP Acct. 2'!N115:N117) -> -3145.5959 | K132: =SUM('Q1 - CAP Acct. 2'!O115:O117) -> -3449.359 | L132: =SUM('Q1 - CAP Acct. 2'!P115:P117) -> -3914.1667 | ... CK132: =SUM('Q1 - CAP Acct. 2'!CO115:CO117) -> 0 | CL132: x
B133: Final Cash Flows to Sponsor | E133: =E131-E132 -> -320677.77 | F133: =F131-F132 -> -11723.167 | G133: =G131-G132 -> -11639.08 | H133: =H131-H132 -> -14892.876 | I133: =I131-I132 -> -29056.89 | J133: =J131-J132 -> -23994.578 | K133: =K131-K132 -> -42460.035 | L133: =L131-L132 -> -66198.402 | ... CK133: =CK131-CK132 -> 0 | CL133: x
B135: Adjusted Sponsor IRR | E135: =IFERROR(XIRR(E133:CK133,HoldingDates,-0.1),XIRR(E133:CK133,HoldingDates)) -> 0.94643975
B136: CFx | E136: =-SUMIF(E133:CK133,">"&0)/SUMIF(E133:CK133,"<"&0) -> 12.227224
...
